Workbook

Sheet Anleitung
A1: SparteNet – Gateway-Standorte, Investition und Buchungsquote der Kleingartenanlagen
A2: Grundlage: Kleingartenentwicklungskonzept 2040, Anlage 1 (Steckbriefe), Anlage 2 (Karte) – Stadt Brandenburg an der Havel, März/April 2026
A4: So ist das Netz aufgebaut
A5: • Ein Gateway versorgt 55 Parzellen (Annahme „Parzellen je Gateway“). An einem Standort stehen so viele Gateways, wie die zugeordneten Sparten brauchen.
A6: • Die Gateways werden der Reihe nach gefüllt: hat die erste Sparte 86 Parzellen, belegt sie Gateway 1 ganz und 31 Plätze von Gateway 2 – die nächste Sparte nutzt die restlichen 24 Plätze, dann folgt Gateway 3.
A7: • Alle Gateways eines Standorts teilen sich einen Internet-Anschluss. Erst wenn der Bedarf größer ist als der Anschluss, wird ein zweiter gerechnet.
A8: • Sparten ohne eigene Gateways werden per Glasfaser von Sparte zu Sparte angebunden (Spalte „Zuleitung von“). Kein Richtfunk, keine Tiefbaukosten (Annahme „Tiefbau €/m“ = 0).
A10: Was Sie frei festlegen (Blatt „Anlagen“, gelbe Spalten)
A11: • „Gateway-Standort“: Nr. der Sparte, in der die Gateways stehen. Eigene Nr. = Sparte ist selbst Standort. Leer = Vorschlag (wenn in „Annahmen“ eingeschaltet), sonst eigener Standort.
A12: • „Zuleitung von“: Nr. der Sparte, von der die Glasfaser kommt (muss am selben Standort hängen). Leer = direkt vom Standort.
A13: • „Reihenfolge“: in welcher Reihenfolge die Sparten die Gateways eines Standorts füllen (1, 2, 3 …). Leer = zuerst die Standort-Sparte selbst, dann die übrigen in Zeilenfolge. Eingetragene Nummern kommen vor allen leeren.
A14: • „Quote manuell“: feste Buchungsquote nur für diese Sparte (z. B. 70 %).
... A30: • Preise netto; bei Kleinunternehmer rechnet die Mappe brutto (keine Vorsteuer).

Sheet Übersicht
A1: Übersicht – Planung gegenüber „jede Sparte eigenständig“
A2: Alle Werte berechnet · Planung in „Anlagen“ (gelbe Spalten) · Regeln und Quote in „Annahmen“
A4: Kennzahl | B4: jede Sparte eigenständig | C4: Ihre Planung | D4: Unterschied
A5: NETZ
A6: Gateway-Standorte (Schränke) | B6: =COUNT(Anlagen!A5:A92) -> 88 | C6: =Standorte!C93 -> 16 | D6: =C6-B6 -> -72
A7: Gateways | B7: =Investition!P93 -> 133 | C7: =Standorte!E93 -> 96 | D7: =C7-B7 -> -37
A8: Internet-Anschlüsse | B8: =SUMPRODUCT(--(Anlagen!A5:A92>0)) -> 88 | C8: =Standorte!K93 -> 23 | D8: =C8-B8 -> -65
A9: Glasfaser-Zuleitungen zwischen Sparten (m) | B9: 0 | C9: =Netz!G93 -> 56896.649 | D9: =C9-B9 -> 56896.649
A10: Prüfungen mit Fehler | C10: =COUNTIF(Netz!P5:P92,"Fehler*")+COUNTIF(Netz!Y5:Y92,"Fehler*") -> 0
A11: KOSTEN
A12: Investition | B12: =Investition!Q93 -> 1812369.8 | C12: =Investition!N93+Standorte!N93 -> 1768027.3 | D12: =C12-B12 -> -44342.525
A13: Laufende Kosten / Jahr | B13: =Investition!R93 -> 183146.94 | C13: =Investition!O93+Standorte!O93 -> 104246.52 | D13: =C13-B13 -> -78900.426
A14: Kosten im Betrachtungszeitraum (Investition + laufend × Jahre) | B14: =B12+B13*Jahre -> 2728104.5 | C14: =C12+C13*Jahre -> 2289259.9 | D14: =C14-B14 -> -438844.65
A15: BUCHUNG UND ERGEBNIS (Ihre Planung)
A16: Parzellen | C16: =SUM(Anlagen!F5:F92) -> 5017
A17: Leerstandsquote heute | C17: =Buchungsquote!E93 -> 0.034084114
A18: Leerstandsquote in 5 Jahren (Prognose) | C18: =Buchungsquote!Q93 -> 0.079125515
A19: Buchungsquote (gewählt) | C19: =Buchungsquote!T93 -> 0.56105513
A20: Kunden | C20: =Buchungsquote!V93 -> 2814.8136
A21: Umsatz / Jahr | C21: =Ergebnis!H93 -> 337777.63
A22: Deckungsbeitrag / Jahr (vor zentralen Firmenkosten) | C22: =Ergebnis!L93 -> 223397.79
A23: Amortisation (Jahre) | C23: =Ergebnis!M93 -> 7.9142561
A24: Investition je Kunde | C24: =Ergebnis!N93 -> 628.11522
A26: Buchungsquote-Modus laut Annahmen: | C26: =IF(Quote_Modus=2,"feste Quote "&TEXT(Quote_fest,"0%"),IF(Szenario=2,"aus Alter und Leerstand, in 5 Jahren","aus Alter und Leerstand, heute")) -> aus Alter und Leerstand, heute

Sheet Annahmen
A1: Annahmen
A2: Gelbe Felder ändern – alle Blätter rechnen neu.
A4: Annahme | C4: Wert | D4: Einheit / Quelle
A6: NETZ-REGELN
A7: Parzellen je Gateway | C7: 55 | D7: Ihre Vorgabe
A8: Gateways je Standort (Richtwert für die Prüfung) | C8: 10 | D8: darüber Warnung
A9: Standort-Vorschlag verwenden, wo keine eigene Wahl (1 = ja, 0 = jede Sparte eigenständig) | C9: 1 | D9: Vorschlag: Glasfaser zur nächsten Sparte bis 1,5 km, max. 10 Gateways
A10: Umwegfaktor Glasfaser (Trasse statt Luftlinie) | C10: 1.3
A11: Kapazität eines Internet-Anschlusses | C11: 1000 | D11: Mbit/s
A12: Überbuchungsfaktor | C12: 8 | D12: 1:x, wie Kalkulation
A13: Ø gebuchte Bandbreite je Kunde | C13: 30 | D13: Mbit/s
A14: Betrachtungszeitraum für Vergleiche | C14: 5 | D14: Jahre
A16: PREISE (netto) – aus Kalkulation_Sparten_WLAN.xlsx, Blatt „Preise“
A17: Gateway (UniFi Cloud Gateway Fiber) | C17: 250 | D17: Stück · UI Store
A18: UniFi Switch Aggregation (8× SFP+) | C18: 240 | D18: Stück · je 8 Anschlüsse
A19: DAC-Kabel 10G (je Gateway) | C19: 20 | D19: Stück
A20: Außenschrank Glasfaser (Standort) | C20: 1500 | D20: Stück · Schätzung
A21: USV + Überspannungsschutz Standort | C21: 250 | D21: Stück · Schätzung
A22: SFP 1G Singlemode | C22: 21.9 | D22: Stück · fiber24
A23: UniFi Switch Flex 2.5G PoE | C23: 179 | D23: Stück · UI Store
A24: Netzteil Flex | C24: 70 | D24: Stück
A25: Hutschienen-Halter | C25: 8.5 | D25: Stück
A26: Lüfter mit Thermostat | C26: 45 | D26: Stück · Schätzung
A27: Mini-Spleißbox LC | C27: 32.9 | D27: Stück · fiber24
A28: Strom-Säule (Leergehäuse) | C28: 300 | D28: Stück · Schätzung
... A39: Montage je Glasfaser-Zuleitung (Spleißen, Einmessen) | C39: 150 | D39: je Zuleitung · Schätzung
A41: STEUER
A42: Kleinunternehmer (1 = ja, 0 = Regelbesteuerung) | C42: 1 | D42: wie Kalkulation
A43: Umsatzsteuersatz | C43: 0.19
A44: Faktor Einkauf (ohne Vorsteuerabzug = brutto) | C44: =IF(KU=1,1+USt,1) -> 1.19 | D44: berechnet
A46: MENGEN IN DER SPARTE (kalibriert an KGV Buchenweg: 86 Parzellen, 49.614 m² → 24 APs, 11 Masten, 6 mit Technik)
A47: Parzellen je Access Point | C47: 3.6 | D47: Buchenweg: 86 ÷ 24
A48: Access Points je Mast | C48: 2.2 | D48: Buchenweg: 24 ÷ 11
A49: Anteil Masten mit Technik (Switch in der Säule) | C49: 0.5 | D49: Buchenweg: 6 von 11
A50: Leitungsweg in der Sparte (m = Faktor × √Fläche m²) | C50: 2.806 | D50: Buchenweg: 625 m ÷ √49.614
A51: Glasfaser m je m Leitungsweg | C51: 1.66 | D51: Buchenweg: 1.039 ÷ 625
A52: Kupferkabel m je m Leitungsweg | C52: 1.06 | D52: Buchenweg: 663 ÷ 625
A53: Kupferkabel (2 Überspannungsschutz) je AP | C53: 0.42 | D53: Buchenweg: 10 ÷ 24
A54: Anschlüsse je Aggregation-Switch | C54: 8 | D54: Gateways + Glasfaserstrecken
A56: LAUFENDE KOSTEN UND ERLÖS
A57: Internet-Anschluss je Monat | C57: 75 | D57: € netto · Kalkulation
A58: Strom Standort (Schrank, Switch) je Jahr | C58: 80 | D58: € · Kalkulation
A59: Strom je Gateway und Jahr | C59: 25 | D59: € · Schätzung (ca. 10 W)
A60: Strom je Mast mit Technik und Jahr | C60: 50 | D60: € · Kalkulation
A61: Wartung/Ersatzteile je Jahr (Anteil der Investition) | C61: 0.03 | D61: Kalkulation
A62: Zahlungsabwicklung (Anteil vom Umsatz) | C62: 0.03 | D62: Kalkulation
A63: Ø Tarifpreis je Kunde und Jahr | C63: 120 | D63: € · Basis-Tarif
A65: BUCHUNGSQUOTE – einstellbar
A66: Modus: 1 = aus Alter und Leerstand, 2 = feste Quote für alle | C66: 1 | D66: „Quote manuell“ je Sparte gilt immer vorrangig
A67: Feste Buchungsquote (Modus 2) | C67: 0.6 | D67: Anteil aller Parzellen
A68: Modus 1 rechnet mit: 1 = heute, 2 = in 5 Jahren | C68: 1
A69: Buchungsneigung Pächter bis 30 Jahre | C69: 0.8 | D69: Annahme
A70: Buchungsneigung Pächter 30–50 Jahre | C70: 0.75 | D70: Annahme
A71: Buchungsneigung Pächter 50–70 Jahre | C71: 0.6 | D71: Annahme
A72: Buchungsneigung Pächter 70–90 Jahre | C72: 0.35 | D72: Annahme · Destatis 2025: 65–74 J. ca. 10 % offline
A73: Buchungsneigung Pächter ab 90 Jahre | C73: 0.1 | D73: Annahme
A74: Faktor Entwicklungsstufe A | C74: 1 | D74: Stabil
A75: Faktor Entwicklungsstufe B | C75: 1 | D75: Beobachtung
A76: Faktor Entwicklungsstufe C | C76: 0.9 | D76: Qualifizierung – Unsicherheit
A77: Faktor Entwicklungsstufe D | C77: 0.75 | D77: Planungskonflikt – Teilflächen fallen weg
A79: PROGNOSE IN 5 JAHREN (Modus 1, Szenario 2)
A80: Pachtaufgabe in 5 Jahren, Pächter bis 30 Jahre | C80: 0.05 | D80: Annahme
A81: Pachtaufgabe in 5 Jahren, Pächter 30–50 Jahre | C81: 0.05 | D81: Annahme
A82: Pachtaufgabe in 5 Jahren, Pächter 50–70 Jahre | C82: 0.1 | D82: Annahme
A83: Pachtaufgabe in 5 Jahren, Pächter 70–90 Jahre | C83: 0.3 | D83: Annahme
A84: Pachtaufgabe in 5 Jahren, Pächter ab 90 Jahre | C84: 0.6 | D84: Annahme
A85: Nachbesetzung frei werdender Parzellen (Grundwert) | C85: 0.7 | D85: Annahme
A86: Abschlag je Prozentpunkt heutiger Leerstand | C86: 2 | D86: 10 % Leerstand → 70 % − 20 % = 50 %
A87: Buchungsneigung neuer Pächter | C87: =Neig_2 -> 0.75 | D87: wie 30–50 Jahre

Sheet Anlagen
A1: Anlagen – Daten aus Steckbriefen und Karte, Ihre Planung in den gelben Spalten
A2: Blau = Daten aus den Unterlagen (änderbar) · Gelb = Gateway-Standort, Zuleitung, Reihenfolge, Quote und genauere Mengen
A4: Nr. | B4: Kleingartenanlage | C4: Adresse | D4: Entwicklungsstufe | E4: Eigentum | F4: Parzellen | G4: Leerstand (Parzellen) | H4: Fläche m² | I4: Pächter bis 30 | J4: 30–50 | K4: 50–70 | L4: 70–90 | M4: ab 90 | N4: Lage x (km) | O4: Lage y (km) | P4: Parzellen lt. Konzept-Tabelle | Q4: Standort (Vorschlag) | R4: Zuleitung (Vorschlag) | S4: Gateway-Standort (eigene Wahl) | T4: Zuleitung von (eigene Wahl) | U4: Reihenfolge | V4: Entfernung manuell (m) | W4: Quote manuell | X4: APs manuell | Y4: Masten manuell | Z4: Leitungsweg m manuell | AA4: Kürzel | AB4: VLAN-Block (eigene Wahl)
A5: 1 | B5: 1. März | C5: Willibald-Alexis-Straße 38 | D5: B – Beobachtung | E5: Stadt BRB | F5: 30 | G5: 2 | H5: 8547 | I5: 0.4 | J5: 24.3 | K5: 10.8 | L5: 4.1 | M5: 0 | N5: 9.22 | O5: 7.78 | P5: 30 | Q5: 33 | R5: 6 | AA5: MAERZ
A6: 2 | B6: Abendfrieden | C6: Ziesarer Landstraße 24 | D6: C – Qualifizierung | E6: Stadt / Kirche | F6: 75 | G6: 4 | H6: 34727 | I6: 0 | J6: 36.8 | K6: 33.3 | L6: 12.7 | M6: 0 | N6: 9.12 | O6: 2.09 | P6: 75 | Q6: 41 | R6: 20 | AA6: ABFRI
A7: 3 | B7: Abendrot | C7: Am Gallberg 3 | D7: A – Stabil | E7: Stadt / privat | F7: 137 | G7: 0 | H7: 64614 | I7: 1.6 | J7: 42.5 | K7: 105.7 | L7: 51.9 | M7: 0 | N7: 9.64 | O7: 6.32 | P7: 137 | Q7: 30 | R7: 30 | AA7: ABROT
A8: 4 | B8: Abendruh | C8: Mahlerstraße 21 | D8: A – Stabil | E8: Stadt BRB | F8: 142 | G8: 0 | H8: 75974 | I8: 2.8 | J8: 46.9 | K8: 71.4 | L8: 52.9 | M8: 2.8 | N8: 8.01 | O8: 7.51 | P8: 142 | Q8: 30 | R8: 30 | AA8: ABRUH
A9: 5 | B9: Abendsonne | C9: Bayernstraße 9a | D9: A – Stabil | E9: Privat | F9: 67 | G9: 13 | H9: 17033 | I9: 1.7 | J9: 21.5 | K9: 30.3 | L9: 8.1 | M9: 0 | N9: 8.03 | O9: 5.22 | P9: 67 | Q9: 23 | R9: 24 | AA9: ABSON
A10: 6 | B10: Altstadt Forst | C10: Rathenower Landstraße 3 | D10: A – Stabil | E10: Stadt / privat | F10: 88 | G10: 0 | H10: 46549 | I10: 2.8 | J10: 46.9 | K10: 71.4 | L10: 52.9 | M10: 2.8 | N10: 8.52 | O10: 8.34 | P10: 88 | Q10: 33 | R10: 33 | AA10: ALTFO
A11: 7 | B11: Am Beetzseeufer | C11: Beetzseeufer 8 | D11: A – Stabil | E11: Stadt BRB | F11: 77 | G11: 0 | H11: 38607 | I11: 0.1 | J11: 44.9 | K11: 59.7 | L11: 11.7 | M11: 0 | N11: 11.55 | O11: 6.05 | P11: 76 | Q11: 49 | R11: 88 | AA11: BEETZ
A12: 8 | B12: Am Büttelhandfassgraben | C12: Am Bittelhandfassgraben 14 | D12: B – Beobachtung | E12: Privat | F12: 5 | G12: 0 | H12: 2345 | I12: 1.1 | J12: 0 | K12: 1.7 | L12: 0 | M12: 0 | N12: 10.02 | O12: 3.54 | P12: 5 | Q12: 49 | R12: 50 | AA12: BUETT
A13: 9 | B13: Am Eichenweg | C13: Ziesarer Landstraße 1 | D13: C – Qualifizierung | E13: Stadt / Kirche | F13: 54 | G13: 2 | H13: 33743 | I13: 0.9 | J13: 33 | K13: 22.2 | L13: 8.9 | M13: 0 | N13: 9.1 | O13: 2.38 | P13: 54 | Q13: 17 | R13: 17 | AA13: EICHW
A14: 10 | B14: Am Jakobsgraben | C14: Otto-Gartz-Straße 10a | D14: D – Planungskonflikt | E14: Stadt BRB | F14: 41 | G14: 0 | H14: 21966 | I14: 0.4 | J14: 17.5 | K14: 22.6 | L14: 9.6 | M14: 0 | N14: 10.92 | O14: 3.53 | P14: 41 | Q14: 17 | R14: 27 | AA14: JAKGR
A15: 11 | B15: Am Schafdamm | C15: Schafdamm 3 | D15: C – Qualifizierung | E15: Stadt / privat | F15: 10 | G15: 0 | H15: 6123 | I15: 0 | J15: 1.6 | K15: 5.1 | L15: 5 | M15: 0 | N15: 8.11 | O15: 9.91 | P15: 10 | Q15: 33 | R15: 12 | AA15: SCHAF
A16: 12 | B16: Am Schlangenpfad | C16: Schlangenpfad 21 | D16: C – Qualifizierung | E16: Stadt BRB | F16: 19 | G16: 0 | H16: 11021 | I16: 0 | J16: 2.9 | K16: 8.6 | L16: 14.6 | M16: 0 | N16: 8.03 | O16: 9.59 | P16: 19 | Q16: 33 | R16: 13 | AA16: SCHLA
... A19: 15 | B19: Bergeshöh | C19: Triglafweg 20 | D19: A – Stabil | E19: Stadt BRB | F19: 14 | G19: 1 | H19: 7551 | I19: 0 | J19: 12.6 | K19: 3.3 | L19: 3.2 | M19: 0 | N19: 10.6 | O19: 5.33 | P19: 14 | Q19: 28 | R19: 83 | AA19: BERGH
A20: 16 | B20: Bergfrieden | C20: Wusterwitzer Str. 71 | D20: C – Qualifizierung | E20: Stadt BRB | F20: 130 | G20: 17 | H20: 55513 | I20: 5 | J20: 38.9 | K20: 45.7 | L20: 47 | M20: 0.1 | N20: 0.27 | O20: 3.02 | P20: 139 | Q20: 16 | AA20: BERGF
A21: 17 | B21: Birkenwäldchen | C21: Wittstocker Gäßchen 36 | D21: B – Beobachtung | E21: Stadt / privat | F21: 56 | G21: 3 | H21: 30065 | I21: 0 | J21: 16.8 | K21: 54.2 | L21: 3.3 | M21: 0 | N21: 9.78 | O21: 1.18 | P21: 56 | Q21: 17 | AA21: BIRKE
A22: 18 | B22: BKV Pfefferland | C22: Pfefferlander Weg 11 | D22: B – Beobachtung | E22: Privat | F22: 64 | G22: 0 | H22: 32712 | I22: 0.3 | J22: 28.5 | K22: 44.4 | L22: 14.5 | M22: 0 | N22: 7.78 | O22: 1.54 | P22: 64 | Q22: 73 | R22: 73 | AA22: PFEFF
A23: 19 | B23: Brielower Dreieck | C23: Am Industriegelande 1 | D23: A – Stabil | E23: Stadt BRB | F23: 35 | G23: 0 | H23: 15539 | I23: 1.3 | J23: 4.4 | K23: 30.4 | L23: 6.9 | M23: 0 | N23: 10.78 | O23: 6.72 | P23: 35 | Q23: 81 | R23: 81 | AA23: BRIDR
A24: 20 | B24: Buchenweg | C24: Buchenweg 77 | D24: B – Beobachtung | E24: Stadt BRB | F24: 86 | G24: 1 | H24: 49614 | I24: 5.4 | J24: 44.2 | K24: 38.1 | L24: 20.6 | M24: 0 | N24: 9.3 | O24: 1.65 | P24: 86 | Q24: 41 | R24: 41 | AA24: BW
A25: 21 | B25: Butterlake | C25: Brielower Aue 30 | D25: B – Beobachtung | E25: Stadt / privat | F25: 75 | G25: 1 | H25: 34343 | I25: 0 | J25: 37.3 | K25: 42.3 | L25: 32.1 | M25: 0.3 | N25: 8.22 | O25: 9.04 | P25: 75 | Q25: 33 | R25: 33 | AA25: BUTTL
A26: 22 | B26: Eichhorstweg | C26: Eichhorstweg 15 | D26: B – Beobachtung | E26: Privat | F26: 38 | G26: 1 | H26: 20436 | I26: 1.2 | J26: 13.9 | K26: 21.9 | L26: 11.6 | M26: 0 | N26: 9.53 | O26: 0.95 | P26: 38 | Q26: 22 | AA26: EICHH
A27: 23 | B27: Eigener Fleiß | C27: Hannoversche Str. 38 | D27: A – Stabil | E27: Stadt BRB | F27: 123 | G27: 0 | H27: 63177 | I27: 6.1 | J27: 44.7 | K27: 81.9 | L27: 49.7 | M27: 0 | N27: 7.81 | O27: 4.85 | P27: 123 | Q27: 23 | AA27: FLEIS
A28: 24 | B28: Einheit | C28: Thuringer Str. 18 | D28: A – Stabil | E28: Stadt BRB | F28: 99 | G28: 1 | H28: 49589 | I28: 4.8 | J28: 45.8 | K28: 49.2 | L28: 21.1 | M28: 0 | N28: 8.32 | O28: 4.92 | P28: 99 | Q28: 23 | R28: 23 | AA28: EINH
A29: 25 | B29: Einigkeit | C29: Klingenbergstr. 2b | D29: A – Stabil | E29: Stadt BRB | F29: 14 | G29: 0 | H29: 4670 | I29: 0.5 | J29: 3.2 | K29: 8.8 | L29: 1.2 | M29: 0 | N29: 9.44 | O29: 4.39 | P29: 14 | Q29: 56 | R29: 56 | AA29: EINIG
A30: 26 | B30: Eintracht I | C30: Franz-Ziegler-Str. 29b | D30: A – Stabil | E30: Stadt / privat | F30: 32 | G30: 1 | H30: 9606 | I30: 0.2 | J30: 7.9 | K30: 18.3 | L30: 4.2 | M30: 0 | N30: 10.46 | O30: 3.81 | P30: 32 | Q30: 23 | R30: 55 | AA30: EINT1
A31: 27 | B31: Eintracht II | C31: Gottiner Landstr. 17 | D31: A – Stabil | E31: k. A. | F31: 42 | G31: 2 | H31: 15820 | I31: 0 | J31: 24 | K31: 26.7 | L31: 8.7 | M31: 0 | N31: 10.2 | O31: 2.67 | P31: 42 | Q31: 17 | R31: 9 | AA31: EINT2
A32: 28 | B32: Erdenglück | C32: Johannisburger Anger 26 | D32: B – Beobachtung | E32: Stadt / privat | F32: 99 | G32: 2 | H32: 40185 | I32: 0.8 | J32: 39.9 | K32: 46.1 | L32: 42.3 | M32: 0 | N32: 6.72 | O32: 7.19 | P32: 96 | Q32: 28 | AA32: ERDGL
A33: 29 | B33: Erntesegen | C33: Brahmsstr. 12b | D33: A – Stabil | E33: Stadt / privat | F33: 92 | G33: 1 | H33: 43349 | I33: 4.4 | J33: 43.6 | K33: 42.2 | L33: 19.8 | M33: 0.4 | N33: 7.97 | O33: 6.74 | P33: 91 | Q33: 28 | R33: 28 | AA33: ERNTE
A34: 30 | B34: Feierabend | C34: Beethovenstr. 31 | D34: A – Stabil | E34: Stadt BRB | F34: 190 | G34: 5 | H34: 99039 | I34: 7.9 | J34: 61.8 | K34: 79.2 | L34: 81.3 | M34: 1.1 | N34: 8.64 | O34: 6.96 | P34: 190 | Q34: 30 | AA34: FEIER
A35: 31 | B35: Feldstraße | C35: Feldstraße 1c | D35: C – Qualifizierung | E35: Stadt BRB | F35: 68 | G35: 4 | H35: 35041 | I35: 1.1 | J35: 24.4 | K35: 32.2 | L35: 21.3 | M35: 0 | N35: 9.65 | O35: 2.54 | P35: 68 | Q35: 41 | R35: 60 | AA35: FELD
A36: 32 | B36: Finkenhain | C36: Mendelssohnstr. 13 | D36: C – Qualifizierung | E36: Stadt BRB | F36: 8 | G36: 0 | H36: 5992 | I36: 0 | J36: 0 | K36: 5.7 | L36: 1.5 | M36: 0 | N36: 7.35 | O36: 7.18 | P36: 8 | Q36: 28 | R36: 82 | AA36: FINK
A37: 33 | B37: Fohrder Landstraße | C37: Brielower Aue 33 | D37: A – Stabil | E37: Stadt / privat | F37: 127 | G37: 1 | H37: 71463 | I37: 1.5 | J37: 54 | K37: 51.7 | L37: 49.4 | M37: 1.6 | N37: 8.35 | O37: 8.76 | P37: 127 | Q37: 33 | AA37: FOHRD
A38: 34 | B38: Freiheit | C38: Feldstr. 1b | D38: C – Qualifizierung | E38: Stadt BRB | F38: 55 | G38: 6 | H38: 28864 | I38: 0 | J38: 30.6 | K38: 18.3 | L38: 6.9 | M38: 0 | N38: 9.86 | O38: 2.55 | P38: 55 | Q38: 49 | R38: 64 | AA38: FREIH
A39: 35 | B39: Freizeit | C39: Ziesarer Landstr. 64 | D39: B – Beobachtung | E39: Stadt / privat | F39: 63 | G39: 1 | H39: 32286 | I39: 1.7 | J39: 20.7 | K39: 28.8 | L39: 20.9 | M39: 0 | N39: 8.93 | O39: 1.91 | P39: 63 | Q39: 41 | R39: 2 | AA39: FREIZ
A40: 36 | B40: Friedland | C40: Klingenbergstr. 19 | D40: A – Stabil | E40: k. A. | F40: 64 | G40: 1 | H40: 29654 | I40: 0 | J40: 30.9 | K40: 24.3 | L40: 23.3 | M40: 0 | N40: 8.93 | O40: 4.49 | P40: 64 | Q40: 23 | R40: 24 | AA40: FRIED
A41: 37 | B41: Frisch Auf | C41: Klingenbergstr. 4 | D41: B – Beobachtung | E41: Stadt BRB | F41: 19 | G41: 1 | H41: 9927 | I41: 0 | J41: 3.7 | K41: 12.4 | L41: 4.9 | M41: 0 | N41: 9.24 | O41: 4.36 | P41: 19 | Q41: 56 | R41: 56 | AA41: FRISA
A42: 38 | B42: Frohsinn | C42: Ziesarer Landstr. 3 | D42: C – Qualifizierung | E42: Stadt / Kirche | F42: 54 | G42: 3 | H42: 29762 | I42: 0.4 | J42: 23.7 | K42: 33.5 | L42: 12.4 | M42: 0 | N42: 8.62 | O42: 1.78 | P42: 54 | Q42: 17 | R42: 9 | AA42: FROH
A43: 39 | B43: Gartenfreunde Brielower Aue | C43: Brielower Aue 47 | D43: B – Beobachtung | E43: Stadt / privat | F43: 69 | G43: 1 | H43: 39053 | I43: 2.4 | J43: 27.5 | K43: 27.7 | L43: 14.1 | M43: 0 | N43: 9.37 | O43: 9.04 | P43: 69 | Q43: 33 | R43: 33 | AA43: BRAUE
A44: 40 | B44: Glück Auf | C44: Ziesarer Landstr. 117 | D44: B – Beobachtung | E44: Stadt BRB | F44: 34 | G44: 2 | H44: 19944 | I44: 0.1 | J44: 12.7 | K44: 13.4 | L44: 7.1 | M44: 0 | N44: 8.31 | O44: 1.36 | P44: 34 | Q44: 73 | R44: 73 | AA44: GLAUF
A45: 41 | B45: Glück im Winkel | C45: Eichhorstweg 3 | D45: B – Beobachtung | E45: Stadt BRB | F45: 139 | G45: 3 | H45: 96483 | I45: 8.4 | J45: 51.3 | K45: 60.8 | L45: 40.7 | M45: 0 | N45: 9.85 | O45: 1.48 | P45: 139 | Q45: 41 | AA45: GLWIN
A46: 42 | B46: Grüne Ecke | C46: Pfefferlander Weg 48 | D46: A – Stabil | E46: Stadt / privat | F46: 50 | G46: 0 | H46: 30158 | I46: 0 | J46: 14.6 | K46: 38.7 | L46: 16.7 | M46: 0 | N46: 8.33 | O46: 1.88 | P46: 50 | Q46: 17 | R46: 38 | AA46: GRECK
A47: 43 | B47: Grüner Kranz | C47: GutsMuthsstr. 21a | D47: A – Stabil | E47: Stadt BRB | F47: 70 | G47: 2 | H47: 31984 | I47: 4.5 | J47: 27.8 | K47: 30.1 | L47: 12.1 | M47: 0 | N47: 11.18 | O47: 6.17 | P47: 70 | Q47: 49 | R47: 7 | AA47: GRKRZ
A48: 44 | B48: Grünes Heim | C48: Ferdinand-Lassalle-Str. 12 | D48: B – Beobachtung | E48: Kirche | F48: 23 | G48: 1 | H48: 9696 | I48: 0.4 | J48: 10.4 | K48: 10.4 | L48: 0.1 | M48: 0 | N48: 9.78 | O48: 4.5 | P48: 23 | Q48: 56 | R48: 56 | AA48: GRHEI
A49: 45 | B49: Gut Wetter | C49: Fohrder Landstr. 9 | D49: A – Stabil | E49: Stadt BRB | F49: 17 | G49: 0 | H49: 8997 | I49: 0 | J49: 4.8 | K49: 6.7 | L49: 4 | M49: 0 | N49: 10.01 | O49: 6.78 | P49: 17 | Q49: 30 | R49: 3 | AA49: GUTWE
A50: 46 | B50: Handwerker | C50: Planeweg 1b | D50: C – Qualifizierung | E50: Kirche | F50: 36 | G50: 1 | H50: 15873 | I50: 2.6 | J50: 15.3 | K50: 20 | L50: 12 | M50: 0 | N50: 9.22 | O50: 2.78 | P50: 36 | Q50: 23 | R50: 79 | AA50: HANDW
A51: 47 | B51: Harmonie | C51: August-Bebel-Str. 19 | D51: D – Planungskonflikt | E51: Stadt BRB | F51: 60 | G51: 20 | H51: 22450 | I51: 2 | J51: 10.4 | K51: 17.5 | L51: 12 | M51: 0 | N51: 9.6 | O51: 5.81 | P51: 62 | Q51: 30 | R51: 3 | AA51: HARMO
A52: 48 | B52: Heidekrug | C52: Plauer Landstr. 42 | D52: B – Beobachtung | E52: Stadt BRB | F52: 34 | G52: 0 | H52: 14955 | I52: 2.1 | J52: 6.7 | K52: 25 | L52: 12 | M52: 0 | N52: 5.88 | O52: 5.58 | P52: 34 | Q52: 48 | AA52: HEIDE
A53: 49 | B53: Helgoland | C53: Grune Aue 31 | D53: A – Stabil | E53: Stadt / Kirche | F53: 110 | G53: 6 | H53: 50704 | I53: 0 | J53: 51.1 | K53: 39 | L53: 15.3 | M53: 0 | N53: 10.37 | O53: 3.98 | P53: 110 | Q53: 49 | AA53: HELGO
A54: 50 | B54: Hoffnung | C54: Baebenrothufer 7 | D54: B – Beobachtung | E54: Stadt BRB | F54: 7 | G54: 1 | H54: 4673 | I54: 0 | J54: 4.8 | K54: 1.8 | L54: 2.1 | M54: 0 | N54: 9.96 | O54: 3.51 | P54: 7 | Q54: 49 | R54: 65 | AA54: HOFFN
A55: 51 | B55: Holland | C55: Klingenbergstr. 2 | D55: B – Beobachtung | E55: Stadt BRB | F55: 9 | G55: 1 | H55: 3365 | I55: 0 | J55: 8.6 | K55: 4.6 | L55: 0 | M55: 0 | N55: 9.55 | O55: 4.66 | P55: 9 | Q55: 56 | R55: 44 | AA55: HOLL
A56: 52 | B56: Im Mittelbruch I | C56: Krakauer Str. 28 | D56: C – Qualifizierung | E56: Stadt / privat | F56: 33 | G56: 0 | H56: 27542 | I56: 0 | J56: 11.3 | K56: 23 | L56: 11 | M56: 0 | N56: 12.71 | O56: 5.58 | P56: 33 | Q56: 85 | R56: 61 | AA56: MBR1
A57: 53 | B57: Im Mittelbruch II | C57: Krakauer Str. 29 | D57: C – Qualifizierung | E57: Stadt / privat | F57: 47 | G57: 1 | H57: 23601 | I57: 0 | J57: 25.9 | K57: 20 | L57: 26.3 | M57: 1.4 | N57: 12.18 | O57: 5.37 | P57: 47 | Q57: 85 | R57: 61 | AA57: MBR2
A58: 54 | B58: Immergrün | C58: Gordenallee 169 | D58: A – Stabil | E58: Stadt BRB | F58: 57 | G58: 0 | H58: 28680 | I58: 6.3 | J58: 21.9 | K58: 25.1 | L58: 14.7 | M58: 0.5 | N58: 8.94 | O58: 6.43 | P58: 57 | Q58: 28 | R58: 29 | AA58: IMMER
A59: 55 | B59: Jakobswerder | C59: Grune Aue 48 | D59: B – Beobachtung | E59: Stadt / Kirche | F59: 49 | G59: 1 | H59: 22337 | I59: 3 | J59: 19.5 | K59: 24.1 | L59: 12.1 | M59: 0 | N59: 9.88 | O59: 3.99 | P59: 49 | Q59: 23 | R59: 36 | AA59: JAKWE
A60: 56 | B60: Kammgarn | C60: Klingenbergstr. 2a | D60: B – Beobachtung | E60: Privat | F60: 28 | G60: 10 | H60: 9938 | I60: 1.8 | J60: 9.4 | K60: 15 | L60: 0 | M60: 0 | N60: 9.62 | O60: 4.34 | P60: 28 | Q60: 56 | AA60: KAMM
A61: 57 | B61: Kirchmöser-Dorf | C61: Bahnhofstr. 3 | D61: C – Qualifizierung | E61: Stadt / privat | F61: 48 | G61: 2 | H61: 34296 | I61: 0 | J61: 10.8 | K61: 23.5 | L61: 16.3 | M61: 0 | N61: 1.57 | O61: 1.76 | P61: 48 | Q61: 57 | AA61: KMDOR
A62: 58 | B62: Kirchmöser-Lehmgarten | C62: Uferstr. 71b | D62: B – Beobachtung | E62: Stadt BRB | F62: 38 | G62: 1 | H62: 13623 | I62: 1 | J62: 14.1 | K62: 23.6 | L62: 8.1 | M62: 0 | N62: 2.69 | O62: 2.18 | P62: 38 | Q62: 59 | R62: 59 | AA62: KMLEH
A63: 59 | B63: Kirchmöser-Ost | C63: Kurze Str. 17 | D63: A – Stabil | E63: Stadt BRB | F63: 66 | G63: 0 | H63: 24565 | I63: 0 | J63: 15.9 | K63: 39.1 | L63: 32.9 | M63: 0 | N63: 3.21 | O63: 2.06 | P63: 71 | Q63: 59 | AA63: KMOST
A64: 60 | B64: Landheim | C64: Wilhelmsdorfer Landstr. 65 | D64: A – Stabil | E64: Stadt BRB | F64: 109 | G64: 11 | H64: 52025 | I64: 2.3 | J64: 42.6 | K64: 44.4 | L64: 28 | M64: 0 | N64: 9.6 | O64: 2.79 | P64: 109 | Q64: 41 | R64: 41 | AA64: LANDH
A65: 61 | B65: Märkische Aue | C65: Krakauer Str. 27 | D65: B – Beobachtung | E65: Stadt / privat | F65: 73 | G65: 0 | H65: 36741 | I65: 0 | J65: 18.2 | K65: 54.1 | L65: 18.1 | M65: 0 | N65: 12.33 | O65: 5.83 | P65: 73 | Q65: 85 | R65: 85 | AA65: MAERK
A66: 62 | B66: Mittelweg | C66: Buchenweg 63a | D66: C – Qualifizierung | E66: Privat | F66: 36 | G66: 2 | H66: 15206 | I66: 0 | J66: 11.9 | K66: 19.5 | L66: 13.4 | M66: 0 | N66: 9.3 | O66: 1.15 | P66: 36 | Q66: 22 | R66: 22 | AA66: MITTW
A67: 63 | B67: Morgenrot | C67: Ziesarer Landstr. 66 | D67: B – Beobachtung | E67: Stadt BRB | F67: 25 | G67: 1 | H67: 14070 | I67: 1.6 | J67: 21.7 | K67: 4.2 | L67: 0 | M67: 0 | N67: 9.02 | O67: 1.75 | P67: 25 | Q67: 73 | R67: 74 | AA67: MORGE
A68: 64 | B68: Neues Leben | C68: Koppehlstr. 7 | D68: C – Qualifizierung | E68: Stadt BRB | F68: 62 | G68: 3 | H68: 34980 | I68: 0.4 | J68: 25.6 | K68: 32.3 | L68: 12.7 | M68: 0 | N68: 10.33 | O68: 3.32 | P68: 76 | Q68: 49 | R68: 65 | AA68: NEUL
A69: 65 | B69: Neu-Sanssouci | C69: Grune Aue 46 | D69: A – Stabil | E69: Stadt / Kirche | F69: 77 | G69: 0 | H69: 30770 | I69: 0 | J69: 36.7 | K69: 34.9 | L69: 14.2 | M69: 0 | N69: 9.91 | O69: 3.76 | P69: 62 | Q69: 49 | R69: 49 | AA69: NSANS
A70: 66 | B70: Oase | C70: Brahmsstr. 14b | D70: A – Stabil | E70: Stadt BRB | F70: 47 | G70: 0 | H70: 25083 | I70: 3.8 | J70: 29 | K70: 25 | L70: 0.8 | M70: 0 | N70: 8.3 | O70: 7.37 | P70: 47 | Q70: 28 | R70: 29 | AA70: OASE
A71: 67 | B71: Pferdewiese | C71: Seestr. 50 | D71: C – Qualifizierung | E71: Stadt BRB | F71: 55 | G71: 1 | H71: 30105 | I71: 1.9 | J71: 15.4 | K71: 42 | L71: 18.1 | M71: 0 | N71: 0.83 | O71: 3.84 | P71: 55 | Q71: 16 | R71: 16 | AA71: PFERD
A72: 68 | B72: Plane II | C72: Planeweg 4& | D72: C – Qualifizierung | E72: Stadt / privat | F72: 28 | G72: 0 | H72: 14775 | I72: 0.7 | J72: 9 | K72: 19.7 | L72: 5.7 | M72: 0 | N72: 8.86 | O72: 2.58 | P72: 28 | Q72: 73 | R72: 40 | AA72: PLAN2
A73: 69 | B73: Platz der Einheit | C73: Platz der Einheit 19 | D73: C – Qualifizierung | E73: Stadt BRB | F73: 48 | G73: 1 | H73: 18906 | I73: 0 | J73: 26.4 | K73: 26.8 | L73: 7.6 | M73: 0 | N73: 1.21 | O73: 2.22 | P73: 48 | Q73: 57 | R73: 57 | AA73: PLEIN
A74: 70 | B74: Sandfurth-Oase | C74: Sandfurthweg 27 | D74: B – Beobachtung | E74: Privat | F74: 15 | G74: 0 | H74: 7765 | I74: 0.5 | J74: 4.8 | K74: 11.1 | L74: 3.3 | M74: 0 | N74: 7.72 | O74: 1.92 | P74: 15 | Q74: 73 | R74: 18 | AA74: SFOAS
A75: 71 | B75: Sanssouci | C75: Wilhelmsdorfer Landstr. 55 | D75: A – Stabil | E75: Stadt / privat | F75: 39 | G75: 5 | H75: 16848 | I75: 0 | J75: 21.5 | K75: 12.2 | L75: 5 | M75: 0 | N75: 9.88 | O75: 3.05 | P75: 39 | Q75: 23 | R75: 55 | AA75: SANS
A76: 72 | B76: Sommerfreude I | C76: Eichhorstweg 9 | D76: B – Beobachtung | E76: Stadt / privat | F76: 49 | G76: 1 | H76: 24945 | I76: 0 | J76: 15.2 | K76: 32.2 | L76: 17.2 | M76: 0 | N76: 9.61 | O76: 1.1 | P76: 49 | Q76: 17 | R76: 17 | AA76: SOMF1
A77: 73 | B77: Sommerfreude II | C77: Pfefferlander Weg 9 | D77: A – Stabil | E77: Stadt / privat | F77: 130 | G77: 1 | H77: 75448 | I77: 7.7 | J77: 41.2 | K77: 59.1 | L77: 50.9 | M77: 0 | N77: 7.94 | O77: 1.38 | P77: 130 | Q77: 73 | AA77: SOMF2
A78: 74 | B78: Sonnenrot | C78: Ziesarer Landstr. 68 | D78: A – Stabil | E78: Privat | F78: 28 | G78: 0 | H78: 12438 | I78: 2.1 | J78: 13.2 | K78: 13.9 | L78: 8.9 | M78: 0 | N78: 8.87 | O78: 1.75 | P78: 28 | Q78: 73 | R78: 40 | AA78: SOROT
A79: 75 | B79: Sonnenschein | C79: Mahlerstr. 22 | D79: A – Stabil | E79: Stadt BRB | F79: 40 | G79: 1 | H79: 19604 | I79: 2.4 | J79: 23.6 | K79: 22.9 | L79: 6.8 | M79: 0 | N79: 7.79 | O79: 7.59 | P79: 40 | Q79: 28 | R79: 82 | AA79: SOSCH
A80: 76 | B80: Sonnenwinkel | C80: Buchenweg 65a | D80: A – Stabil | E80: Stadt / privat | F80: 48 | G80: 0 | H80: 22186 | I80: 0.5 | J80: 25.6 | K80: 21.7 | L80: 14.8 | M80: 0 | N80: 9.45 | O80: 1.29 | P80: 48 | Q80: 17 | R80: 72 | AA80: SOWIN
A81: 77 | B81: Sorgenfrei I | C81: Ziesarer Landstr. 76 | D81: B – Beobachtung | E81: Stadt BRB | F81: 45 | G81: 2 | H81: 23588 | I81: 1.6 | J81: 20 | K81: 18.9 | L81: 7.1 | M81: 0 | N81: 8.91 | O81: 1.61 | P81: 45 | Q81: 17 | R81: 38 | AA81: SORG1
A82: 78 | B82: Sorgenfrei II | C82: Buchenweg 62 | D82: B – Beobachtung | E82: Privat | F82: 23 | G82: 2 | H82: 16763 | I82: 0 | J82: 10.2 | K82: 16 | L82: 3.9 | M82: 0 | N82: 9.03 | O82: 1.43 | P82: 23 | Q82: 73 | R82: 63 | AA82: SORG2
A83: 79 | B83: Sportpark | C83: Wilhelmsdorfer Landstr. 90 | D83: C – Qualifizierung | E83: Privat | F83: 37 | G83: 1 | H83: 19323 | I83: 0.7 | J83: 11.9 | K83: 17 | L83: 18.5 | M83: 0.6 | N83: 9.33 | O83: 2.94 | P83: 37 | Q83: 23 | R83: 71 | AA83: SPORT
A84: 80 | B84: Stiller Winkel | C84: Pfefferlander Weg 50 | D84: B – Beobachtung | E84: Stadt / privat | F84: 50 | G84: 2 | H84: 27635 | I84: 0.3 | J84: 19.8 | K84: 24.7 | L84: 18.2 | M84: 0 | N84: 8.56 | O84: 2.02 | P84: 50 | Q84: 17 | R84: 38 | AA84: STILL
A85: 81 | B85: Traumland | C85: Fritze-Bollmann-Weg 82 | D85: B – Beobachtung | E85: Stadt BRB | F85: 49 | G85: 1 | H85: 21764 | I85: 0 | J85: 16.9 | K85: 26.4 | L85: 8.8 | M85: 0 | N85: 11.1 | O85: 7.69 | P85: 49 | Q85: 81 | AA85: TRAUM
A86: 82 | B86: Waldfrieden | C86: Weberstr. 59 | D86: A – Stabil | E86: Stadt / privat | F86: 90 | G86: 3 | H86: 51208 | I86: 2.3 | J86: 47 | K86: 42.1 | L86: 23.5 | M86: 0 | N86: 7.54 | O86: 7.41 | P86: 90 | Q86: 28 | R86: 29 | AA86: WALDF
A87: 83 | B87: Weinmeisterweg | C87: Weinmeisterweg 10 | D87: A – Stabil | E87: Privat | F87: 26 | G87: 1 | H87: 8902 | I87: 0 | J87: 13.2 | K87: 7.4 | L87: 8.8 | M87: 0 | N87: 9.97 | O87: 5.72 | P87: 26 | Q87: 28 | R87: 54 | AA87: WEINM
A88: 84 | B88: Wittstocker Gäßchen | C88: Wittstocker Gäßchen 15 | D88: B – Beobachtung | E88: Stadt / Kirche | F88: 54 | G88: 0 | H88: 36135 | I88: 0.9 | J88: 16.7 | K88: 22.5 | L88: 24.1 | M88: 0 | N88: 9.54 | O88: 1.72 | P88: 54 | Q88: 17 | R88: 17 | AA88: WITTS
A89: 85 | B89: Zukunft | C89: Hagelberger Str. 3 | D89: A – Stabil | E89: Privat | F89: 85 | G89: 3 | H89: 47523 | I89: 2.9 | J89: 33.3 | K89: 65.8 | L89: 11.4 | M89: 0 | N89: 12.47 | O89: 6.53 | P89: 85 | Q89: 85 | AA89: ZUKUN
A90: 86 | B90: Zum Burgweg | C90: Burgweg 4a | D90: A – Stabil | E90: Stadt BRB | F90: 9 | G90: 0 | H90: 5216 | I90: 0 | J90: 1.9 | K90: 7.5 | L90: 2.4 | M90: 0 | N90: 11.66 | O90: 5.29 | P90: 9 | Q90: 85 | R90: 87 | AA90: BURGW
A91: 87 | B91: Zum kühlen Grunde | C91: Grillendamm 8 | D91: A – Stabil | E91: Stadt BRB | F91: 26 | G91: 0 | H91: 14389 | I91: 2.6 | J91: 8.1 | K91: 15.7 | L91: 9 | M91: 0 | N91: 11.67 | O91: 5.46 | P91: 26 | Q91: 85 | R91: 53 | AA91: KUEHL
A92: 88 | B92: Zur Insel | C92: Domkietz 8a | D92: A – Stabil | E92: Stadt / privat | F92: 86 | G92: 0 | H92: 54091 | I92: 0 | J92: 21.8 | K92: 53.6 | L92: 28.7 | M92: 0 | N92: 11.24 | O92: 5.17 | P92: 86 | Q92: 49 | R92: 49 | AA92: INSEL
A94: Rot: Parzellenzahl in den Konzept-Tabellen 5–8 weicht vom Steckbrief ab (gerechnet wird mit dem Steckbrief, Summe 5.017 = Konzept S. 18).
A95: Lage: aus der Beschriftung der Übersichtskarte gemessen (10-km-Maßstab), Ursprung links unten, ca. ±300 m.

Sheet Buchungsquote
A1: Buchungsquote – berechnet aus Alter und Leerstand, fest oder je Sparte manuell
A2: Modus 1: Ø Buchungsneigung nach Alter × (1 − Leerstandsquote) × Faktor Entwicklungsstufe · Modus 2: feste Quote · „Quote manuell“ (Anlagen) hat Vorrang
A4: Nr. | B4: Kleingartenanlage | C4: Parzellen | D4: Leerstand | E4: Leerstands-quote | F4: Anteil bis 30 | G4: 30–50 | H4: 50–70 | I4: 70–90 | J4: ab 90 | K4: Ø Buchungs-neigung | L4: Faktor Stufe | M4: Quote heute (Alter) | N4: Pachtaufgabe 5 J. | O4: Nachbe-setzung | P4: Leerstand in 5 J. | Q4: Leerstands-quote 5 J. | R4: Neigung Bestand 5 J. | S4: Quote in 5 J. (Alter) | T4: Quote gewählt | U4: Herkunft | V4: Kunden
A5: =Anlagen!A5 -> 1 | B5: =Anlagen!B5 -> 1. März | C5: =Anlagen!F5 -> 30 | D5: =Anlagen!G5 -> 2 | E5: =D5/C5 -> 0.066666667 | F5: =Anlagen!I5/MAX(0.0001,SUM(Anlagen!I5:M5)) -> 0.01010101 | G5: =Anlagen!J5/MAX(0.0001,SUM(Anlagen!I5:M5)) -> 0.61363636 | H5: =Anlagen!K5/MAX(0.0001,SUM(Anlagen!I5:M5)) -> 0.27272727 | I5: =Anlagen!L5/MAX(0.0001,SUM(Anlagen!I5:M5)) -> 0.10353535 | J5: =Anlagen!M5/MAX(0.0001,SUM(Anlagen!I5:M5)) -> 0 | K5: =F5*Neig_1+G5*Neig_2+H5*Neig_3+I5*Neig_4+J5*Neig_5 -> 0.66818182 | L5: =IF(LEFT(Anlagen!D5,1)="A",Stufe_A,IF(LEFT(Anlagen!D5,1)="B",Stufe_B,IF(LEFT(Anlagen!D5,1)="C",Stufe_C,Stufe_D))) -> 1 | M5: =K5*(1-E5)*L5 -> 0.62363636 | N5: =F5*Abg_1+G5*Abg_2+H5*Abg_3+I5*Abg_4+J5*Abg_5 -> 0.089520202 | O5: =MAX(0,MIN(1,Nachbes-E5*Nachbes_Leer)) -> 0.56666667 | P5: =D5+(C5-D5)*N5*(1-O5) -> 3.0861785 | Q5: =P5/C5 -> 0.10287262 | R5: =(F5*(1-Abg_1)*Neig_1+G5*(1-Abg_2)*Neig_2+H5*(1-Abg_3)*Neig_3+I5*(1-Abg_4)*Neig_4+J5*(1-Abg_5)*Neig_5)/MAX(0.0001,1-N5) -> 0.67824851 | S5: =(C5-D5)*((1-N5)*R5+N5*O5*Neig_Neu)*L5/C5 -> 0.61187247 | T5: =IF(Anlagen!W5<>"",Anlagen!W5,IF(Quote_Modus=2,Quote_fest,IF(Szenario=2,S5,M5))) -> 0.62363636 | U5: =IF(Anlagen!W5<>"","manuell",IF(Quote_Modus=2,"fest",IF(Szenario=2,"Alter, in 5 J.","Alter, heute"))) -> Alter, heute | V5: =C5*T5 -> 18.709091
A6: =Anlagen!A6 -> 2 | B6: =Anlagen!B6 -> Abendfrieden | C6: =Anlagen!F6 -> 75 | D6: =Anlagen!G6 -> 4 | E6: =D6/C6 -> 0.053333333 | F6: =Anlagen!I6/MAX(0.0001,SUM(Anlagen!I6:M6)) -> 0 | G6: =Anlagen!J6/MAX(0.0001,SUM(Anlagen!I6:M6)) -> 0.44444444 | H6: =Anlagen!K6/MAX(0.0001,SUM(Anlagen!I6:M6)) -> 0.40217391 | I6: =Anlagen!L6/MAX(0.0001,SUM(Anlagen!I6:M6)) -> 0.15338164 | J6: =Anlagen!M6/MAX(0.0001,SUM(Anlagen!I6:M6)) -> 0 | K6: =F6*Neig_1+G6*Neig_2+H6*Neig_3+I6*Neig_4+J6*Neig_5 -> 0.62832126 | L6: =IF(LEFT(Anlagen!D6,1)="A",Stufe_A,IF(LEFT(Anlagen!D6,1)="B",Stufe_B,IF(LEFT(Anlagen!D6,1)="C",Stufe_C,Stufe_D))) -> 0.9 | M6: =K6*(1-E6)*L6 -> 0.53532971 | N6: =F6*Abg_1+G6*Abg_2+H6*Abg_3+I6*Abg_4+J6*Abg_5 -> 0.10845411 | O6: =MAX(0,MIN(1,Nachbes-E6*Nachbes_Leer)) -> 0.59333333 | P6: =D6+(C6-D6)*N6*(1-O6) -> 7.1314316 | Q6: =P6/C6 -> 0.095085754 | R6: =(F6*(1-Abg_1)*Neig_1+G6*(1-Abg_2)*Neig_2+H6*(1-Abg_3)*Neig_3+I6*(1-Abg_4)*Neig_4+J6*(1-Abg_5)*Neig_5)/MAX(0.0001,1-N6) -> 0.64093064 | S6: =(C6-D6)*((1-N6)*R6+N6*O6*Neig_Neu)*L6/C6 -> 0.52796835 | T6: =IF(Anlagen!W6<>"",Anlagen!W6,IF(Quote_Modus=2,Quote_fest,IF(Szenario=2,S6,M6))) -> 0.53532971 | U6: =IF(Anlagen!W6<>"","manuell",IF(Quote_Modus=2,"fest",IF(Szenario=2,"Alter, in 5 J.","Alter, heute"))) -> Alter, heute | V6: =C6*T6 -> 40.149728
A7: =Anlagen!A7 -> 3 | B7: =Anlagen!B7 -> Abendrot | C7: =Anlagen!F7 -> 137 | D7: =Anlagen!G7 -> 0 | E7: =D7/C7 -> 0 | F7: =Anlagen!I7/MAX(0.0001,SUM(Anlagen!I7:M7)) -> 0.0079325731 | G7: =Anlagen!J7/MAX(0.0001,SUM(Anlagen!I7:M7)) -> 0.21070897 | H7: =Anlagen!K7/MAX(0.0001,SUM(Anlagen!I7:M7)) -> 0.52404561 | I7: =Anlagen!L7/MAX(0.0001,SUM(Anlagen!I7:M7)) -> 0.25731284 | J7: =Anlagen!M7/MAX(0.0001,SUM(Anlagen!I7:M7)) -> 0 | K7: =F7*Neig_1+G7*Neig_2+H7*Neig_3+I7*Neig_4+J7*Neig_5 -> 0.56886465 | L7: =IF(LEFT(Anlagen!D7,1)="A",Stufe_A,IF(LEFT(Anlagen!D7,1)="B",Stufe_B,IF(LEFT(Anlagen!D7,1)="C",Stufe_C,Stufe_D))) -> 1 | M7: =K7*(1-E7)*L7 -> 0.56886465 | N7: =F7*Abg_1+G7*Abg_2+H7*Abg_3+I7*Abg_4+J7*Abg_5 -> 0.14053049 | O7: =MAX(0,MIN(1,Nachbes-E7*Nachbes_Leer)) -> 0.7 | P7: =D7+(C7-D7)*N7*(1-O7) -> 5.7758032 | Q7: =P7/C7 -> 0.042159147 | R7: =(F7*(1-Abg_1)*Neig_1+G7*(1-Abg_2)*Neig_2+H7*(1-Abg_3)*Neig_3+I7*(1-Abg_4)*Neig_4+J7*(1-Abg_5)*Neig_5)/MAX(0.0001,1-N7) -> 0.58429667 | S7: =(C7-D7)*((1-N7)*R7+N7*O7*Neig_Neu)*L7/C7 -> 0.57596368 | T7: =IF(Anlagen!W7<>"",Anlagen!W7,IF(Quote_Modus=2,Quote_fest,IF(Szenario=2,S7,M7))) -> 0.56886465 | U7: =IF(Anlagen!W7<>"","manuell",IF(Quote_Modus=2,"fest",IF(Szenario=2,"Alter, in 5 J.","Alter, heute"))) -> Alter, heute | V7: =C7*T7 -> 77.934457
A8: =Anlagen!A8 -> 4 | B8: =Anlagen!B8 -> Abendruh | C8: =Anlagen!F8 -> 142 | D8: =Anlagen!G8 -> 0 | E8: =D8/C8 -> 0 | F8: =Anlagen!I8/MAX(0.0001,SUM(Anlagen!I8:M8)) -> 0.015837104 | G8: =Anlagen!J8/MAX(0.0001,SUM(Anlagen!I8:M8)) -> 0.26527149 | H8: =Anlagen!K8/MAX(0.0001,SUM(Anlagen!I8:M8)) -> 0.40384615 | I8: =Anlagen!L8/MAX(0.0001,SUM(Anlagen!I8:M8)) -> 0.29920814 | J8: =Anlagen!M8/MAX(0.0001,SUM(Anlagen!I8:M8)) -> 0.015837104 | K8: =F8*Neig_1+G8*Neig_2+H8*Neig_3+I8*Neig_4+J8*Neig_5 -> 0.56023756 | L8: =IF(LEFT(Anlagen!D8,1)="A",Stufe_A,IF(LEFT(Anlagen!D8,1)="B",Stufe_B,IF(LEFT(Anlagen!D8,1)="C",Stufe_C,Stufe_D))) -> 1 | M8: =K8*(1-E8)*L8 -> 0.56023756 | N8: =F8*Abg_1+G8*Abg_2+H8*Abg_3+I8*Abg_4+J8*Abg_5 -> 0.15370475 | O8: =MAX(0,MIN(1,Nachbes-E8*Nachbes_Leer)) -> 0.7 | P8: =D8+(C8-D8)*N8*(1-O8) -> 6.5478224 | Q8: =P8/C8 -> 0.046111425 | R8: =(F8*(1-Abg_1)*Neig_1+G8*(1-Abg_2)*Neig_2+H8*(1-Abg_3)*Neig_3+I8*(1-Abg_4)*Neig_4+J8*(1-Abg_5)*Neig_5)/MAX(0.0001,1-N8) -> 0.58260819 | S8: =(C8-D8)*((1-N8)*R8+N8*O8*Neig_Neu)*L8/C8 -> 0.57375354 | T8: =IF(Anlagen!W8<>"",Anlagen!W8,IF(Quote_Modus=2,Quote_fest,IF(Szenario=2,S8,M8))) -> 0.56023756 | U8: =IF(Anlagen!W8<>"","manuell",IF(Quote_Modus=2,"fest",IF(Szenario=2,"Alter, in 5 J.","Alter, heute"))) -> Alter, heute | V8: =C8*T8 -> 79.553733
A9: =Anlagen!A9 -> 5 | B9: =Anlagen!B9 -> Abendsonne | C9: =Anlagen!F9 -> 67 | D9: =Anlagen!G9 -> 13 | E9: =D9/C9 -> 0.19402985 | F9: =Anlagen!I9/MAX(0.0001,SUM(Anlagen!I9:M9)) -> 0.027597403 | G9: =Anlagen!J9/MAX(0.0001,SUM(Anlagen!I9:M9)) -> 0.34902597 | H9: =Anlagen!K9/MAX(0.0001,SUM(Anlagen!I9:M9)) -> 0.49188312 | I9: =Anlagen!L9/MAX(0.0001,SUM(Anlagen!I9:M9)) -> 0.13149351 | J9: =Anlagen!M9/MAX(0.0001,SUM(Anlagen!I9:M9)) -> 0 | K9: =F9*Neig_1+G9*Neig_2+H9*Neig_3+I9*Neig_4+J9*Neig_5 -> 0.625 | L9: =IF(LEFT(Anlagen!D9,1)="A",Stufe_A,IF(LEFT(Anlagen!D9,1)="B",Stufe_B,IF(LEFT(Anlagen!D9,1)="C",Stufe_C,Stufe_D))) -> 1 | M9: =K9*(1-E9)*L9 -> 0.50373134 | N9: =F9*Abg_1+G9*Abg_2+H9*Abg_3+I9*Abg_4+J9*Abg_5 -> 0.10746753 | O9: =MAX(0,MIN(1,Nachbes-E9*Nachbes_Leer)) -> 0.3119403 | P9: =D9+(C9-D9)*N9*(1-O9) -> 16.99298 | Q9: =P9/C9 -> 0.25362657 | R9: =(F9*(1-Abg_1)*Neig_1+G9*(1-Abg_2)*Neig_2+H9*(1-Abg_3)*Neig_3+I9*(1-Abg_4)*Neig_4+J9*(1-Abg_5)*Neig_5)/MAX(0.0001,1-N9) -> 0.63581757 | S9: =(C9-D9)*((1-N9)*R9+N9*O9*Neig_Neu)*L9/C9 -> 0.47764242 | T9: =IF(Anlagen!W9<>"",Anlagen!W9,IF(Quote_Modus=2,Quote_fest,IF(Szenario=2,S9,M9))) -> 0.50373134 | U9: =IF(Anlagen!W9<>"","manuell",IF(Quote_Modus=2,"fest",IF(Szenario=2,"Alter, in 5 J.","Alter, heute"))) -> Alter, heute | V9: =C9*T9 -> 33.75
A10: =Anlagen!A10 -> 6 | B10: =Anlagen!B10 -> Altstadt Forst | C10: =Anlagen!F10 -> 88 | D10: =Anlagen!G10 -> 0 | E10: =D10/C10 -> 0 | F10: =Anlagen!I10/MAX(0.0001,SUM(Anlagen!I10:M10)) -> 0.015837104 | G10: =Anlagen!J10/MAX(0.0001,SUM(Anlagen!I10:M10)) -> 0.26527149 | H10: =Anlagen!K10/MAX(0.0001,SUM(Anlagen!I10:M10)) -> 0.40384615 | I10: =Anlagen!L10/MAX(0.0001,SUM(Anlagen!I10:M10)) -> 0.29920814 | J10: =Anlagen!M10/MAX(0.0001,SUM(Anlagen!I10:M10)) -> 0.015837104 | K10: =F10*Neig_1+G10*Neig_2+H10*Neig_3+I10*Neig_4+J10*Neig_5 -> 0.56023756 | L10: =IF(LEFT(Anlagen!D10,1)="A",Stufe_A,IF(LEFT(Anlagen!D10,1)="B",Stufe_B,IF(LEFT(Anlagen!D10,1)="C",Stufe_C,Stufe_D))) -> 1 | M10: =K10*(1-E10)*L10 -> 0.56023756 | N10: =F10*Abg_1+G10*Abg_2+H10*Abg_3+I10*Abg_4+J10*Abg_5 -> 0.15370475 | O10: =MAX(0,MIN(1,Nachbes-E10*Nachbes_Leer)) -> 0.7 | P10: =D10+(C10-D10)*N10*(1-O10) -> 4.0578054 | Q10: =P10/C10 -> 0.046111425 | R10: =(F10*(1-Abg_1)*Neig_1+G10*(1-Abg_2)*Neig_2+H10*(1-Abg_3)*Neig_3+I10*(1-Abg_4)*Neig_4+J10*(1-Abg_5)*Neig_5)/MAX(0.0001,1-N10) -> 0.58260819 | S10: =(C10-D10)*((1-N10)*R10+N10*O10*Neig_Neu)*L10/C10 -> 0.57375354 | T10: =IF(Anlagen!W10<>"",Anlagen!W10,IF(Quote_Modus=2,Quote_fest,IF(Szenario=2,S10,M10))) -> 0.56023756 | U10: =IF(Anlagen!W10<>"","manuell",IF(Quote_Modus=2,"fest",IF(Szenario=2,"Alter, in 5 J.","Alter, heute"))) -> Alter, heute | V10: =C10*T10 -> 49.300905
A11: =Anlagen!A11 -> 7 | B11: =Anlagen!B11 -> Am Beetzseeufer | C11: =Anlagen!F11 -> 77 | D11: =Anlagen!G11 -> 0 | E11: =D11/C11 -> 0 | F11: =Anlagen!I11/MAX(0.0001,SUM(Anlagen!I11:M11)) -> 0.00085910653 | G11: =Anlagen!J11/MAX(0.0001,SUM(Anlagen!I11:M11)) -> 0.38573883 | H11: =Anlagen!K11/MAX(0.0001,SUM(Anlagen!I11:M11)) -> 0.5128866 | I11: =Anlagen!L11/MAX(0.0001,SUM(Anlagen!I11:M11)) -> 0.10051546 | J11: =Anlagen!M11/MAX(0.0001,SUM(Anlagen!I11:M11)) -> 0 | K11: =F11*Neig_1+G11*Neig_2+H11*Neig_3+I11*Neig_4+J11*Neig_5 -> 0.63290378 | L11: =IF(LEFT(Anlagen!D11,1)="A",Stufe_A,IF(LEFT(Anlagen!D11,1)="B",Stufe_B,IF(LEFT(Anlagen!D11,1)="C",Stufe_C,Stufe_D))) -> 1 | M11: =K11*(1-E11)*L11 -> 0.63290378 | N11: =F11*Abg_1+G11*Abg_2+H11*Abg_3+I11*Abg_4+J11*Abg_5 -> 0.1007732 | O11: =MAX(0,MIN(1,Nachbes-E11*Nachbes_Leer)) -> 0.7 | P11: =D11+(C11-D11)*N11*(1-O11) -> 2.3278608 | Q11: =P11/C11 -> 0.030231959 | R11: =(F11*(1-Abg_1)*Neig_1+G11*(1-Abg_2)*Neig_2+H11*(1-Abg_3)*Neig_3+I11*(1-Abg_4)*Neig_4+J11*(1-Abg_5)*Neig_5)/MAX(0.0001,1-N11) -> 0.64174787 | S11: =(C11-D11)*((1-N11)*R11+N11*O11*Neig_Neu)*L11/C11 -> 0.62998282 | T11: =IF(Anlagen!W11<>"",Anlagen!W11,IF(Quote_Modus=2,Quote_fest,IF(Szenario=2,S11,M11))) -> 0.63290378 | U11: =IF(Anlagen!W11<>"","manuell",IF(Quote_Modus=2,"fest",IF(Szenario=2,"Alter, in 5 J.","Alter, heute"))) -> Alter, heute | V11: =C11*T11 -> 48.733591
A12: =Anlagen!A12 -> 8 | B12: =Anlagen!B12 -> Am Büttelhandfassgraben | C12: =Anlagen!F12 -> 5 | D12: =Anlagen!G12 -> 0 | E12: =D12/C12 -> 0 | F12: =Anlagen!I12/MAX(0.0001,SUM(Anlagen!I12:M12)) -> 0.39285714 | G12: =Anlagen!J12/MAX(0.0001,SUM(Anlagen!I12:M12)) -> 0 | H12: =Anlagen!K12/MAX(0.0001,SUM(Anlagen!I12:M12)) -> 0.60714286 | I12: =Anlagen!L12/MAX(0.0001,SUM(Anlagen!I12:M12)) -> 0 | J12: =Anlagen!M12/MAX(0.0001,SUM(Anlagen!I12:M12)) -> 0 | K12: =F12*Neig_1+G12*Neig_2+H12*Neig_3+I12*Neig_4+J12*Neig_5 -> 0.67857143 | L12: =IF(LEFT(Anlagen!D12,1)="A",Stufe_A,IF(LEFT(Anlagen!D12,1)="B",Stufe_B,IF(LEFT(Anlagen!D12,1)="C",Stufe_C,Stufe_D))) -> 1 | M12: =K12*(1-E12)*L12 -> 0.67857143 | N12: =F12*Abg_1+G12*Abg_2+H12*Abg_3+I12*Abg_4+J12*Abg_5 -> 0.080357143 | O12: =MAX(0,MIN(1,Nachbes-E12*Nachbes_Leer)) -> 0.7 | P12: =D12+(C12-D12)*N12*(1-O12) -> 0.12053571 | Q12: =P12/C12 -> 0.024107143 | R12: =(F12*(1-Abg_1)*Neig_1+G12*(1-Abg_2)*Neig_2+H12*(1-Abg_3)*Neig_3+I12*(1-Abg_4)*Neig_4+J12*(1-Abg_5)*Neig_5)/MAX(0.0001,1-N12) -> 0.68116505 | S12: =(C12-D12)*((1-N12)*R12+N12*O12*Neig_Neu)*L12/C12 -> 0.66861607 | T12: =IF(Anlagen!W12<>"",Anlagen!W12,IF(Quote_Modus=2,Quote_fest,IF(Szenario=2,S12,M12))) -> 0.67857143 | U12: =IF(Anlagen!W12<>"","manuell",IF(Quote_Modus=2,"fest",IF(Szenario=2,"Alter, in 5 J.","Alter, heute"))) -> Alter, heute | V12: =C12*T12 -> 3.3928571
A13: =Anlagen!A13 -> 9 | B13: =Anlagen!B13 -> Am Eichenweg | C13: =Anlagen!F13 -> 54 | D13: =Anlagen!G13 -> 2 | E13: =D13/C13 -> 0.037037037 | F13: =Anlagen!I13/MAX(0.0001,SUM(Anlagen!I13:M13)) -> 0.013846154 | G13: =Anlagen!J13/MAX(0.0001,SUM(Anlagen!I13:M13)) -> 0.50769231 | H13: =Anlagen!K13/MAX(0.0001,SUM(Anlagen!I13:M13)) -> 0.34153846 | I13: =Anlagen!L13/MAX(0.0001,SUM(Anlagen!I13:M13)) -> 0.13692308 | J13: =Anlagen!M13/MAX(0.0001,SUM(Anlagen!I13:M13)) -> 0 | K13: =F13*Neig_1+G13*Neig_2+H13*Neig_3+I13*Neig_4+J13*Neig_5 -> 0.64469231 | L13: =IF(LEFT(Anlagen!D13,1)="A",Stufe_A,IF(LEFT(Anlagen!D13,1)="B",Stufe_B,IF(LEFT(Anlagen!D13,1)="C",Stufe_C,Stufe_D))) -> 0.9 | M13: =K13*(1-E13)*L13 -> 0.55873333 | N13: =F13*Abg_1+G13*Abg_2+H13*Abg_3+I13*Abg_4+J13*Abg_5 -> 0.10130769 | O13: =MAX(0,MIN(1,Nachbes-E13*Nachbes_Leer)) -> 0.62592593 | P13: =D13+(C13-D13)*N13*(1-O13) -> 3.9706222 | Q13: =P13/C13 -> 0.073530041 | R13: =(F13*(1-Abg_1)*Neig_1+G13*(1-Abg_2)*Neig_2+H13*(1-Abg_3)*Neig_3+I13*(1-Abg_4)*Neig_4+J13*(1-Abg_5)*Neig_5)/MAX(0.0001,1-N13) -> 0.65676624 | S13: =(C13-D13)*((1-N13)*R13+N13*O13*Neig_Neu)*L13/C13 -> 0.55275056 | T13: =IF(Anlagen!W13<>"",Anlagen!W13,IF(Quote_Modus=2,Quote_fest,IF(Szenario=2,S13,M13))) -> 0.55873333 | U13: =IF(Anlagen!W13<>"","manuell",IF(Quote_Modus=2,"fest",IF(Szenario=2,"Alter, in 5 J.","Alter, heute"))) -> Alter, heute | V13: =C13*T13 -> 30.1716
A14: =Anlagen!A14 -> 10 | B14: =Anlagen!B14 -> Am Jakobsgraben | C14: =Anlagen!F14 -> 41 | D14: =Anlagen!G14 -> 0 | E14: =D14/C14 -> 0 | F14: =Anlagen!I14/MAX(0.0001,SUM(Anlagen!I14:M14)) -> 0.0079840319 | G14: =Anlagen!J14/MAX(0.0001,SUM(Anlagen!I14:M14)) -> 0.3493014 | H14: =Anlagen!K14/MAX(0.0001,SUM(Anlagen!I14:M14)) -> 0.4510978 | I14: =Anlagen!L14/MAX(0.0001,SUM(Anlagen!I14:M14)) -> 0.19161677 | J14: =Anlagen!M14/MAX(0.0001,SUM(Anlagen!I14:M14)) -> 0 | K14: =F14*Neig_1+G14*Neig_2+H14*Neig_3+I14*Neig_4+J14*Neig_5 -> 0.60608782 | L14: =IF(LEFT(Anlagen!D14,1)="A",Stufe_A,IF(LEFT(Anlagen!D14,1)="B",Stufe_B,IF(LEFT(Anlagen!D14,1)="C",Stufe_C,Stufe_D))) -> 0.75 | M14: =K14*(1-E14)*L14 -> 0.45456587 | N14: =F14*Abg_1+G14*Abg_2+H14*Abg_3+I14*Abg_4+J14*Abg_5 -> 0.12045908 | O14: =MAX(0,MIN(1,Nachbes-E14*Nachbes_Leer)) -> 0.7 | P14: =D14+(C14-D14)*N14*(1-O14) -> 1.4816467 | Q14: =P14/C14 -> 0.036137725 | R14: =(F14*(1-Abg_1)*Neig_1+G14*(1-Abg_2)*Neig_2+H14*(1-Abg_3)*Neig_3+I14*(1-Abg_4)*Neig_4+J14*(1-Abg_5)*Neig_5)/MAX(0.0001,1-N14) -> 0.62019176 | S14: =(C14-D14)*((1-N14)*R14+N14*O14*Neig_Neu)*L14/C14 -> 0.45654379 | T14: =IF(Anlagen!W14<>"",Anlagen!W14,IF(Quote_Modus=2,Quote_fest,IF(Szenario=2,S14,M14))) -> 0.45456587 | U14: =IF(Anlagen!W14<>"","manuell",IF(Quote_Modus=2,"fest",IF(Szenario=2,"Alter, in 5 J.","Alter, heute"))) -> Alter, heute | V14: =C14*T14 -> 18.637201
A15: =Anlagen!A15 -> 11 | B15: =Anlagen!B15 -> Am Schafdamm | C15: =Anlagen!F15 -> 10 | D15: =Anlagen!G15 -> 0 | E15: =D15/C15 -> 0 | F15: =Anlagen!I15/MAX(0.0001,SUM(Anlagen!I15:M15)) -> 0 | G15: =Anlagen!J15/MAX(0.0001,SUM(Anlagen!I15:M15)) -> 0.13675214 | H15: =Anlagen!K15/MAX(0.0001,SUM(Anlagen!I15:M15)) -> 0.43589744 | I15: =Anlagen!L15/MAX(0.0001,SUM(Anlagen!I15:M15)) -> 0.42735043 | J15: =Anlagen!M15/MAX(0.0001,SUM(Anlagen!I15:M15)) -> 0 | K15: =F15*Neig_1+G15*Neig_2+H15*Neig_3+I15*Neig_4+J15*Neig_5 -> 0.51367521 | L15: =IF(LEFT(Anlagen!D15,1)="A",Stufe_A,IF(LEFT(Anlagen!D15,1)="B",Stufe_B,IF(LEFT(Anlagen!D15,1)="C",Stufe_C,Stufe_D))) -> 0.9 | M15: =K15*(1-E15)*L15 -> 0.46230769 | N15: =F15*Abg_1+G15*Abg_2+H15*Abg_3+I15*Abg_4+J15*Abg_5 -> 0.17863248 | O15: =MAX(0,MIN(1,Nachbes-E15*Nachbes_Leer)) -> 0.7 | P15: =D15+(C15-D15)*N15*(1-O15) -> 0.53589744 | Q15: =P15/C15 -> 0.053589744 | R15: =(F15*(1-Abg_1)*Neig_1+G15*(1-Abg_2)*Neig_2+H15*(1-Abg_3)*Neig_3+I15*(1-Abg_4)*Neig_4+J15*(1-Abg_5)*Neig_5)/MAX(0.0001,1-N15) -> 0.5326743 | S15: =(C15-D15)*((1-N15)*R15+N15*O15*Neig_Neu)*L15/C15 -> 0.47817308 | T15: =IF(Anlagen!W15<>"",Anlagen!W15,IF(Quote_Modus=2,Quote_fest,IF(Szenario=2,S15,M15))) -> 0.46230769 | U15: =IF(Anlagen!W15<>"","manuell",IF(Quote_Modus=2,"fest",IF(Szenario=2,"Alter, in 5 J.","Alter, heute"))) -> Alter, heute | V15: =C15*T15 -> 4.6230769
A16: =Anlagen!A16 -> 12 | B16: =Anlagen!B16 -> Am Schlangenpfad | C16: =Anlagen!F16 -> 19 | D16: =Anlagen!G16 -> 0 | E16: =D16/C16 -> 0 | F16: =Anlagen!I16/MAX(0.0001,SUM(Anlagen!I16:M16)) -> 0 | G16: =Anlagen!J16/MAX(0.0001,SUM(Anlagen!I16:M16)) -> 0.11111111 | H16: =Anlagen!K16/MAX(0.0001,SUM(Anlagen!I16:M16)) -> 0.32950192 | I16: =Anlagen!L16/MAX(0.0001,SUM(Anlagen!I16:M16)) -> 0.55938697 | J16: =Anlagen!M16/MAX(0.0001,SUM(Anlagen!I16:M16)) -> 0 | K16: =F16*Neig_1+G16*Neig_2+H16*Neig_3+I16*Neig_4+J16*Neig_5 -> 0.47681992 | L16: =IF(LEFT(Anlagen!D16,1)="A",Stufe_A,IF(LEFT(Anlagen!D16,1)="B",Stufe_B,IF(LEFT(Anlagen!D16,1)="C",Stufe_C,Stufe_D))) -> 0.9 | M16: =K16*(1-E16)*L16 -> 0.42913793 | N16: =F16*Abg_1+G16*Abg_2+H16*Abg_3+I16*Abg_4+J16*Abg_5 -> 0.20632184 | O16: =MAX(0,MIN(1,Nachbes-E16*Nachbes_Leer)) -> 0.7 | P16: =D16+(C16-D16)*N16*(1-O16) -> 1.1760345 | Q16: =P16/C16 -> 0.061896552 | R16: =(F16*(1-Abg_1)*Neig_1+G16*(1-Abg_2)*Neig_2+H16*(1-Abg_3)*Neig_3+I16*(1-Abg_4)*Neig_4+J16*(1-Abg_5)*Neig_5)/MAX(0.0001,1-N16) -> 0.49660874 | S16: =(C16-D16)*((1-N16)*R16+N16*O16*Neig_Neu)*L16/C16 -> 0.45221983 | T16: =IF(Anlagen!W16<>"",Anlagen!W16,IF(Quote_Modus=2,Quote_fest,IF(Szenario=2,S16,M16))) -> 0.42913793 | U16: =IF(Anlagen!W16<>"","manuell",IF(Quote_Modus=2,"fest",IF(Szenario=2,"Alter, in 5 J.","Alter, heute"))) -> Alter, heute | V16: =C16*T16 -> 8.1536207
... A92: =Anlagen!A92 -> 88 | B92: =Anlagen!B92 -> Zur Insel | C92: =Anlagen!F92 -> 86 | D92: =Anlagen!G92 -> 0 | E92: =D92/C92 -> 0 | F92: =Anlagen!I92/MAX(0.0001,SUM(Anlagen!I92:M92)) -> 0 | G92: =Anlagen!J92/MAX(0.0001,SUM(Anlagen!I92:M92)) -> 0.20941402 | H92: =Anlagen!K92/MAX(0.0001,SUM(Anlagen!I92:M92)) -> 0.51488953 | I92: =Anlagen!L92/MAX(0.0001,SUM(Anlagen!I92:M92)) -> 0.27569645 | J92: =Anlagen!M92/MAX(0.0001,SUM(Anlagen!I92:M92)) -> 0 | K92: =F92*Neig_1+G92*Neig_2+H92*Neig_3+I92*Neig_4+J92*Neig_5 -> 0.56248799 | L92: =IF(LEFT(Anlagen!D92,1)="A",Stufe_A,IF(LEFT(Anlagen!D92,1)="B",Stufe_B,IF(LEFT(Anlagen!D92,1)="C",Stufe_C,Stufe_D))) -> 1 | M92: =K92*(1-E92)*L92 -> 0.56248799 | N92: =F92*Abg_1+G92*Abg_2+H92*Abg_3+I92*Abg_4+J92*Abg_5 -> 0.14466859 | O92: =MAX(0,MIN(1,Nachbes-E92*Nachbes_Leer)) -> 0.7 | P92: =D92+(C92-D92)*N92*(1-O92) -> 3.7324496 | Q92: =P92/C92 -> 0.043400576 | R92: =(F92*(1-Abg_1)*Neig_1+G92*(1-Abg_2)*Neig_2+H92*(1-Abg_3)*Neig_3+I92*(1-Abg_4)*Neig_4+J92*(1-Abg_5)*Neig_5)/MAX(0.0001,1-N92) -> 0.57848158 | S92: =(C92-D92)*((1-N92)*R92+N92*O92*Neig_Neu)*L92/C92 -> 0.57074448 | T92: =IF(Anlagen!W92<>"",Anlagen!W92,IF(Quote_Modus=2,Quote_fest,IF(Szenario=2,S92,M92))) -> 0.56248799 | U92: =IF(Anlagen!W92<>"","manuell",IF(Quote_Modus=2,"fest",IF(Szenario=2,"Alter, in 5 J.","Alter, heute"))) -> Alter, heute | V92: =C92*T92 -> 48.373967
B93: Summe / Ø | C93: =SUM(C5:C92) -> 5017 | D93: =SUM(D5:D92) -> 171 | E93: =D93/C93 -> 0.034084114 | M93: =SUMPRODUCT(C5:C92,M5:M92)/C93 -> 0.56105513 | P93: =SUM(P5:P92) -> 396.97271 | Q93: =P93/C93 -> 0.079125515 | S93: =SUMPRODUCT(C5:C92,S5:S92)/C93 -> 0.56106063 | T93: =V93/C93 -> 0.56105513 | V93: =SUM(V5:V92) -> 2814.8136

Sheet Netz
A1: Netz – Gateway-Standort, Glasfaser-Zuleitung und Gateway-Belegung je Sparte
A2: Gateways eines Standorts werden in der Reihenfolge gefüllt (je 55 Parzellen) · Zuleitung von Sparte zu Sparte per Glasfaser
A4: Nr. | B4: Kleingartenanlage | C4: Gateway-Standort (wirksam) | D4: Zuleitung von (wirksam) | E4: Rolle | F4: Entfernung km | G4: Glasfaser Zuleitung m | H4: Zuleitung € | I4: Unterverteiler € | J4: Sortierung | K4: Parzellen davor am Standort | L4: Gateway von | M4: Gateway bis | N4: versorgt durch | O4: Kunden | P4: Prüfung | Q4: Kürzel | R4: VLAN-Block | S4: VLAN Parzellen von | T4: VLAN Parzellen bis | U4: VLAN Vorstand | V4: VLAN Gäste | W4: VLAN Technik | X4: Subnetz Parzelle 1 | Y4: Prüfung VLAN
A5: =Anlagen!A5 -> 1 | B5: =Anlagen!B5 -> 1. März | C5: =IF(Anlagen!S5<>"",Anlagen!S5,IF(Vorschlag_nutzen=1,Anlagen!Q5,A5)) -> 33 | D5: =IF(C5=A5,"",IF(Anlagen!T5<>"",Anlagen!T5,IF(AND(Anlagen!S5="",Vorschlag_nutzen=1,Anlagen!R5<>""),Anlagen!R5,C5))) -> 6 | E5: =IF(C5=A5,IF(COUNTIF($C$5:$C$92,A5)>1,"Gateway-Standort","eigenständig"),"über "&IFERROR(INDEX(Anlagen!$B$5:$B$92,MATCH(D5,Anlagen!$A$5:$A$92,0)),"?")) -> über Altstadt Forst | F5: =IF(C5=A5,0,IF(Anlagen!V5<>"",Anlagen!V5/1000,IFERROR(SQRT((Anlagen!N5-INDEX(Anlagen!$N$5:$N$92,MATCH(D5,Anlagen!$A$5:$A$92,0)))^2+(Anlagen!O5-INDEX(Anlagen!$O$5:$O$92,MATCH(D5,Anlagen!$A$5:$A$92,0)))^2),0))) -> 0.89643739 | G5: =IF(C5=A5,0,IF(Anlagen!V5<>"",Anlagen!V5,F5*1000*Umweg)) -> 1165.3686 | H5: =IF(C5=A5,0,(G5*(P_Faser+P_Tiefbau)+2*P_SFP+P_MontZul)*EK) -> 2310.805 | I5: =IF(C5=A5,0,(P_Saeule+P_Flex+P_NT+P_Halter+P_Luefter+P_Spleiss+P_Ueber)*EK) -> 851.326 | J5: =IF(Anlagen!U5<>"",Anlagen!U5,IF(C5=A5,500,1000)+ROW()) -> 1005 | K5: =SUMIFS(Anlagen!$F$5:$F$92,$C$5:$C$92,C5,$J$5:$J$92,"<"&J5) -> 127 | L5: =INT(K5/PG)+1 -> 3 | M5: =MAX(L5,CEILING((K5+Anlagen!F5)/PG,1)) -> 3 | N5: =IFERROR(INDEX(Anlagen!$B$5:$B$92,MATCH(C5,Anlagen!$A$5:$A$92,0)),"?")&": GW "&L5&IF(M5>L5,"–"&M5,"") -> Fohrder Landstraße: GW 3 | O5: =Buchungsquote!V5 -> 18.709091 | P5: =IF(ISNA(MATCH(C5,Anlagen!$A$5:$A$92,0)),"Fehler: Standort unbekannt",IF(C5=A5,"OK",IF(INDEX($C$5:$C$92,MATCH(C5,Anlagen!$A$5:$A$92,0))<>C5,"Fehler: Standort hängt selbst an anderem Standort",IF(D5=A5,"Fehler: Zuleitung von sich selbst",IF(ISNA(MATCH(D5,Anlagen!$A$5:$A$92,0)),"Fehler: Zuleitung unbekannt",IF(INDEX($C$5:$C$92,MATCH(D5,Anlagen!$A$5:$A$92,0))<>C5,"Fehler: Zuleitung hängt an anderem Standort","OK")))))) -> OK | Q5: =Anlagen!AA5 -> MAERZ | R5: =IF(Anlagen!AB5<>"",Anlagen!AB5,COUNTIFS($C$5:$C$92,C5,$J$5:$J$92,"<"&J5)+1) -> 2 | S5: =1000+200*(R5-1)+1 -> 1201 | T5: =1000+200*(R5-1)+Anlagen!F5 -> 1230 | U5: =100+A5 -> 101 | V5: =200+A5 -> 201 | W5: =300+A5 -> 301 | X5: ="10."&A5&".1.0/24" -> 10.1.1.0/24 | Y5: =IF(R5>15,"Fehler: VLAN-Block über 15",IF(COUNTIFS($C$5:$C$92,C5,$R$5:$R$92,R5)>1,"Fehler: VLAN-Block am Standort doppelt",IF(COUNTIF($Q$5:$Q$92,Q5)>1,"Fehler: Kürzel doppelt",IF(Anlagen!F5>199,"Fehler: mehr als 199 Parzellen","OK")))) -> OK
A6: =Anlagen!A6 -> 2 | B6: =Anlagen!B6 -> Abendfrieden | C6: =IF(Anlagen!S6<>"",Anlagen!S6,IF(Vorschlag_nutzen=1,Anlagen!Q6,A6)) -> 41 | D6: =IF(C6=A6,"",IF(Anlagen!T6<>"",Anlagen!T6,IF(AND(Anlagen!S6="",Vorschlag_nutzen=1,Anlagen!R6<>""),Anlagen!R6,C6))) -> 20 | E6: =IF(C6=A6,IF(COUNTIF($C$5:$C$92,A6)>1,"Gateway-Standort","eigenständig"),"über "&IFERROR(INDEX(Anlagen!$B$5:$B$92,MATCH(D6,Anlagen!$A$5:$A$92,0)),"?")) -> über Buchenweg | F6: =IF(C6=A6,0,IF(Anlagen!V6<>"",Anlagen!V6/1000,IFERROR(SQRT((Anlagen!N6-INDEX(Anlagen!$N$5:$N$92,MATCH(D6,Anlagen!$A$5:$A$92,0)))^2+(Anlagen!O6-INDEX(Anlagen!$O$5:$O$92,MATCH(D6,Anlagen!$A$5:$A$92,0)))^2),0))) -> 0.47539457 | G6: =IF(C6=A6,0,IF(Anlagen!V6<>"",Anlagen!V6,F6*1000*Umweg)) -> 618.01294 | H6: =IF(C6=A6,0,(G6*(P_Faser+P_Tiefbau)+2*P_SFP+P_MontZul)*EK) -> 1333.7751 | I6: =IF(C6=A6,0,(P_Saeule+P_Flex+P_NT+P_Halter+P_Luefter+P_Spleiss+P_Ueber)*EK) -> 851.326 | J6: =IF(Anlagen!U6<>"",Anlagen!U6,IF(C6=A6,500,1000)+ROW()) -> 1006 | K6: =SUMIFS(Anlagen!$F$5:$F$92,$C$5:$C$92,C6,$J$5:$J$92,"<"&J6) -> 139 | L6: =INT(K6/PG)+1 -> 3 | M6: =MAX(L6,CEILING((K6+Anlagen!F6)/PG,1)) -> 4 | N6: =IFERROR(INDEX(Anlagen!$B$5:$B$92,MATCH(C6,Anlagen!$A$5:$A$92,0)),"?")&": GW "&L6&IF(M6>L6,"–"&M6,"") -> Glück im Winkel: GW 3–4 | O6: =Buchungsquote!V6 -> 40.149728 | P6: =IF(ISNA(MATCH(C6,Anlagen!$A$5:$A$92,0)),"Fehler: Standort unbekannt",IF(C6=A6,"OK",IF(INDEX($C$5:$C$92,MATCH(C6,Anlagen!$A$5:$A$92,0))<>C6,"Fehler: Standort hängt selbst an anderem Standort",IF(D6=A6,"Fehler: Zuleitung von sich selbst",IF(ISNA(MATCH(D6,Anlagen!$A$5:$A$92,0)),"Fehler: Zuleitung unbekannt",IF(INDEX($C$5:$C$92,MATCH(D6,Anlagen!$A$5:$A$92,0))<>C6,"Fehler: Zuleitung hängt an anderem Standort","OK")))))) -> OK | Q6: =Anlagen!AA6 -> ABFRI | R6: =IF(Anlagen!AB6<>"",Anlagen!AB6,COUNTIFS($C$5:$C$92,C6,$J$5:$J$92,"<"&J6)+1) -> 2 | S6: =1000+200*(R6-1)+1 -> 1201 | T6: =1000+200*(R6-1)+Anlagen!F6 -> 1275 | U6: =100+A6 -> 102 | V6: =200+A6 -> 202 | W6: =300+A6 -> 302 | X6: ="10."&A6&".1.0/24" -> 10.2.1.0/24 | Y6: =IF(R6>15,"Fehler: VLAN-Block über 15",IF(COUNTIFS($C$5:$C$92,C6,$R$5:$R$92,R6)>1,"Fehler: VLAN-Block am Standort doppelt",IF(COUNTIF($Q$5:$Q$92,Q6)>1,"Fehler: Kürzel doppelt",IF(Anlagen!F6>199,"Fehler: mehr als 199 Parzellen","OK")))) -> OK
A7: =Anlagen!A7 -> 3 | B7: =Anlagen!B7 -> Abendrot | C7: =IF(Anlagen!S7<>"",Anlagen!S7,IF(Vorschlag_nutzen=1,Anlagen!Q7,A7)) -> 30 | D7: =IF(C7=A7,"",IF(Anlagen!T7<>"",Anlagen!T7,IF(AND(Anlagen!S7="",Vorschlag_nutzen=1,Anlagen!R7<>""),Anlagen!R7,C7))) -> 30 | E7: =IF(C7=A7,IF(COUNTIF($C$5:$C$92,A7)>1,"Gateway-Standort","eigenständig"),"über "&IFERROR(INDEX(Anlagen!$B$5:$B$92,MATCH(D7,Anlagen!$A$5:$A$92,0)),"?")) -> über Feierabend | F7: =IF(C7=A7,0,IF(Anlagen!V7<>"",Anlagen!V7/1000,IFERROR(SQRT((Anlagen!N7-INDEX(Anlagen!$N$5:$N$92,MATCH(D7,Anlagen!$A$5:$A$92,0)))^2+(Anlagen!O7-INDEX(Anlagen!$O$5:$O$92,MATCH(D7,Anlagen!$A$5:$A$92,0)))^2),0))) -> 1.1872658 | G7: =IF(C7=A7,0,IF(Anlagen!V7<>"",Anlagen!V7,F7*1000*Umweg)) -> 1543.4455 | H7: =IF(C7=A7,0,(G7*(P_Faser+P_Tiefbau)+2*P_SFP+P_MontZul)*EK) -> 2985.6722 | I7: =IF(C7=A7,0,(P_Saeule+P_Flex+P_NT+P_Halter+P_Luefter+P_Spleiss+P_Ueber)*EK) -> 851.326 | J7: =IF(Anlagen!U7<>"",Anlagen!U7,IF(C7=A7,500,1000)+ROW()) -> 1007 | K7: =SUMIFS(Anlagen!$F$5:$F$92,$C$5:$C$92,C7,$J$5:$J$92,"<"&J7) -> 190 | L7: =INT(K7/PG)+1 -> 4 | M7: =MAX(L7,CEILING((K7+Anlagen!F7)/PG,1)) -> 6 | N7: =IFERROR(INDEX(Anlagen!$B$5:$B$92,MATCH(C7,Anlagen!$A$5:$A$92,0)),"?")&": GW "&L7&IF(M7>L7,"–"&M7,"") -> Feierabend: GW 4–6 | O7: =Buchungsquote!V7 -> 77.934457 | P7: =IF(ISNA(MATCH(C7,Anlagen!$A$5:$A$92,0)),"Fehler: Standort unbekannt",IF(C7=A7,"OK",IF(INDEX($C$5:$C$92,MATCH(C7,Anlagen!$A$5:$A$92,0))<>C7,"Fehler: Standort hängt selbst an anderem Standort",IF(D7=A7,"Fehler: Zuleitung von sich selbst",IF(ISNA(MATCH(D7,Anlagen!$A$5:$A$92,0)),"Fehler: Zuleitung unbekannt",IF(INDEX($C$5:$C$92,MATCH(D7,Anlagen!$A$5:$A$92,0))<>C7,"Fehler: Zuleitung hängt an anderem Standort","OK")))))) -> OK | Q7: =Anlagen!AA7 -> ABROT | R7: =IF(Anlagen!AB7<>"",Anlagen!AB7,COUNTIFS($C$5:$C$92,C7,$J$5:$J$92,"<"&J7)+1) -> 2 | S7: =1000+200*(R7-1)+1 -> 1201 | T7: =1000+200*(R7-1)+Anlagen!F7 -> 1337 | U7: =100+A7 -> 103 | V7: =200+A7 -> 203 | W7: =300+A7 -> 303 | X7: ="10."&A7&".1.0/24" -> 10.3.1.0/24 | Y7: =IF(R7>15,"Fehler: VLAN-Block über 15",IF(COUNTIFS($C$5:$C$92,C7,$R$5:$R$92,R7)>1,"Fehler: VLAN-Block am Standort doppelt",IF(COUNTIF($Q$5:$Q$92,Q7)>1,"Fehler: Kürzel doppelt",IF(Anlagen!F7>199,"Fehler: mehr als 199 Parzellen","OK")))) -> OK
A8: =Anlagen!A8 -> 4 | B8: =Anlagen!B8 -> Abendruh | C8: =IF(Anlagen!S8<>"",Anlagen!S8,IF(Vorschlag_nutzen=1,Anlagen!Q8,A8)) -> 30 | D8: =IF(C8=A8,"",IF(Anlagen!T8<>"",Anlagen!T8,IF(AND(Anlagen!S8="",Vorschlag_nutzen=1,Anlagen!R8<>""),Anlagen!R8,C8))) -> 30 | E8: =IF(C8=A8,IF(COUNTIF($C$5:$C$92,A8)>1,"Gateway-Standort","eigenständig"),"über "&IFERROR(INDEX(Anlagen!$B$5:$B$92,MATCH(D8,Anlagen!$A$5:$A$92,0)),"?")) -> über Feierabend | F8: =IF(C8=A8,0,IF(Anlagen!V8<>"",Anlagen!V8/1000,IFERROR(SQRT((Anlagen!N8-INDEX(Anlagen!$N$5:$N$92,MATCH(D8,Anlagen!$A$5:$A$92,0)))^2+(Anlagen!O8-INDEX(Anlagen!$O$5:$O$92,MATCH(D8,Anlagen!$A$5:$A$92,0)))^2),0))) -> 0.83630138 | G8: =IF(C8=A8,0,IF(Anlagen!V8<>"",Anlagen!V8,F8*1000*Umweg)) -> 1087.1918 | H8: =IF(C8=A8,0,(G8*(P_Faser+P_Tiefbau)+2*P_SFP+P_MontZul)*EK) -> 2171.2594 | I8: =IF(C8=A8,0,(P_Saeule+P_Flex+P_NT+P_Halter+P_Luefter+P_Spleiss+P_Ueber)*EK) -> 851.326 | J8: =IF(Anlagen!U8<>"",Anlagen!U8,IF(C8=A8,500,1000)+ROW()) -> 1008 | K8: =SUMIFS(Anlagen!$F$5:$F$92,$C$5:$C$92,C8,$J$5:$J$92,"<"&J8) -> 327 | L8: =INT(K8/PG)+1 -> 6 | M8: =MAX(L8,CEILING((K8+Anlagen!F8)/PG,1)) -> 9 | N8: =IFERROR(INDEX(Anlagen!$B$5:$B$92,MATCH(C8,Anlagen!$A$5:$A$92,0)),"?")&": GW "&L8&IF(M8>L8,"–"&M8,"") -> Feierabend: GW 6–9 | O8: =Buchungsquote!V8 -> 79.553733 | P8: =IF(ISNA(MATCH(C8,Anlagen!$A$5:$A$92,0)),"Fehler: Standort unbekannt",IF(C8=A8,"OK",IF(INDEX($C$5:$C$92,MATCH(C8,Anlagen!$A$5:$A$92,0))<>C8,"Fehler: Standort hängt selbst an anderem Standort",IF(D8=A8,"Fehler: Zuleitung von sich selbst",IF(ISNA(MATCH(D8,Anlagen!$A$5:$A$92,0)),"Fehler: Zuleitung unbekannt",IF(INDEX($C$5:$C$92,MATCH(D8,Anlagen!$A$5:$A$92,0))<>C8,"Fehler: Zuleitung hängt an anderem Standort","OK")))))) -> OK | Q8: =Anlagen!AA8 -> ABRUH | R8: =IF(Anlagen!AB8<>"",Anlagen!AB8,COUNTIFS($C$5:$C$92,C8,$J$5:$J$92,"<"&J8)+1) -> 3 | S8: =1000+200*(R8-1)+1 -> 1401 | T8: =1000+200*(R8-1)+Anlagen!F8 -> 1542 | U8: =100+A8 -> 104 | V8: =200+A8 -> 204 | W8: =300+A8 -> 304 | X8: ="10."&A8&".1.0/24" -> 10.4.1.0/24 | Y8: =IF(R8>15,"Fehler: VLAN-Block über 15",IF(COUNTIFS($C$5:$C$92,C8,$R$5:$R$92,R8)>1,"Fehler: VLAN-Block am Standort doppelt",IF(COUNTIF($Q$5:$Q$92,Q8)>1,"Fehler: Kürzel doppelt",IF(Anlagen!F8>199,"Fehler: mehr als 199 Parzellen","OK")))) -> OK
A9: =Anlagen!A9 -> 5 | B9: =Anlagen!B9 -> Abendsonne | C9: =IF(Anlagen!S9<>"",Anlagen!S9,IF(Vorschlag_nutzen=1,Anlagen!Q9,A9)) -> 23 | D9: =IF(C9=A9,"",IF(Anlagen!T9<>"",Anlagen!T9,IF(AND(Anlagen!S9="",Vorschlag_nutzen=1,Anlagen!R9<>""),Anlagen!R9,C9))) -> 24 | E9: =IF(C9=A9,IF(COUNTIF($C$5:$C$92,A9)>1,"Gateway-Standort","eigenständig"),"über "&IFERROR(INDEX(Anlagen!$B$5:$B$92,MATCH(D9,Anlagen!$A$5:$A$92,0)),"?")) -> über Einheit | F9: =IF(C9=A9,0,IF(Anlagen!V9<>"",Anlagen!V9/1000,IFERROR(SQRT((Anlagen!N9-INDEX(Anlagen!$N$5:$N$92,MATCH(D9,Anlagen!$A$5:$A$92,0)))^2+(Anlagen!O9-INDEX(Anlagen!$O$5:$O$92,MATCH(D9,Anlagen!$A$5:$A$92,0)))^2),0))) -> 0.41725292 | G9: =IF(C9=A9,0,IF(Anlagen!V9<>"",Anlagen!V9,F9*1000*Umweg)) -> 542.4288 | H9: =IF(C9=A9,0,(G9*(P_Faser+P_Tiefbau)+2*P_SFP+P_MontZul)*EK) -> 1198.8574 | I9: =IF(C9=A9,0,(P_Saeule+P_Flex+P_NT+P_Halter+P_Luefter+P_Spleiss+P_Ueber)*EK) -> 851.326 | J9: =IF(Anlagen!U9<>"",Anlagen!U9,IF(C9=A9,500,1000)+ROW()) -> 1009 | K9: =SUMIFS(Anlagen!$F$5:$F$92,$C$5:$C$92,C9,$J$5:$J$92,"<"&J9) -> 123 | L9: =INT(K9/PG)+1 -> 3 | M9: =MAX(L9,CEILING((K9+Anlagen!F9)/PG,1)) -> 4 | N9: =IFERROR(INDEX(Anlagen!$B$5:$B$92,MATCH(C9,Anlagen!$A$5:$A$92,0)),"?")&": GW "&L9&IF(M9>L9,"–"&M9,"") -> Eigener Fleiß: GW 3–4 | O9: =Buchungsquote!V9 -> 33.75 | P9: =IF(ISNA(MATCH(C9,Anlagen!$A$5:$A$92,0)),"Fehler: Standort unbekannt",IF(C9=A9,"OK",IF(INDEX($C$5:$C$92,MATCH(C9,Anlagen!$A$5:$A$92,0))<>C9,"Fehler: Standort hängt selbst an anderem Standort",IF(D9=A9,"Fehler: Zuleitung von sich selbst",IF(ISNA(MATCH(D9,Anlagen!$A$5:$A$92,0)),"Fehler: Zuleitung unbekannt",IF(INDEX($C$5:$C$92,MATCH(D9,Anlagen!$A$5:$A$92,0))<>C9,"Fehler: Zuleitung hängt an anderem Standort","OK")))))) -> OK | Q9: =Anlagen!AA9 -> ABSON | R9: =IF(Anlagen!AB9<>"",Anlagen!AB9,COUNTIFS($C$5:$C$92,C9,$J$5:$J$92,"<"&J9)+1) -> 2 | S9: =1000+200*(R9-1)+1 -> 1201 | T9: =1000+200*(R9-1)+Anlagen!F9 -> 1267 | U9: =100+A9 -> 105 | V9: =200+A9 -> 205 | W9: =300+A9 -> 305 | X9: ="10."&A9&".1.0/24" -> 10.5.1.0/24 | Y9: =IF(R9>15,"Fehler: VLAN-Block über 15",IF(COUNTIFS($C$5:$C$92,C9,$R$5:$R$92,R9)>1,"Fehler: VLAN-Block am Standort doppelt",IF(COUNTIF($Q$5:$Q$92,Q9)>1,"Fehler: Kürzel doppelt",IF(Anlagen!F9>199,"Fehler: mehr als 199 Parzellen","OK")))) -> OK
A10: =Anlagen!A10 -> 6 | B10: =Anlagen!B10 -> Altstadt Forst | C10: =IF(Anlagen!S10<>"",Anlagen!S10,IF(Vorschlag_nutzen=1,Anlagen!Q10,A10)) -> 33 | D10: =IF(C10=A10,"",IF(Anlagen!T10<>"",Anlagen!T10,IF(AND(Anlagen!S10="",Vorschlag_nutzen=1,Anlagen!R10<>""),Anlagen!R10,C10))) -> 33 | E10: =IF(C10=A10,IF(COUNTIF($C$5:$C$92,A10)>1,"Gateway-Standort","eigenständig"),"über "&IFERROR(INDEX(Anlagen!$B$5:$B$92,MATCH(D10,Anlagen!$A$5:$A$92,0)),"?")) -> über Fohrder Landstraße | F10: =IF(C10=A10,0,IF(Anlagen!V10<>"",Anlagen!V10/1000,IFERROR(SQRT((Anlagen!N10-INDEX(Anlagen!$N$5:$N$92,MATCH(D10,Anlagen!$A$5:$A$92,0)))^2+(Anlagen!O10-INDEX(Anlagen!$O$5:$O$92,MATCH(D10,Anlagen!$A$5:$A$92,0)))^2),0))) -> 0.45310043 | G10: =IF(C10=A10,0,IF(Anlagen!V10<>"",Anlagen!V10,F10*1000*Umweg)) -> 589.03056 | H10: =IF(C10=A10,0,(G10*(P_Faser+P_Tiefbau)+2*P_SFP+P_MontZul)*EK) -> 1282.0415 | I10: =IF(C10=A10,0,(P_Saeule+P_Flex+P_NT+P_Halter+P_Luefter+P_Spleiss+P_Ueber)*EK) -> 851.326 | J10: =IF(Anlagen!U10<>"",Anlagen!U10,IF(C10=A10,500,1000)+ROW()) -> 1010 | K10: =SUMIFS(Anlagen!$F$5:$F$92,$C$5:$C$92,C10,$J$5:$J$92,"<"&J10) -> 157 | L10: =INT(K10/PG)+1 -> 3 | M10: =MAX(L10,CEILING((K10+Anlagen!F10)/PG,1)) -> 5 | N10: =IFERROR(INDEX(Anlagen!$B$5:$B$92,MATCH(C10,Anlagen!$A$5:$A$92,0)),"?")&": GW "&L10&IF(M10>L10,"–"&M10,"") -> Fohrder Landstraße: GW 3–5 | O10: =Buchungsquote!V10 -> 49.300905 | P10: =IF(ISNA(MATCH(C10,Anlagen!$A$5:$A$92,0)),"Fehler: Standort unbekannt",IF(C10=A10,"OK",IF(INDEX($C$5:$C$92,MATCH(C10,Anlagen!$A$5:$A$92,0))<>C10,"Fehler: Standort hängt selbst an anderem Standort",IF(D10=A10,"Fehler: Zuleitung von sich selbst",IF(ISNA(MATCH(D10,Anlagen!$A$5:$A$92,0)),"Fehler: Zuleitung unbekannt",IF(INDEX($C$5:$C$92,MATCH(D10,Anlagen!$A$5:$A$92,0))<>C10,"Fehler: Zuleitung hängt an anderem Standort","OK")))))) -> OK | Q10: =Anlagen!AA10 -> ALTFO | R10: =IF(Anlagen!AB10<>"",Anlagen!AB10,COUNTIFS($C$5:$C$92,C10,$J$5:$J$92,"<"&J10)+1) -> 3 | S10: =1000+200*(R10-1)+1 -> 1401 | T10: =1000+200*(R10-1)+Anlagen!F10 -> 1488 | U10: =100+A10 -> 106 | V10: =200+A10 -> 206 | W10: =300+A10 -> 306 | X10: ="10."&A10&".1.0/24" -> 10.6.1.0/24 | Y10: =IF(R10>15,"Fehler: VLAN-Block über 15",IF(COUNTIFS($C$5:$C$92,C10,$R$5:$R$92,R10)>1,"Fehler: VLAN-Block am Standort doppelt",IF(COUNTIF($Q$5:$Q$92,Q10)>1,"Fehler: Kürzel doppelt",IF(Anlagen!F10>199,"Fehler: mehr als 199 Parzellen","OK")))) -> OK
A11: =Anlagen!A11 -> 7 | B11: =Anlagen!B11 -> Am Beetzseeufer | C11: =IF(Anlagen!S11<>"",Anlagen!S11,IF(Vorschlag_nutzen=1,Anlagen!Q11,A11)) -> 49 | D11: =IF(C11=A11,"",IF(Anlagen!T11<>"",Anlagen!T11,IF(AND(Anlagen!S11="",Vorschlag_nutzen=1,Anlagen!R11<>""),Anlagen!R11,C11))) -> 88 | E11: =IF(C11=A11,IF(COUNTIF($C$5:$C$92,A11)>1,"Gateway-Standort","eigenständig"),"über "&IFERROR(INDEX(Anlagen!$B$5:$B$92,MATCH(D11,Anlagen!$A$5:$A$92,0)),"?")) -> über Zur Insel | F11: =IF(C11=A11,0,IF(Anlagen!V11<>"",Anlagen!V11/1000,IFERROR(SQRT((Anlagen!N11-INDEX(Anlagen!$N$5:$N$92,MATCH(D11,Anlagen!$A$5:$A$92,0)))^2+(Anlagen!O11-INDEX(Anlagen!$O$5:$O$92,MATCH(D11,Anlagen!$A$5:$A$92,0)))^2),0))) -> 0.93300589 | G11: =IF(C11=A11,0,IF(Anlagen!V11<>"",Anlagen!V11,F11*1000*Umweg)) -> 1212.9077 | H11: =IF(C11=A11,0,(G11*(P_Faser+P_Tiefbau)+2*P_SFP+P_MontZul)*EK) -> 2395.6622 | I11: =IF(C11=A11,0,(P_Saeule+P_Flex+P_NT+P_Halter+P_Luefter+P_Spleiss+P_Ueber)*EK) -> 851.326 | J11: =IF(Anlagen!U11<>"",Anlagen!U11,IF(C11=A11,500,1000)+ROW()) -> 1011 | K11: =SUMIFS(Anlagen!$F$5:$F$92,$C$5:$C$92,C11,$J$5:$J$92,"<"&J11) -> 110 | L11: =INT(K11/PG)+1 -> 3 | M11: =MAX(L11,CEILING((K11+Anlagen!F11)/PG,1)) -> 4 | N11: =IFERROR(INDEX(Anlagen!$B$5:$B$92,MATCH(C11,Anlagen!$A$5:$A$92,0)),"?")&": GW "&L11&IF(M11>L11,"–"&M11,"") -> Helgoland: GW 3–4 | O11: =Buchungsquote!V11 -> 48.733591 | P11: =IF(ISNA(MATCH(C11,Anlagen!$A$5:$A$92,0)),"Fehler: Standort unbekannt",IF(C11=A11,"OK",IF(INDEX($C$5:$C$92,MATCH(C11,Anlagen!$A$5:$A$92,0))<>C11,"Fehler: Standort hängt selbst an anderem Standort",IF(D11=A11,"Fehler: Zuleitung von sich selbst",IF(ISNA(MATCH(D11,Anlagen!$A$5:$A$92,0)),"Fehler: Zuleitung unbekannt",IF(INDEX($C$5:$C$92,MATCH(D11,Anlagen!$A$5:$A$92,0))<>C11,"Fehler: Zuleitung hängt an anderem Standort","OK")))))) -> OK | Q11: =Anlagen!AA11 -> BEETZ | R11: =IF(Anlagen!AB11<>"",Anlagen!AB11,COUNTIFS($C$5:$C$92,C11,$J$5:$J$92,"<"&J11)+1) -> 2 | S11: =1000+200*(R11-1)+1 -> 1201 | T11: =1000+200*(R11-1)+Anlagen!F11 -> 1277 | U11: =100+A11 -> 107 | V11: =200+A11 -> 207 | W11: =300+A11 -> 307 | X11: ="10."&A11&".1.0/24" -> 10.7.1.0/24 | Y11: =IF(R11>15,"Fehler: VLAN-Block über 15",IF(COUNTIFS($C$5:$C$92,C11,$R$5:$R$92,R11)>1,"Fehler: VLAN-Block am Standort doppelt",IF(COUNTIF($Q$5:$Q$92,Q11)>1,"Fehler: Kürzel doppelt",IF(Anlagen!F11>199,"Fehler: mehr als 199 Parzellen","OK")))) -> OK
A12: =Anlagen!A12 -> 8 | B12: =Anlagen!B12 -> Am Büttelhandfassgraben | C12: =IF(Anlagen!S12<>"",Anlagen!S12,IF(Vorschlag_nutzen=1,Anlagen!Q12,A12)) -> 49 | D12: =IF(C12=A12,"",IF(Anlagen!T12<>"",Anlagen!T12,IF(AND(Anlagen!S12="",Vorschlag_nutzen=1,Anlagen!R12<>""),Anlagen!R12,C12))) -> 50 | E12: =IF(C12=A12,IF(COUNTIF($C$5:$C$92,A12)>1,"Gateway-Standort","eigenständig"),"über "&IFERROR(INDEX(Anlagen!$B$5:$B$92,MATCH(D12,Anlagen!$A$5:$A$92,0)),"?")) -> über Hoffnung | F12: =IF(C12=A12,0,IF(Anlagen!V12<>"",Anlagen!V12/1000,IFERROR(SQRT((Anlagen!N12-INDEX(Anlagen!$N$5:$N$92,MATCH(D12,Anlagen!$A$5:$A$92,0)))^2+(Anlagen!O12-INDEX(Anlagen!$O$5:$O$92,MATCH(D12,Anlagen!$A$5:$A$92,0)))^2),0))) -> 0.067082039 | G12: =IF(C12=A12,0,IF(Anlagen!V12<>"",Anlagen!V12,F12*1000*Umweg)) -> 87.206651 | H12: =IF(C12=A12,0,(G12*(P_Faser+P_Tiefbau)+2*P_SFP+P_MontZul)*EK) -> 386.28587 | I12: =IF(C12=A12,0,(P_Saeule+P_Flex+P_NT+P_Halter+P_Luefter+P_Spleiss+P_Ueber)*EK) -> 851.326 | J12: =IF(Anlagen!U12<>"",Anlagen!U12,IF(C12=A12,500,1000)+ROW()) -> 1012 | K12: =SUMIFS(Anlagen!$F$5:$F$92,$C$5:$C$92,C12,$J$5:$J$92,"<"&J12) -> 187 | L12: =INT(K12/PG)+1 -> 4 | M12: =MAX(L12,CEILING((K12+Anlagen!F12)/PG,1)) -> 4 | N12: =IFERROR(INDEX(Anlagen!$B$5:$B$92,MATCH(C12,Anlagen!$A$5:$A$92,0)),"?")&": GW "&L12&IF(M12>L12,"–"&M12,"") -> Helgoland: GW 4 | O12: =Buchungsquote!V12 -> 3.3928571 | P12: =IF(ISNA(MATCH(C12,Anlagen!$A$5:$A$92,0)),"Fehler: Standort unbekannt",IF(C12=A12,"OK",IF(INDEX($C$5:$C$92,MATCH(C12,Anlagen!$A$5:$A$92,0))<>C12,"Fehler: Standort hängt selbst an anderem Standort",IF(D12=A12,"Fehler: Zuleitung von sich selbst",IF(ISNA(MATCH(D12,Anlagen!$A$5:$A$92,0)),"Fehler: Zuleitung unbekannt",IF(INDEX($C$5:$C$92,MATCH(D12,Anlagen!$A$5:$A$92,0))<>C12,"Fehler: Zuleitung hängt an anderem Standort","OK")))))) -> OK | Q12: =Anlagen!AA12 -> BUETT | R12: =IF(Anlagen!AB12<>"",Anlagen!AB12,COUNTIFS($C$5:$C$92,C12,$J$5:$J$92,"<"&J12)+1) -> 3 | S12: =1000+200*(R12-1)+1 -> 1401 | T12: =1000+200*(R12-1)+Anlagen!F12 -> 1405 | U12: =100+A12 -> 108 | V12: =200+A12 -> 208 | W12: =300+A12 -> 308 | X12: ="10."&A12&".1.0/24" -> 10.8.1.0/24 | Y12: =IF(R12>15,"Fehler: VLAN-Block über 15",IF(COUNTIFS($C$5:$C$92,C12,$R$5:$R$92,R12)>1,"Fehler: VLAN-Block am Standort doppelt",IF(COUNTIF($Q$5:$Q$92,Q12)>1,"Fehler: Kürzel doppelt",IF(Anlagen!F12>199,"Fehler: mehr als 199 Parzellen","OK")))) -> OK
A13: =Anlagen!A13 -> 9 | B13: =Anlagen!B13 -> Am Eichenweg | C13: =IF(Anlagen!S13<>"",Anlagen!S13,IF(Vorschlag_nutzen=1,Anlagen!Q13,A13)) -> 17 | D13: =IF(C13=A13,"",IF(Anlagen!T13<>"",Anlagen!T13,IF(AND(Anlagen!S13="",Vorschlag_nutzen=1,Anlagen!R13<>""),Anlagen!R13,C13))) -> 17 | E13: =IF(C13=A13,IF(COUNTIF($C$5:$C$92,A13)>1,"Gateway-Standort","eigenständig"),"über "&IFERROR(INDEX(Anlagen!$B$5:$B$92,MATCH(D13,Anlagen!$A$5:$A$92,0)),"?")) -> über Birkenwäldchen | F13: =IF(C13=A13,0,IF(Anlagen!V13<>"",Anlagen!V13/1000,IFERROR(SQRT((Anlagen!N13-INDEX(Anlagen!$N$5:$N$92,MATCH(D13,Anlagen!$A$5:$A$92,0)))^2+(Anlagen!O13-INDEX(Anlagen!$O$5:$O$92,MATCH(D13,Anlagen!$A$5:$A$92,0)))^2),0))) -> 1.3792752 | G13: =IF(C13=A13,0,IF(Anlagen!V13<>"",Anlagen!V13,F13*1000*Umweg)) -> 1793.0577 | H13: =IF(C13=A13,0,(G13*(P_Faser+P_Tiefbau)+2*P_SFP+P_MontZul)*EK) -> 3431.23 | I13: =IF(C13=A13,0,(P_Saeule+P_Flex+P_NT+P_Halter+P_Luefter+P_Spleiss+P_Ueber)*EK) -> 851.326 | J13: =IF(Anlagen!U13<>"",Anlagen!U13,IF(C13=A13,500,1000)+ROW()) -> 1013 | K13: =SUMIFS(Anlagen!$F$5:$F$92,$C$5:$C$92,C13,$J$5:$J$92,"<"&J13) -> 56 | L13: =INT(K13/PG)+1 -> 2 | M13: =MAX(L13,CEILING((K13+Anlagen!F13)/PG,1)) -> 2 | N13: =IFERROR(INDEX(Anlagen!$B$5:$B$92,MATCH(C13,Anlagen!$A$5:$A$92,0)),"?")&": GW "&L13&IF(M13>L13,"–"&M13,"") -> Birkenwäldchen: GW 2 | O13: =Buchungsquote!V13 -> 30.1716 | P13: =IF(ISNA(MATCH(C13,Anlagen!$A$5:$A$92,0)),"Fehler: Standort unbekannt",IF(C13=A13,"OK",IF(INDEX($C$5:$C$92,MATCH(C13,Anlagen!$A$5:$A$92,0))<>C13,"Fehler: Standort hängt selbst an anderem Standort",IF(D13=A13,"Fehler: Zuleitung von sich selbst",IF(ISNA(MATCH(D13,Anlagen!$A$5:$A$92,0)),"Fehler: Zuleitung unbekannt",IF(INDEX($C$5:$C$92,MATCH(D13,Anlagen!$A$5:$A$92,0))<>C13,"Fehler: Zuleitung hängt an anderem Standort","OK")))))) -> OK | Q13: =Anlagen!AA13 -> EICHW | R13: =IF(Anlagen!AB13<>"",Anlagen!AB13,COUNTIFS($C$5:$C$92,C13,$J$5:$J$92,"<"&J13)+1) -> 2 | S13: =1000+200*(R13-1)+1 -> 1201 | T13: =1000+200*(R13-1)+Anlagen!F13 -> 1254 | U13: =100+A13 -> 109 | V13: =200+A13 -> 209 | W13: =300+A13 -> 309 | X13: ="10."&A13&".1.0/24" -> 10.9.1.0/24 | Y13: =IF(R13>15,"Fehler: VLAN-Block über 15",IF(COUNTIFS($C$5:$C$92,C13,$R$5:$R$92,R13)>1,"Fehler: VLAN-Block am Standort doppelt",IF(COUNTIF($Q$5:$Q$92,Q13)>1,"Fehler: Kürzel doppelt",IF(Anlagen!F13>199,"Fehler: mehr als 199 Parzellen","OK")))) -> OK
A14: =Anlagen!A14 -> 10 | B14: =Anlagen!B14 -> Am Jakobsgraben | C14: =IF(Anlagen!S14<>"",Anlagen!S14,IF(Vorschlag_nutzen=1,Anlagen!Q14,A14)) -> 17 | D14: =IF(C14=A14,"",IF(Anlagen!T14<>"",Anlagen!T14,IF(AND(Anlagen!S14="",Vorschlag_nutzen=1,Anlagen!R14<>""),Anlagen!R14,C14))) -> 27 | E14: =IF(C14=A14,IF(COUNTIF($C$5:$C$92,A14)>1,"Gateway-Standort","eigenständig"),"über "&IFERROR(INDEX(Anlagen!$B$5:$B$92,MATCH(D14,Anlagen!$A$5:$A$92,0)),"?")) -> über Eintracht II | F14: =IF(C14=A14,0,IF(Anlagen!V14<>"",Anlagen!V14/1000,IFERROR(SQRT((Anlagen!N14-INDEX(Anlagen!$N$5:$N$92,MATCH(D14,Anlagen!$A$5:$A$92,0)))^2+(Anlagen!O14-INDEX(Anlagen!$O$5:$O$92,MATCH(D14,Anlagen!$A$5:$A$92,0)))^2),0))) -> 1.121606 | G14: =IF(C14=A14,0,IF(Anlagen!V14<>"",Anlagen!V14,F14*1000*Umweg)) -> 1458.0878 | H14: =IF(C14=A14,0,(G14*(P_Faser+P_Tiefbau)+2*P_SFP+P_MontZul)*EK) -> 2833.3087 | I14: =IF(C14=A14,0,(P_Saeule+P_Flex+P_NT+P_Halter+P_Luefter+P_Spleiss+P_Ueber)*EK) -> 851.326 | J14: =IF(Anlagen!U14<>"",Anlagen!U14,IF(C14=A14,500,1000)+ROW()) -> 1014 | K14: =SUMIFS(Anlagen!$F$5:$F$92,$C$5:$C$92,C14,$J$5:$J$92,"<"&J14) -> 110 | L14: =INT(K14/PG)+1 -> 3 | M14: =MAX(L14,CEILING((K14+Anlagen!F14)/PG,1)) -> 3 | N14: =IFERROR(INDEX(Anlagen!$B$5:$B$92,MATCH(C14,Anlagen!$A$5:$A$92,0)),"?")&": GW "&L14&IF(M14>L14,"–"&M14,"") -> Birkenwäldchen: GW 3 | O14: =Buchungsquote!V14 -> 18.637201 | P14: =IF(ISNA(MATCH(C14,Anlagen!$A$5:$A$92,0)),"Fehler: Standort unbekannt",IF(C14=A14,"OK",IF(INDEX($C$5:$C$92,MATCH(C14,Anlagen!$A$5:$A$92,0))<>C14,"Fehler: Standort hängt selbst an anderem Standort",IF(D14=A14,"Fehler: Zuleitung von sich selbst",IF(ISNA(MATCH(D14,Anlagen!$A$5:$A$92,0)),"Fehler: Zuleitung unbekannt",IF(INDEX($C$5:$C$92,MATCH(D14,Anlagen!$A$5:$A$92,0))<>C14,"Fehler: Zuleitung hängt an anderem Standort","OK")))))) -> OK | Q14: =Anlagen!AA14 -> JAKGR | R14: =IF(Anlagen!AB14<>"",Anlagen!AB14,COUNTIFS($C$5:$C$92,C14,$J$5:$J$92,"<"&J14)+1) -> 3 | S14: =1000+200*(R14-1)+1 -> 1401 | T14: =1000+200*(R14-1)+Anlagen!F14 -> 1441 | U14: =100+A14 -> 110 | V14: =200+A14 -> 210 | W14: =300+A14 -> 310 | X14: ="10."&A14&".1.0/24" -> 10.10.1.0/24 | Y14: =IF(R14>15,"Fehler: VLAN-Block über 15",IF(COUNTIFS($C$5:$C$92,C14,$R$5:$R$92,R14)>1,"Fehler: VLAN-Block am Standort doppelt",IF(COUNTIF($Q$5:$Q$92,Q14)>1,"Fehler: Kürzel doppelt",IF(Anlagen!F14>199,"Fehler: mehr als 199 Parzellen","OK")))) -> OK
A15: =Anlagen!A15 -> 11 | B15: =Anlagen!B15 -> Am Schafdamm | C15: =IF(Anlagen!S15<>"",Anlagen!S15,IF(Vorschlag_nutzen=1,Anlagen!Q15,A15)) -> 33 | D15: =IF(C15=A15,"",IF(Anlagen!T15<>"",Anlagen!T15,IF(AND(Anlagen!S15="",Vorschlag_nutzen=1,Anlagen!R15<>""),Anlagen!R15,C15))) -> 12 | E15: =IF(C15=A15,IF(COUNTIF($C$5:$C$92,A15)>1,"Gateway-Standort","eigenständig"),"über "&IFERROR(INDEX(Anlagen!$B$5:$B$92,MATCH(D15,Anlagen!$A$5:$A$92,0)),"?")) -> über Am Schlangenpfad | F15: =IF(C15=A15,0,IF(Anlagen!V15<>"",Anlagen!V15/1000,IFERROR(SQRT((Anlagen!N15-INDEX(Anlagen!$N$5:$N$92,MATCH(D15,Anlagen!$A$5:$A$92,0)))^2+(Anlagen!O15-INDEX(Anlagen!$O$5:$O$92,MATCH(D15,Anlagen!$A$5:$A$92,0)))^2),0))) -> 0.32984845 | G15: =IF(C15=A15,0,IF(Anlagen!V15<>"",Anlagen!V15,F15*1000*Umweg)) -> 428.80299 | H15: =IF(C15=A15,0,(G15*(P_Faser+P_Tiefbau)+2*P_SFP+P_MontZul)*EK) -> 996.03533 | I15: =IF(C15=A15,0,(P_Saeule+P_Flex+P_NT+P_Halter+P_Luefter+P_Spleiss+P_Ueber)*EK) -> 851.326 | J15: =IF(Anlagen!U15<>"",Anlagen!U15,IF(C15=A15,500,1000)+ROW()) -> 1015 | K15: =SUMIFS(Anlagen!$F$5:$F$92,$C$5:$C$92,C15,$J$5:$J$92,"<"&J15) -> 245 | L15: =INT(K15/PG)+1 -> 5 | M15: =MAX(L15,CEILING((K15+Anlagen!F15)/PG,1)) -> 5 | N15: =IFERROR(INDEX(Anlagen!$B$5:$B$92,MATCH(C15,Anlagen!$A$5:$A$92,0)),"?")&": GW "&L15&IF(M15>L15,"–"&M15,"") -> Fohrder Landstraße: GW 5 | O15: =Buchungsquote!V15 -> 4.6230769 | P15: =IF(ISNA(MATCH(C15,Anlagen!$A$5:$A$92,0)),"Fehler: Standort unbekannt",IF(C15=A15,"OK",IF(INDEX($C$5:$C$92,MATCH(C15,Anlagen!$A$5:$A$92,0))<>C15,"Fehler: Standort hängt selbst an anderem Standort",IF(D15=A15,"Fehler: Zuleitung von sich selbst",IF(ISNA(MATCH(D15,Anlagen!$A$5:$A$92,0)),"Fehler: Zuleitung unbekannt",IF(INDEX($C$5:$C$92,MATCH(D15,Anlagen!$A$5:$A$92,0))<>C15,"Fehler: Zuleitung hängt an anderem Standort","OK")))))) -> OK | Q15: =Anlagen!AA15 -> SCHAF | R15: =IF(Anlagen!AB15<>"",Anlagen!AB15,COUNTIFS($C$5:$C$92,C15,$J$5:$J$92,"<"&J15)+1) -> 4 | S15: =1000+200*(R15-1)+1 -> 1601 | T15: =1000+200*(R15-1)+Anlagen!F15 -> 1610 | U15: =100+A15 -> 111 | V15: =200+A15 -> 211 | W15: =300+A15 -> 311 | X15: ="10."&A15&".1.0/24" -> 10.11.1.0/24 | Y15: =IF(R15>15,"Fehler: VLAN-Block über 15",IF(COUNTIFS($C$5:$C$92,C15,$R$5:$R$92,R15)>1,"Fehler: VLAN-Block am Standort doppelt",IF(COUNTIF($Q$5:$Q$92,Q15)>1,"Fehler: Kürzel doppelt",IF(Anlagen!F15>199,"Fehler: mehr als 199 Parzellen","OK")))) -> OK
A16: =Anlagen!A16 -> 12 | B16: =Anlagen!B16 -> Am Schlangenpfad | C16: =IF(Anlagen!S16<>"",Anlagen!S16,IF(Vorschlag_nutzen=1,Anlagen!Q16,A16)) -> 33 | D16: =IF(C16=A16,"",IF(Anlagen!T16<>"",Anlagen!T16,IF(AND(Anlagen!S16="",Vorschlag_nutzen=1,Anlagen!R16<>""),Anlagen!R16,C16))) -> 13 | E16: =IF(C16=A16,IF(COUNTIF($C$5:$C$92,A16)>1,"Gateway-Standort","eigenständig"),"über "&IFERROR(INDEX(Anlagen!$B$5:$B$92,MATCH(D16,Anlagen!$A$5:$A$92,0)),"?")) -> über Am Waldesrand | F16: =IF(C16=A16,0,IF(Anlagen!V16<>"",Anlagen!V16/1000,IFERROR(SQRT((Anlagen!N16-INDEX(Anlagen!$N$5:$N$92,MATCH(D16,Anlagen!$A$5:$A$92,0)))^2+(Anlagen!O16-INDEX(Anlagen!$O$5:$O$92,MATCH(D16,Anlagen!$A$5:$A$92,0)))^2),0))) -> 0.27202941 | G16: =IF(C16=A16,0,IF(Anlagen!V16<>"",Anlagen!V16,F16*1000*Umweg)) -> 353.63823 | H16: =IF(C16=A16,0,(G16*(P_Faser+P_Tiefbau)+2*P_SFP+P_MontZul)*EK) -> 861.86625 | I16: =IF(C16=A16,0,(P_Saeule+P_Flex+P_NT+P_Halter+P_Luefter+P_Spleiss+P_Ueber)*EK) -> 851.326 | J16: =IF(Anlagen!U16<>"",Anlagen!U16,IF(C16=A16,500,1000)+ROW()) -> 1016 | K16: =SUMIFS(Anlagen!$F$5:$F$92,$C$5:$C$92,C16,$J$5:$J$92,"<"&J16) -> 255 | L16: =INT(K16/PG)+1 -> 5 | M16: =MAX(L16,CEILING((K16+Anlagen!F16)/PG,1)) -> 5 | N16: =IFERROR(INDEX(Anlagen!$B$5:$B$92,MATCH(C16,Anlagen!$A$5:$A$92,0)),"?")&": GW "&L16&IF(M16>L16,"–"&M16,"") -> Fohrder Landstraße: GW 5 | O16: =Buchungsquote!V16 -> 8.1536207 | P16: =IF(ISNA(MATCH(C16,Anlagen!$A$5:$A$92,0)),"Fehler: Standort unbekannt",IF(C16=A16,"OK",IF(INDEX($C$5:$C$92,MATCH(C16,Anlagen!$A$5:$A$92,0))<>C16,"Fehler: Standort hängt selbst an anderem Standort",IF(D16=A16,"Fehler: Zuleitung von sich selbst",IF(ISNA(MATCH(D16,Anlagen!$A$5:$A$92,0)),"Fehler: Zuleitung unbekannt",IF(INDEX($C$5:$C$92,MATCH(D16,Anlagen!$A$5:$A$92,0))<>C16,"Fehler: Zuleitung hängt an anderem Standort","OK")))))) -> OK | Q16: =Anlagen!AA16 -> SCHLA | R16: =IF(Anlagen!AB16<>"",Anlagen!AB16,COUNTIFS($C$5:$C$92,C16,$J$5:$J$92,"<"&J16)+1) -> 5 | S16: =1000+200*(R16-1)+1 -> 1801 | T16: =1000+200*(R16-1)+Anlagen!F16 -> 1819 | U16: =100+A16 -> 112 | V16: =200+A16 -> 212 | W16: =300+A16 -> 312 | X16: ="10."&A16&".1.0/24" -> 10.12.1.0/24 | Y16: =IF(R16>15,"Fehler: VLAN-Block über 15",IF(COUNTIFS($C$5:$C$92,C16,$R$5:$R$92,R16)>1,"Fehler: VLAN-Block am Standort doppelt",IF(COUNTIF($Q$5:$Q$92,Q16)>1,"Fehler: Kürzel doppelt",IF(Anlagen!F16>199,"Fehler: mehr als 199 Parzellen","OK")))) -> OK
... A92: =Anlagen!A92 -> 88 | B92: =Anlagen!B92 -> Zur Insel | C92: =IF(Anlagen!S92<>"",Anlagen!S92,IF(Vorschlag_nutzen=1,Anlagen!Q92,A92)) -> 49 | D92: =IF(C92=A92,"",IF(Anlagen!T92<>"",Anlagen!T92,IF(AND(Anlagen!S92="",Vorschlag_nutzen=1,Anlagen!R92<>""),Anlagen!R92,C92))) -> 49 | E92: =IF(C92=A92,IF(COUNTIF($C$5:$C$92,A92)>1,"Gateway-Standort","eigenständig"),"über "&IFERROR(INDEX(Anlagen!$B$5:$B$92,MATCH(D92,Anlagen!$A$5:$A$92,0)),"?")) -> über Helgoland | F92: =IF(C92=A92,0,IF(Anlagen!V92<>"",Anlagen!V92/1000,IFERROR(SQRT((Anlagen!N92-INDEX(Anlagen!$N$5:$N$92,MATCH(D92,Anlagen!$A$5:$A$92,0)))^2+(Anlagen!O92-INDEX(Anlagen!$O$5:$O$92,MATCH(D92,Anlagen!$A$5:$A$92,0)))^2),0))) -> 1.4741099 | G92: =IF(C92=A92,0,IF(Anlagen!V92<>"",Anlagen!V92,F92*1000*Umweg)) -> 1916.3429 | H92: =IF(C92=A92,0,(G92*(P_Faser+P_Tiefbau)+2*P_SFP+P_MontZul)*EK) -> 3651.294 | I92: =IF(C92=A92,0,(P_Saeule+P_Flex+P_NT+P_Halter+P_Luefter+P_Spleiss+P_Ueber)*EK) -> 851.326 | J92: =IF(Anlagen!U92<>"",Anlagen!U92,IF(C92=A92,500,1000)+ROW()) -> 1092 | K92: =SUMIFS(Anlagen!$F$5:$F$92,$C$5:$C$92,C92,$J$5:$J$92,"<"&J92) -> 463 | L92: =INT(K92/PG)+1 -> 9 | M92: =MAX(L92,CEILING((K92+Anlagen!F92)/PG,1)) -> 10 | N92: =IFERROR(INDEX(Anlagen!$B$5:$B$92,MATCH(C92,Anlagen!$A$5:$A$92,0)),"?")&": GW "&L92&IF(M92>L92,"–"&M92,"") -> Helgoland: GW 9–10 | O92: =Buchungsquote!V92 -> 48.373967 | P92: =IF(ISNA(MATCH(C92,Anlagen!$A$5:$A$92,0)),"Fehler: Standort unbekannt",IF(C92=A92,"OK",IF(INDEX($C$5:$C$92,MATCH(C92,Anlagen!$A$5:$A$92,0))<>C92,"Fehler: Standort hängt selbst an anderem Standort",IF(D92=A92,"Fehler: Zuleitung von sich selbst",IF(ISNA(MATCH(D92,Anlagen!$A$5:$A$92,0)),"Fehler: Zuleitung unbekannt",IF(INDEX($C$5:$C$92,MATCH(D92,Anlagen!$A$5:$A$92,0))<>C92,"Fehler: Zuleitung hängt an anderem Standort","OK")))))) -> OK | Q92: =Anlagen!AA92 -> INSEL | R92: =IF(Anlagen!AB92<>"",Anlagen!AB92,COUNTIFS($C$5:$C$92,C92,$J$5:$J$92,"<"&J92)+1) -> 9 | S92: =1000+200*(R92-1)+1 -> 2601 | T92: =1000+200*(R92-1)+Anlagen!F92 -> 2686 | U92: =100+A92 -> 188 | V92: =200+A92 -> 288 | W92: =300+A92 -> 388 | X92: ="10."&A92&".1.0/24" -> 10.88.1.0/24 | Y92: =IF(R92>15,"Fehler: VLAN-Block über 15",IF(COUNTIFS($C$5:$C$92,C92,$R$5:$R$92,R92)>1,"Fehler: VLAN-Block am Standort doppelt",IF(COUNTIF($Q$5:$Q$92,Q92)>1,"Fehler: Kürzel doppelt",IF(Anlagen!F92>199,"Fehler: mehr als 199 Parzellen","OK")))) -> OK
B93: Summe | G93: =SUM(G5:G92) -> 56896.649 | H93: =SUM(H5:H92) -> 118165.3 | I93: =SUM(I5:I92) -> 61295.472 | O93: =SUM(O5:O92) -> 2814.8136
B95: VLAN-Schema: Parzelle = 1000 + 200 × (VLAN-Block − 1) + Parzelle (letzte zwei Ziffern = Parzelle) · Vorstand 100 + Nr. · Gäste 200 + Nr. · Technik 300 + Nr. · Subnetz 10.<Nr.>.<Parzelle>.0/24 · eindeutig je Standort

Sheet Investition
A1: Investition – Technik in den Sparten (ohne Gateways und Standort, die stehen im Blatt „Standorte“)
A2: Mengen nach den Faustregeln in „Annahmen“ oder manuell aus „Anlagen“ · rechts der Vergleich „Sparte eigenständig“
A4: Nr. | B4: Kleingartenanlage | C4: Access Points | D4: Masten | E4: Masten mit Technik | F4: Leitungsweg m | G4: Glasfaser m | H4: Kupfer m | I4: Kupferkabel | J4: Technik in Säulen € | K4: APs, Masten, Montage € | L4: Leitungen € | M4: Zuleitung + Unterverteiler € | N4: Investition Sparte (ohne Standort) | O4: laufend Sparte / Jahr | P4: Gateways eigenständig | Q4: Investition eigenständig | R4: laufend eigenständig / Jahr
A5: =Anlagen!A5 -> 1 | B5: =Anlagen!B5 -> 1. März | C5: =IF(Anlagen!X5<>"",Anlagen!X5,MAX(2,CEILING(Anlagen!F5/Parz_je_AP,1))) -> 9 | D5: =IF(Anlagen!Y5<>"",Anlagen!Y5,CEILING(C5/AP_je_Mast,1)) -> 5 | E5: =MAX(1,CEILING(D5*Anteil_Technik,1)) -> 3 | F5: =IF(Anlagen!Z5<>"",Anlagen!Z5,Leitung_k*SQRT(Anlagen!H5)) -> 259.41466 | G5: =F5*Faser_f -> 430.62834 | H5: =F5*Kupfer_f -> 274.97954 | I5: =ROUND(C5*Kabel_je_AP,0) -> 4 | J5: =E5*(2*P_SFP+P_Flex+P_NT+P_Halter+P_Luefter+P_Spleiss+P_Saeule+P_Ueber)*EK -> 2710.344 | K5: =(C5*P_AP+D5*(P_Mast+P_Fund+P_MontMast)+I5*2*P_Surge)*EK -> 6730.64 | L5: =(G5*P_Faser+H5*P_Kupfer+F5*P_Tiefbau)*EK -> 1161.3424 | M5: =Netz!H5+Netz!I5 -> 3162.131 | N5: =J5+K5+L5+M5 -> 13764.457 | O5: =E5*Strom_Mast*EK+N5*Wartung -> 591.43372 | P5: =CEILING(Anlagen!F5/PG,1) -> 1 | Q5: =J5+K5+L5+(P_KVz+P_USV+P_MontStandort+P5*(P_UCG+P_DAC)+P_Agg*CEILING((P5+E5)/Ports_Agg,1))*EK -> 13886.726 | R5: =(Uplink_Monat*12*MAX(1,CEILING(Buchungsquote!V5*Bandbreite/Ueberbuchung/Uplink_Kap,1))+Strom_Standort+P5*Strom_GW+E5*Strom_Mast)*EK+Q5*Wartung -> 1791.0518
A6: =Anlagen!A6 -> 2 | B6: =Anlagen!B6 -> Abendfrieden | C6: =IF(Anlagen!X6<>"",Anlagen!X6,MAX(2,CEILING(Anlagen!F6/Parz_je_AP,1))) -> 21 | D6: =IF(Anlagen!Y6<>"",Anlagen!Y6,CEILING(C6/AP_je_Mast,1)) -> 10 | E6: =MAX(1,CEILING(D6*Anteil_Technik,1)) -> 5 | F6: =IF(Anlagen!Z6<>"",Anlagen!Z6,Leitung_k*SQRT(Anlagen!H6)) -> 522.9032 | G6: =F6*Faser_f -> 868.01931 | H6: =F6*Kupfer_f -> 554.27739 | I6: =ROUND(C6*Kabel_je_AP,0) -> 9 | J6: =E6*(2*P_SFP+P_Flex+P_NT+P_Halter+P_Luefter+P_Spleiss+P_Saeule+P_Ueber)*EK -> 4517.24 | K6: =(C6*P_AP+D6*(P_Mast+P_Fund+P_MontMast)+I6*2*P_Surge)*EK -> 14382.34 | L6: =(G6*P_Faser+H6*P_Kupfer+F6*P_Tiefbau)*EK -> 2340.9226 | M6: =Netz!H6+Netz!I6 -> 2185.1011 | N6: =J6+K6+L6+M6 -> 23425.604 | O6: =E6*Strom_Mast*EK+N6*Wartung -> 1000.2681 | P6: =CEILING(Anlagen!F6/PG,1) -> 2 | Q6: =J6+K6+L6+(P_KVz+P_USV+P_MontStandort+P6*(P_UCG+P_DAC)+P_Agg*CEILING((P6+E6)/Ports_Agg,1))*EK -> 24846.203 | R6: =(Uplink_Monat*12*MAX(1,CEILING(Buchungsquote!V6*Bandbreite/Ueberbuchung/Uplink_Kap,1))+Strom_Standort+P6*Strom_GW+E6*Strom_Mast)*EK+Q6*Wartung -> 2268.5861
A7: =Anlagen!A7 -> 3 | B7: =Anlagen!B7 -> Abendrot | C7: =IF(Anlagen!X7<>"",Anlagen!X7,MAX(2,CEILING(Anlagen!F7/Parz_je_AP,1))) -> 39 | D7: =IF(Anlagen!Y7<>"",Anlagen!Y7,CEILING(C7/AP_je_Mast,1)) -> 18 | E7: =MAX(1,CEILING(D7*Anteil_Technik,1)) -> 9 | F7: =IF(Anlagen!Z7<>"",Anlagen!Z7,Leitung_k*SQRT(Anlagen!H7)) -> 713.26511 | G7: =F7*Faser_f -> 1184.0201 | H7: =F7*Kupfer_f -> 756.06102 | I7: =ROUND(C7*Kabel_je_AP,0) -> 16 | J7: =E7*(2*P_SFP+P_Flex+P_NT+P_Halter+P_Luefter+P_Spleiss+P_Saeule+P_Ueber)*EK -> 8131.032 | K7: =(C7*P_AP+D7*(P_Mast+P_Fund+P_MontMast)+I7*2*P_Surge)*EK -> 26239.5 | L7: =(G7*P_Faser+H7*P_Kupfer+F7*P_Tiefbau)*EK -> 3193.131 | M7: =Netz!H7+Netz!I7 -> 3836.9982 | N7: =J7+K7+L7+M7 -> 41400.661 | O7: =E7*Strom_Mast*EK+N7*Wartung -> 1777.5198 | P7: =CEILING(Anlagen!F7/PG,1) -> 3 | Q7: =J7+K7+L7+(P_KVz+P_USV+P_MontStandort+P7*(P_UCG+P_DAC)+P_Agg*CEILING((P7+E7)/Ports_Agg,1))*EK -> 41776.263 | R7: =(Uplink_Monat*12*MAX(1,CEILING(Buchungsquote!V7*Bandbreite/Ueberbuchung/Uplink_Kap,1))+Strom_Standort+P7*Strom_GW+E7*Strom_Mast)*EK+Q7*Wartung -> 3044.2379
A8: =Anlagen!A8 -> 4 | B8: =Anlagen!B8 -> Abendruh | C8: =IF(Anlagen!X8<>"",Anlagen!X8,MAX(2,CEILING(Anlagen!F8/Parz_je_AP,1))) -> 40 | D8: =IF(Anlagen!Y8<>"",Anlagen!Y8,CEILING(C8/AP_je_Mast,1)) -> 19 | E8: =MAX(1,CEILING(D8*Anteil_Technik,1)) -> 10 | F8: =IF(Anlagen!Z8<>"",Anlagen!Z8,Leitung_k*SQRT(Anlagen!H8)) -> 773.42849 | G8: =F8*Faser_f -> 1283.8913 | H8: =F8*Kupfer_f -> 819.83419 | I8: =ROUND(C8*Kabel_je_AP,0) -> 17 | J8: =E8*(2*P_SFP+P_Flex+P_NT+P_Halter+P_Luefter+P_Spleiss+P_Saeule+P_Ueber)*EK -> 9034.48 | K8: =(C8*P_AP+D8*(P_Mast+P_Fund+P_MontMast)+I8*2*P_Surge)*EK -> 27353.34 | L8: =(G8*P_Faser+H8*P_Kupfer+F8*P_Tiefbau)*EK -> 3462.4692 | M8: =Netz!H8+Netz!I8 -> 3022.5854 | N8: =J8+K8+L8+M8 -> 42872.875 | O8: =E8*Strom_Mast*EK+N8*Wartung -> 1881.1862 | P8: =CEILING(Anlagen!F8/PG,1) -> 3 | Q8: =J8+K8+L8+(P_KVz+P_USV+P_MontStandort+P8*(P_UCG+P_DAC)+P_Agg*CEILING((P8+E8)/Ports_Agg,1))*EK -> 44062.889 | R8: =(Uplink_Monat*12*MAX(1,CEILING(Buchungsquote!V8*Bandbreite/Ueberbuchung/Uplink_Kap,1))+Strom_Standort+P8*Strom_GW+E8*Strom_Mast)*EK+Q8*Wartung -> 3172.3367
A9: =Anlagen!A9 -> 5 | B9: =Anlagen!B9 -> Abendsonne | C9: =IF(Anlagen!X9<>"",Anlagen!X9,MAX(2,CEILING(Anlagen!F9/Parz_je_AP,1))) -> 19 | D9: =IF(Anlagen!Y9<>"",Anlagen!Y9,CEILING(C9/AP_je_Mast,1)) -> 9 | E9: =MAX(1,CEILING(D9*Anteil_Technik,1)) -> 5 | F9: =IF(Anlagen!Z9<>"",Anlagen!Z9,Leitung_k*SQRT(Anlagen!H9)) -> 366.21256 | G9: =F9*Faser_f -> 607.91286 | H9: =F9*Kupfer_f -> 388.18532 | I9: =ROUND(C9*Kabel_je_AP,0) -> 8 | J9: =E9*(2*P_SFP+P_Flex+P_NT+P_Halter+P_Luefter+P_Spleiss+P_Saeule+P_Ueber)*EK -> 4517.24 | K9: =(C9*P_AP+D9*(P_Mast+P_Fund+P_MontMast)+I9*2*P_Surge)*EK -> 12971 | L9: =(G9*P_Faser+H9*P_Kupfer+F9*P_Tiefbau)*EK -> 1639.4531 | M9: =Netz!H9+Netz!I9 -> 2050.1834 | N9: =J9+K9+L9+M9 -> 21177.876 | O9: =E9*Strom_Mast*EK+N9*Wartung -> 932.83629 | P9: =CEILING(Anlagen!F9/PG,1) -> 2 | Q9: =J9+K9+L9+(P_KVz+P_USV+P_MontStandort+P9*(P_UCG+P_DAC)+P_Agg*CEILING((P9+E9)/Ports_Agg,1))*EK -> 22733.393 | R9: =(Uplink_Monat*12*MAX(1,CEILING(Buchungsquote!V9*Bandbreite/Ueberbuchung/Uplink_Kap,1))+Strom_Standort+P9*Strom_GW+E9*Strom_Mast)*EK+Q9*Wartung -> 2205.2018
A10: =Anlagen!A10 -> 6 | B10: =Anlagen!B10 -> Altstadt Forst | C10: =IF(Anlagen!X10<>"",Anlagen!X10,MAX(2,CEILING(Anlagen!F10/Parz_je_AP,1))) -> 25 | D10: =IF(Anlagen!Y10<>"",Anlagen!Y10,CEILING(C10/AP_je_Mast,1)) -> 12 | E10: =MAX(1,CEILING(D10*Anteil_Technik,1)) -> 6 | F10: =IF(Anlagen!Z10<>"",Anlagen!Z10,Leitung_k*SQRT(Anlagen!H10)) -> 605.4006 | G10: =F10*Faser_f -> 1004.965 | H10: =F10*Kupfer_f -> 641.72463 | I10: =ROUND(C10*Kabel_je_AP,0) -> 11 | J10: =E10*(2*P_SFP+P_Flex+P_NT+P_Halter+P_Luefter+P_Spleiss+P_Saeule+P_Ueber)*EK -> 5420.688 | K10: =(C10*P_AP+D10*(P_Mast+P_Fund+P_MontMast)+I10*2*P_Surge)*EK -> 17205.02 | L10: =(G10*P_Faser+H10*P_Kupfer+F10*P_Tiefbau)*EK -> 2710.2453 | M10: =Netz!H10+Netz!I10 -> 2133.3675 | N10: =J10+K10+L10+M10 -> 27469.321 | O10: =E10*Strom_Mast*EK+N10*Wartung -> 1181.0796 | P10: =CEILING(Anlagen!F10/PG,1) -> 2 | Q10: =J10+K10+L10+(P_KVz+P_USV+P_MontStandort+P10*(P_UCG+P_DAC)+P_Agg*CEILING((P10+E10)/Ports_Agg,1))*EK -> 28941.653 | R10: =(Uplink_Monat*12*MAX(1,CEILING(Buchungsquote!V10*Bandbreite/Ueberbuchung/Uplink_Kap,1))+Strom_Standort+P10*Strom_GW+E10*Strom_Mast)*EK+Q10*Wartung -> 2450.9496
A11: =Anlagen!A11 -> 7 | B11: =Anlagen!B11 -> Am Beetzseeufer | C11: =IF(Anlagen!X11<>"",Anlagen!X11,MAX(2,CEILING(Anlagen!F11/Parz_je_AP,1))) -> 22 | D11: =IF(Anlagen!Y11<>"",Anlagen!Y11,CEILING(C11/AP_je_Mast,1)) -> 10 | E11: =MAX(1,CEILING(D11*Anteil_Technik,1)) -> 5 | F11: =IF(Anlagen!Z11<>"",Anlagen!Z11,Leitung_k*SQRT(Anlagen!H11)) -> 551.34151 | G11: =F11*Faser_f -> 915.22691 | H11: =F11*Kupfer_f -> 584.422 | I11: =ROUND(C11*Kabel_je_AP,0) -> 9 | J11: =E11*(2*P_SFP+P_Flex+P_NT+P_Halter+P_Luefter+P_Spleiss+P_Saeule+P_Ueber)*EK -> 4517.24 | K11: =(C11*P_AP+D11*(P_Mast+P_Fund+P_MontMast)+I11*2*P_Surge)*EK -> 14679.84 | L11: =(G11*P_Faser+H11*P_Kupfer+F11*P_Tiefbau)*EK -> 2468.2347 | M11: =Netz!H11+Netz!I11 -> 3246.9882 | N11: =J11+K11+L11+M11 -> 24912.303 | O11: =E11*Strom_Mast*EK+N11*Wartung -> 1044.8691 | P11: =CEILING(Anlagen!F11/PG,1) -> 2 | Q11: =J11+K11+L11+(P_KVz+P_USV+P_MontStandort+P11*(P_UCG+P_DAC)+P_Agg*CEILING((P11+E11)/Ports_Agg,1))*EK -> 25271.015 | R11: =(Uplink_Monat*12*MAX(1,CEILING(Buchungsquote!V11*Bandbreite/Ueberbuchung/Uplink_Kap,1))+Strom_Standort+P11*Strom_GW+E11*Strom_Mast)*EK+Q11*Wartung -> 2281.3304
A12: =Anlagen!A12 -> 8 | B12: =Anlagen!B12 -> Am Büttelhandfassgraben | C12: =IF(Anlagen!X12<>"",Anlagen!X12,MAX(2,CEILING(Anlagen!F12/Parz_je_AP,1))) -> 2 | D12: =IF(Anlagen!Y12<>"",Anlagen!Y12,CEILING(C12/AP_je_Mast,1)) -> 1 | E12: =MAX(1,CEILING(D12*Anteil_Technik,1)) -> 1 | F12: =IF(Anlagen!Z12<>"",Anlagen!Z12,Leitung_k*SQRT(Anlagen!H12)) -> 135.88111 | G12: =F12*Faser_f -> 225.56264 | H12: =F12*Kupfer_f -> 144.03398 | I12: =ROUND(C12*Kabel_je_AP,0) -> 1 | J12: =E12*(2*P_SFP+P_Flex+P_NT+P_Halter+P_Luefter+P_Spleiss+P_Saeule+P_Ueber)*EK -> 903.448 | K12: =(C12*P_AP+D12*(P_Mast+P_Fund+P_MontMast)+I12*2*P_Surge)*EK -> 1411.34 | L12: =(G12*P_Faser+H12*P_Kupfer+F12*P_Tiefbau)*EK -> 608.30984 | M12: =Netz!H12+Netz!I12 -> 1237.6119 | N12: =J12+K12+L12+M12 -> 4160.7097 | O12: =E12*Strom_Mast*EK+N12*Wartung -> 184.32129 | P12: =CEILING(Anlagen!F12/PG,1) -> 1 | Q12: =J12+K12+L12+(P_KVz+P_USV+P_MontStandort+P12*(P_UCG+P_DAC)+P_Agg*CEILING((P12+E12)/Ports_Agg,1))*EK -> 6207.4978 | R12: =(Uplink_Monat*12*MAX(1,CEILING(Buchungsquote!V12*Bandbreite/Ueberbuchung/Uplink_Kap,1))+Strom_Standort+P12*Strom_GW+E12*Strom_Mast)*EK+Q12*Wartung -> 1441.6749
A13: =Anlagen!A13 -> 9 | B13: =Anlagen!B13 -> Am Eichenweg | C13: =IF(Anlagen!X13<>"",Anlagen!X13,MAX(2,CEILING(Anlagen!F13/Parz_je_AP,1))) -> 15 | D13: =IF(Anlagen!Y13<>"",Anlagen!Y13,CEILING(C13/AP_je_Mast,1)) -> 7 | E13: =MAX(1,CEILING(D13*Anteil_Technik,1)) -> 4 | F13: =IF(Anlagen!Z13<>"",Anlagen!Z13,Leitung_k*SQRT(Anlagen!H13)) -> 515.44165 | G13: =F13*Faser_f -> 855.63315 | H13: =F13*Kupfer_f -> 546.36815 | I13: =ROUND(C13*Kabel_je_AP,0) -> 6 | J13: =E13*(2*P_SFP+P_Flex+P_NT+P_Halter+P_Luefter+P_Spleiss+P_Saeule+P_Ueber)*EK -> 3613.792 | K13: =(C13*P_AP+D13*(P_Mast+P_Fund+P_MontMast)+I13*2*P_Surge)*EK -> 10148.32 | L13: =(G13*P_Faser+H13*P_Kupfer+F13*P_Tiefbau)*EK -> 2307.5189 | M13: =Netz!H13+Netz!I13 -> 4282.556 | N13: =J13+K13+L13+M13 -> 20352.187 | O13: =E13*Strom_Mast*EK+N13*Wartung -> 848.56561 | P13: =CEILING(Anlagen!F13/PG,1) -> 1 | Q13: =J13+K13+L13+(P_KVz+P_USV+P_MontStandort+P13*(P_UCG+P_DAC)+P_Agg*CEILING((P13+E13)/Ports_Agg,1))*EK -> 19354.031 | R13: =(Uplink_Monat*12*MAX(1,CEILING(Buchungsquote!V13*Bandbreite/Ueberbuchung/Uplink_Kap,1))+Strom_Standort+P13*Strom_GW+E13*Strom_Mast)*EK+Q13*Wartung -> 2014.5709
A14: =Anlagen!A14 -> 10 | B14: =Anlagen!B14 -> Am Jakobsgraben | C14: =IF(Anlagen!X14<>"",Anlagen!X14,MAX(2,CEILING(Anlagen!F14/Parz_je_AP,1))) -> 12 | D14: =IF(Anlagen!Y14<>"",Anlagen!Y14,CEILING(C14/AP_je_Mast,1)) -> 6 | E14: =MAX(1,CEILING(D14*Anteil_Technik,1)) -> 3 | F14: =IF(Anlagen!Z14<>"",Anlagen!Z14,Leitung_k*SQRT(Anlagen!H14)) -> 415.87533 | G14: =F14*Faser_f -> 690.35304 | H14: =F14*Kupfer_f -> 440.82785 | I14: =ROUND(C14*Kabel_je_AP,0) -> 5 | J14: =E14*(2*P_SFP+P_Flex+P_NT+P_Halter+P_Luefter+P_Spleiss+P_Saeule+P_Ueber)*EK -> 2710.344 | K14: =(C14*P_AP+D14*(P_Mast+P_Fund+P_MontMast)+I14*2*P_Surge)*EK -> 8439.48 | L14: =(G14*P_Faser+H14*P_Kupfer+F14*P_Tiefbau)*EK -> 1861.7824 | M14: =Netz!H14+Netz!I14 -> 3684.6347 | N14: =J14+K14+L14+M14 -> 16696.241 | O14: =E14*Strom_Mast*EK+N14*Wartung -> 679.38723 | P14: =CEILING(Anlagen!F14/PG,1) -> 1 | Q14: =J14+K14+L14+(P_KVz+P_USV+P_MontStandort+P14*(P_UCG+P_DAC)+P_Agg*CEILING((P14+E14)/Ports_Agg,1))*EK -> 16296.006 | R14: =(Uplink_Monat*12*MAX(1,CEILING(Buchungsquote!V14*Bandbreite/Ueberbuchung/Uplink_Kap,1))+Strom_Standort+P14*Strom_GW+E14*Strom_Mast)*EK+Q14*Wartung -> 1863.3302
A15: =Anlagen!A15 -> 11 | B15: =Anlagen!B15 -> Am Schafdamm | C15: =IF(Anlagen!X15<>"",Anlagen!X15,MAX(2,CEILING(Anlagen!F15/Parz_je_AP,1))) -> 3 | D15: =IF(Anlagen!Y15<>"",Anlagen!Y15,CEILING(C15/AP_je_Mast,1)) -> 2 | E15: =MAX(1,CEILING(D15*Anteil_Technik,1)) -> 1 | F15: =IF(Anlagen!Z15<>"",Anlagen!Z15,Leitung_k*SQRT(Anlagen!H15)) -> 219.56838 | G15: =F15*Faser_f -> 364.48351 | H15: =F15*Kupfer_f -> 232.74248 | I15: =ROUND(C15*Kabel_je_AP,0) -> 1 | J15: =E15*(2*P_SFP+P_Flex+P_NT+P_Halter+P_Luefter+P_Spleiss+P_Saeule+P_Ueber)*EK -> 903.448 | K15: =(C15*P_AP+D15*(P_Mast+P_Fund+P_MontMast)+I15*2*P_Surge)*EK -> 2496.62 | L15: =(G15*P_Faser+H15*P_Kupfer+F15*P_Tiefbau)*EK -> 982.95933 | M15: =Netz!H15+Netz!I15 -> 1847.3613 | N15: =J15+K15+L15+M15 -> 6230.3887 | O15: =E15*Strom_Mast*EK+N15*Wartung -> 246.41166 | P15: =CEILING(Anlagen!F15/PG,1) -> 1 | Q15: =J15+K15+L15+(P_KVz+P_USV+P_MontStandort+P15*(P_UCG+P_DAC)+P_Agg*CEILING((P15+E15)/Ports_Agg,1))*EK -> 7667.4273 | R15: =(Uplink_Monat*12*MAX(1,CEILING(Buchungsquote!V15*Bandbreite/Ueberbuchung/Uplink_Kap,1))+Strom_Standort+P15*Strom_GW+E15*Strom_Mast)*EK+Q15*Wartung -> 1485.4728
A16: =Anlagen!A16 -> 12 | B16: =Anlagen!B16 -> Am Schlangenpfad | C16: =IF(Anlagen!X16<>"",Anlagen!X16,MAX(2,CEILING(Anlagen!F16/Parz_je_AP,1))) -> 6 | D16: =IF(Anlagen!Y16<>"",Anlagen!Y16,CEILING(C16/AP_je_Mast,1)) -> 3 | E16: =MAX(1,CEILING(D16*Anteil_Technik,1)) -> 2 | F16: =IF(Anlagen!Z16<>"",Anlagen!Z16,Leitung_k*SQRT(Anlagen!H16)) -> 294.57655 | G16: =F16*Faser_f -> 488.99707 | H16: =F16*Kupfer_f -> 312.25114 | I16: =ROUND(C16*Kabel_je_AP,0) -> 3 | J16: =E16*(2*P_SFP+P_Flex+P_NT+P_Halter+P_Luefter+P_Spleiss+P_Saeule+P_Ueber)*EK -> 1806.896 | K16: =(C16*P_AP+D16*(P_Mast+P_Fund+P_MontMast)+I16*2*P_Surge)*EK -> 4234.02 | L16: =(G16*P_Faser+H16*P_Kupfer+F16*P_Tiefbau)*EK -> 1318.7544 | M16: =Netz!H16+Netz!I16 -> 1713.1922 | N16: =J16+K16+L16+M16 -> 9072.8626 | O16: =E16*Strom_Mast*EK+N16*Wartung -> 391.18588 | P16: =CEILING(Anlagen!F16/PG,1) -> 1 | Q16: =J16+K16+L16+(P_KVz+P_USV+P_MontStandort+P16*(P_UCG+P_DAC)+P_Agg*CEILING((P16+E16)/Ports_Agg,1))*EK -> 10644.07 | R16: =(Uplink_Monat*12*MAX(1,CEILING(Buchungsquote!V16*Bandbreite/Ueberbuchung/Uplink_Kap,1))+Strom_Standort+P16*Strom_GW+E16*Strom_Mast)*EK+Q16*Wartung -> 1634.2721
... A92: =Anlagen!A92 -> 88 | B92: =Anlagen!B92 -> Zur Insel | C92: =IF(Anlagen!X92<>"",Anlagen!X92,MAX(2,CEILING(Anlagen!F92/Parz_je_AP,1))) -> 24 | D92: =IF(Anlagen!Y92<>"",Anlagen!Y92,CEILING(C92/AP_je_Mast,1)) -> 11 | E92: =MAX(1,CEILING(D92*Anteil_Technik,1)) -> 6 | F92: =IF(Anlagen!Z92<>"",Anlagen!Z92,Leitung_k*SQRT(Anlagen!H92)) -> 652.60466 | G92: =F92*Faser_f -> 1083.3237 | H92: =F92*Kupfer_f -> 691.76094 | I92: =ROUND(C92*Kabel_je_AP,0) -> 10 | J92: =E92*(2*P_SFP+P_Flex+P_NT+P_Halter+P_Luefter+P_Spleiss+P_Saeule+P_Ueber)*EK -> 5420.688 | K92: =(C92*P_AP+D92*(P_Mast+P_Fund+P_MontMast)+I92*2*P_Surge)*EK -> 16091.18 | L92: =(G92*P_Faser+H92*P_Kupfer+F92*P_Tiefbau)*EK -> 2921.5675 | M92: =Netz!H92+Netz!I92 -> 4502.62 | N92: =J92+K92+L92+M92 -> 28936.056 | O92: =E92*Strom_Mast*EK+N92*Wartung -> 1225.0817 | P92: =CEILING(Anlagen!F92/PG,1) -> 2 | Q92: =J92+K92+L92+(P_KVz+P_USV+P_MontStandort+P92*(P_UCG+P_DAC)+P_Agg*CEILING((P92+E92)/Ports_Agg,1))*EK -> 28039.135 | R92: =(Uplink_Monat*12*MAX(1,CEILING(Buchungsquote!V92*Bandbreite/Ueberbuchung/Uplink_Kap,1))+Strom_Standort+P92*Strom_GW+E92*Strom_Mast)*EK+Q92*Wartung -> 2423.8741
B93: Summe | C93: =SUM(C5:C92) -> 1434 | D93: =SUM(D5:D92) -> 694 | E93: =SUM(E5:E92) -> 373 | F93: =SUM(F5:F92) -> 39601.338 | G93: =SUM(G5:G92) -> 65738.221 | H93: =SUM(H5:H92) -> 41977.418 | I93: =SUM(I5:I92) -> 605 | J93: =SUM(J5:J92) -> 336986.1 | ... R93: =SUM(R5:R92) -> 183146.94
B95: Kontrolle: KGV Buchenweg eigenständig – Kalkulation Variante A ohne Tiefbau 27.597 € mit 1 Gateway; hier 2 Gateways (55 Parzellen je Gateway), also ca. 321 € mehr | Q95: =INDEX(Q5:Q92,MATCH(20,A5:A92,0)) -> 27915.618

Sheet Standorte
A1: Standorte – Gateways, Internet-Anschluss und Kosten je Gateway-Standort
A2: Nur Zeilen von Sparten, die selbst Standort sind, sind gefüllt · alle Gateways eines Standorts teilen sich den Internet-Anschluss
A4: Nr. | B4: Standort (Sparte) | C4: Sparten am Standort | D4: Parzellen | E4: Gateways | F4: Belegung | G4: Glasfaserstrecken im Schrank | H4: Aggregation-Switches | I4: Kunden | J4: Uplink-Bedarf Mbit/s | K4: Internet-Anschlüsse | L4: Gateways € | M4: Schrank, USV, Switches, Montage € | N4: Investition Standort | O4: laufend Standort / Jahr | P4: Prüfung
A5: =Anlagen!A5 -> 1 | B5: =IF(Netz!C5=A5,Anlagen!B5,"") | C5: =IF(Netz!C5=A5,COUNTIF(Netz!$C$5:$C$92,A5),"") | D5: =IF(Netz!C5=A5,SUMIF(Netz!$C$5:$C$92,A5,Anlagen!$F$5:$F$92),"") | E5: =IF(Netz!C5=A5,CEILING(D5/PG,1),"") | F5: =IF(Netz!C5=A5,D5/(E5*PG),"") | G5: =IF(Netz!C5=A5,Investition!E5+COUNTIF(Netz!$D$5:$D$92,A5),"") | H5: =IF(Netz!C5=A5,CEILING((E5+G5)/Ports_Agg,1),"") | I5: =IF(Netz!C5=A5,SUMIF(Netz!$C$5:$C$92,A5,Netz!$O$5:$O$92),"") | J5: =IF(Netz!C5=A5,I5*Bandbreite/Ueberbuchung,"") | K5: =IF(Netz!C5=A5,MAX(1,CEILING(J5/Uplink_Kap,1)),"") | L5: =IF(Netz!C5=A5,E5*(P_UCG+P_DAC)*EK,"") | M5: =IF(Netz!C5=A5,(P_KVz+P_USV+P_MontStandort+H5*P_Agg)*EK,"") | N5: =IF(Netz!C5=A5,L5+M5,"") | O5: =IF(Netz!C5=A5,(K5*Uplink_Monat*12+Strom_Standort+E5*Strom_GW)*EK+N5*Wartung,"") | P5: =IF(Netz!C5=A5,IF(E5>Max_GW,"Achtung: mehr als "&Max_GW&" Gateways",IF(K5>1,"OK – "&K5&" Internet-Anschlüsse nötig","OK")),"")
A6: =Anlagen!A6 -> 2 | B6: =IF(Netz!C6=A6,Anlagen!B6,"") | C6: =IF(Netz!C6=A6,COUNTIF(Netz!$C$5:$C$92,A6),"") | D6: =IF(Netz!C6=A6,SUMIF(Netz!$C$5:$C$92,A6,Anlagen!$F$5:$F$92),"") | E6: =IF(Netz!C6=A6,CEILING(D6/PG,1),"") | F6: =IF(Netz!C6=A6,D6/(E6*PG),"") | G6: =IF(Netz!C6=A6,Investition!E6+COUNTIF(Netz!$D$5:$D$92,A6),"") | H6: =IF(Netz!C6=A6,CEILING((E6+G6)/Ports_Agg,1),"") | I6: =IF(Netz!C6=A6,SUMIF(Netz!$C$5:$C$92,A6,Netz!$O$5:$O$92),"") | J6: =IF(Netz!C6=A6,I6*Bandbreite/Ueberbuchung,"") | K6: =IF(Netz!C6=A6,MAX(1,CEILING(J6/Uplink_Kap,1)),"") | L6: =IF(Netz!C6=A6,E6*(P_UCG+P_DAC)*EK,"") | M6: =IF(Netz!C6=A6,(P_KVz+P_USV+P_MontStandort+H6*P_Agg)*EK,"") | N6: =IF(Netz!C6=A6,L6+M6,"") | O6: =IF(Netz!C6=A6,(K6*Uplink_Monat*12+Strom_Standort+E6*Strom_GW)*EK+N6*Wartung,"") | P6: =IF(Netz!C6=A6,IF(E6>Max_GW,"Achtung: mehr als "&Max_GW&" Gateways",IF(K6>1,"OK – "&K6&" Internet-Anschlüsse nötig","OK")),"")
A7: =Anlagen!A7 -> 3 | B7: =IF(Netz!C7=A7,Anlagen!B7,"") | C7: =IF(Netz!C7=A7,COUNTIF(Netz!$C$5:$C$92,A7),"") | D7: =IF(Netz!C7=A7,SUMIF(Netz!$C$5:$C$92,A7,Anlagen!$F$5:$F$92),"") | E7: =IF(Netz!C7=A7,CEILING(D7/PG,1),"") | F7: =IF(Netz!C7=A7,D7/(E7*PG),"") | G7: =IF(Netz!C7=A7,Investition!E7+COUNTIF(Netz!$D$5:$D$92,A7),"") | H7: =IF(Netz!C7=A7,CEILING((E7+G7)/Ports_Agg,1),"") | I7: =IF(Netz!C7=A7,SUMIF(Netz!$C$5:$C$92,A7,Netz!$O$5:$O$92),"") | J7: =IF(Netz!C7=A7,I7*Bandbreite/Ueberbuchung,"") | K7: =IF(Netz!C7=A7,MAX(1,CEILING(J7/Uplink_Kap,1)),"") | L7: =IF(Netz!C7=A7,E7*(P_UCG+P_DAC)*EK,"") | M7: =IF(Netz!C7=A7,(P_KVz+P_USV+P_MontStandort+H7*P_Agg)*EK,"") | N7: =IF(Netz!C7=A7,L7+M7,"") | O7: =IF(Netz!C7=A7,(K7*Uplink_Monat*12+Strom_Standort+E7*Strom_GW)*EK+N7*Wartung,"") | P7: =IF(Netz!C7=A7,IF(E7>Max_GW,"Achtung: mehr als "&Max_GW&" Gateways",IF(K7>1,"OK – "&K7&" Internet-Anschlüsse nötig","OK")),"")
A8: =Anlagen!A8 -> 4 | B8: =IF(Netz!C8=A8,Anlagen!B8,"") | C8: =IF(Netz!C8=A8,COUNTIF(Netz!$C$5:$C$92,A8),"") | D8: =IF(Netz!C8=A8,SUMIF(Netz!$C$5:$C$92,A8,Anlagen!$F$5:$F$92),"") | E8: =IF(Netz!C8=A8,CEILING(D8/PG,1),"") | F8: =IF(Netz!C8=A8,D8/(E8*PG),"") | G8: =IF(Netz!C8=A8,Investition!E8+COUNTIF(Netz!$D$5:$D$92,A8),"") | H8: =IF(Netz!C8=A8,CEILING((E8+G8)/Ports_Agg,1),"") | I8: =IF(Netz!C8=A8,SUMIF(Netz!$C$5:$C$92,A8,Netz!$O$5:$O$92),"") | J8: =IF(Netz!C8=A8,I8*Bandbreite/Ueberbuchung,"") | K8: =IF(Netz!C8=A8,MAX(1,CEILING(J8/Uplink_Kap,1)),"") | L8: =IF(Netz!C8=A8,E8*(P_UCG+P_DAC)*EK,"") | M8: =IF(Netz!C8=A8,(P_KVz+P_USV+P_MontStandort+H8*P_Agg)*EK,"") | N8: =IF(Netz!C8=A8,L8+M8,"") | O8: =IF(Netz!C8=A8,(K8*Uplink_Monat*12+Strom_Standort+E8*Strom_GW)*EK+N8*Wartung,"") | P8: =IF(Netz!C8=A8,IF(E8>Max_GW,"Achtung: mehr als "&Max_GW&" Gateways",IF(K8>1,"OK – "&K8&" Internet-Anschlüsse nötig","OK")),"")
A9: =Anlagen!A9 -> 5 | B9: =IF(Netz!C9=A9,Anlagen!B9,"") | C9: =IF(Netz!C9=A9,COUNTIF(Netz!$C$5:$C$92,A9),"") | D9: =IF(Netz!C9=A9,SUMIF(Netz!$C$5:$C$92,A9,Anlagen!$F$5:$F$92),"") | E9: =IF(Netz!C9=A9,CEILING(D9/PG,1),"") | F9: =IF(Netz!C9=A9,D9/(E9*PG),"") | G9: =IF(Netz!C9=A9,Investition!E9+COUNTIF(Netz!$D$5:$D$92,A9),"") | H9: =IF(Netz!C9=A9,CEILING((E9+G9)/Ports_Agg,1),"") | I9: =IF(Netz!C9=A9,SUMIF(Netz!$C$5:$C$92,A9,Netz!$O$5:$O$92),"") | J9: =IF(Netz!C9=A9,I9*Bandbreite/Ueberbuchung,"") | K9: =IF(Netz!C9=A9,MAX(1,CEILING(J9/Uplink_Kap,1)),"") | L9: =IF(Netz!C9=A9,E9*(P_UCG+P_DAC)*EK,"") | M9: =IF(Netz!C9=A9,(P_KVz+P_USV+P_MontStandort+H9*P_Agg)*EK,"") | N9: =IF(Netz!C9=A9,L9+M9,"") | O9: =IF(Netz!C9=A9,(K9*Uplink_Monat*12+Strom_Standort+E9*Strom_GW)*EK+N9*Wartung,"") | P9: =IF(Netz!C9=A9,IF(E9>Max_GW,"Achtung: mehr als "&Max_GW&" Gateways",IF(K9>1,"OK – "&K9&" Internet-Anschlüsse nötig","OK")),"")
A10: =Anlagen!A10 -> 6 | B10: =IF(Netz!C10=A10,Anlagen!B10,"") | C10: =IF(Netz!C10=A10,COUNTIF(Netz!$C$5:$C$92,A10),"") | D10: =IF(Netz!C10=A10,SUMIF(Netz!$C$5:$C$92,A10,Anlagen!$F$5:$F$92),"") | E10: =IF(Netz!C10=A10,CEILING(D10/PG,1),"") | F10: =IF(Netz!C10=A10,D10/(E10*PG),"") | G10: =IF(Netz!C10=A10,Investition!E10+COUNTIF(Netz!$D$5:$D$92,A10),"") | H10: =IF(Netz!C10=A10,CEILING((E10+G10)/Ports_Agg,1),"") | I10: =IF(Netz!C10=A10,SUMIF(Netz!$C$5:$C$92,A10,Netz!$O$5:$O$92),"") | J10: =IF(Netz!C10=A10,I10*Bandbreite/Ueberbuchung,"") | K10: =IF(Netz!C10=A10,MAX(1,CEILING(J10/Uplink_Kap,1)),"") | L10: =IF(Netz!C10=A10,E10*(P_UCG+P_DAC)*EK,"") | M10: =IF(Netz!C10=A10,(P_KVz+P_USV+P_MontStandort+H10*P_Agg)*EK,"") | N10: =IF(Netz!C10=A10,L10+M10,"") | O10: =IF(Netz!C10=A10,(K10*Uplink_Monat*12+Strom_Standort+E10*Strom_GW)*EK+N10*Wartung,"") | P10: =IF(Netz!C10=A10,IF(E10>Max_GW,"Achtung: mehr als "&Max_GW&" Gateways",IF(K10>1,"OK – "&K10&" Internet-Anschlüsse nötig","OK")),"")
A11: =Anlagen!A11 -> 7 | B11: =IF(Netz!C11=A11,Anlagen!B11,"") | C11: =IF(Netz!C11=A11,COUNTIF(Netz!$C$5:$C$92,A11),"") | D11: =IF(Netz!C11=A11,SUMIF(Netz!$C$5:$C$92,A11,Anlagen!$F$5:$F$92),"") | E11: =IF(Netz!C11=A11,CEILING(D11/PG,1),"") | F11: =IF(Netz!C11=A11,D11/(E11*PG),"") | G11: =IF(Netz!C11=A11,Investition!E11+COUNTIF(Netz!$D$5:$D$92,A11),"") | H11: =IF(Netz!C11=A11,CEILING((E11+G11)/Ports_Agg,1),"") | I11: =IF(Netz!C11=A11,SUMIF(Netz!$C$5:$C$92,A11,Netz!$O$5:$O$92),"") | J11: =IF(Netz!C11=A11,I11*Bandbreite/Ueberbuchung,"") | K11: =IF(Netz!C11=A11,MAX(1,CEILING(J11/Uplink_Kap,1)),"") | L11: =IF(Netz!C11=A11,E11*(P_UCG+P_DAC)*EK,"") | M11: =IF(Netz!C11=A11,(P_KVz+P_USV+P_MontStandort+H11*P_Agg)*EK,"") | N11: =IF(Netz!C11=A11,L11+M11,"") | O11: =IF(Netz!C11=A11,(K11*Uplink_Monat*12+Strom_Standort+E11*Strom_GW)*EK+N11*Wartung,"") | P11: =IF(Netz!C11=A11,IF(E11>Max_GW,"Achtung: mehr als "&Max_GW&" Gateways",IF(K11>1,"OK – "&K11&" Internet-Anschlüsse nötig","OK")),"")
A12: =Anlagen!A12 -> 8 | B12: =IF(Netz!C12=A12,Anlagen!B12,"") | C12: =IF(Netz!C12=A12,COUNTIF(Netz!$C$5:$C$92,A12),"") | D12: =IF(Netz!C12=A12,SUMIF(Netz!$C$5:$C$92,A12,Anlagen!$F$5:$F$92),"") | E12: =IF(Netz!C12=A12,CEILING(D12/PG,1),"") | F12: =IF(Netz!C12=A12,D12/(E12*PG),"") | G12: =IF(Netz!C12=A12,Investition!E12+COUNTIF(Netz!$D$5:$D$92,A12),"") | H12: =IF(Netz!C12=A12,CEILING((E12+G12)/Ports_Agg,1),"") | I12: =IF(Netz!C12=A12,SUMIF(Netz!$C$5:$C$92,A12,Netz!$O$5:$O$92),"") | J12: =IF(Netz!C12=A12,I12*Bandbreite/Ueberbuchung,"") | K12: =IF(Netz!C12=A12,MAX(1,CEILING(J12/Uplink_Kap,1)),"") | L12: =IF(Netz!C12=A12,E12*(P_UCG+P_DAC)*EK,"") | M12: =IF(Netz!C12=A12,(P_KVz+P_USV+P_MontStandort+H12*P_Agg)*EK,"") | N12: =IF(Netz!C12=A12,L12+M12,"") | O12: =IF(Netz!C12=A12,(K12*Uplink_Monat*12+Strom_Standort+E12*Strom_GW)*EK+N12*Wartung,"") | P12: =IF(Netz!C12=A12,IF(E12>Max_GW,"Achtung: mehr als "&Max_GW&" Gateways",IF(K12>1,"OK – "&K12&" Internet-Anschlüsse nötig","OK")),"")
A13: =Anlagen!A13 -> 9 | B13: =IF(Netz!C13=A13,Anlagen!B13,"") | C13: =IF(Netz!C13=A13,COUNTIF(Netz!$C$5:$C$92,A13),"") | D13: =IF(Netz!C13=A13,SUMIF(Netz!$C$5:$C$92,A13,Anlagen!$F$5:$F$92),"") | E13: =IF(Netz!C13=A13,CEILING(D13/PG,1),"") | F13: =IF(Netz!C13=A13,D13/(E13*PG),"") | G13: =IF(Netz!C13=A13,Investition!E13+COUNTIF(Netz!$D$5:$D$92,A13),"") | H13: =IF(Netz!C13=A13,CEILING((E13+G13)/Ports_Agg,1),"") | I13: =IF(Netz!C13=A13,SUMIF(Netz!$C$5:$C$92,A13,Netz!$O$5:$O$92),"") | J13: =IF(Netz!C13=A13,I13*Bandbreite/Ueberbuchung,"") | K13: =IF(Netz!C13=A13,MAX(1,CEILING(J13/Uplink_Kap,1)),"") | L13: =IF(Netz!C13=A13,E13*(P_UCG+P_DAC)*EK,"") | M13: =IF(Netz!C13=A13,(P_KVz+P_USV+P_MontStandort+H13*P_Agg)*EK,"") | N13: =IF(Netz!C13=A13,L13+M13,"") | O13: =IF(Netz!C13=A13,(K13*Uplink_Monat*12+Strom_Standort+E13*Strom_GW)*EK+N13*Wartung,"") | P13: =IF(Netz!C13=A13,IF(E13>Max_GW,"Achtung: mehr als "&Max_GW&" Gateways",IF(K13>1,"OK – "&K13&" Internet-Anschlüsse nötig","OK")),"")
A14: =Anlagen!A14 -> 10 | B14: =IF(Netz!C14=A14,Anlagen!B14,"") | C14: =IF(Netz!C14=A14,COUNTIF(Netz!$C$5:$C$92,A14),"") | D14: =IF(Netz!C14=A14,SUMIF(Netz!$C$5:$C$92,A14,Anlagen!$F$5:$F$92),"") | E14: =IF(Netz!C14=A14,CEILING(D14/PG,1),"") | F14: =IF(Netz!C14=A14,D14/(E14*PG),"") | G14: =IF(Netz!C14=A14,Investition!E14+COUNTIF(Netz!$D$5:$D$92,A14),"") | H14: =IF(Netz!C14=A14,CEILING((E14+G14)/Ports_Agg,1),"") | I14: =IF(Netz!C14=A14,SUMIF(Netz!$C$5:$C$92,A14,Netz!$O$5:$O$92),"") | J14: =IF(Netz!C14=A14,I14*Bandbreite/Ueberbuchung,"") | K14: =IF(Netz!C14=A14,MAX(1,CEILING(J14/Uplink_Kap,1)),"") | L14: =IF(Netz!C14=A14,E14*(P_UCG+P_DAC)*EK,"") | M14: =IF(Netz!C14=A14,(P_KVz+P_USV+P_MontStandort+H14*P_Agg)*EK,"") | N14: =IF(Netz!C14=A14,L14+M14,"") | O14: =IF(Netz!C14=A14,(K14*Uplink_Monat*12+Strom_Standort+E14*Strom_GW)*EK+N14*Wartung,"") | P14: =IF(Netz!C14=A14,IF(E14>Max_GW,"Achtung: mehr als "&Max_GW&" Gateways",IF(K14>1,"OK – "&K14&" Internet-Anschlüsse nötig","OK")),"")
A15: =Anlagen!A15 -> 11 | B15: =IF(Netz!C15=A15,Anlagen!B15,"") | C15: =IF(Netz!C15=A15,COUNTIF(Netz!$C$5:$C$92,A15),"") | D15: =IF(Netz!C15=A15,SUMIF(Netz!$C$5:$C$92,A15,Anlagen!$F$5:$F$92),"") | E15: =IF(Netz!C15=A15,CEILING(D15/PG,1),"") | F15: =IF(Netz!C15=A15,D15/(E15*PG),"") | G15: =IF(Netz!C15=A15,Investition!E15+COUNTIF(Netz!$D$5:$D$92,A15),"") | H15: =IF(Netz!C15=A15,CEILING((E15+G15)/Ports_Agg,1),"") | I15: =IF(Netz!C15=A15,SUMIF(Netz!$C$5:$C$92,A15,Netz!$O$5:$O$92),"") | J15: =IF(Netz!C15=A15,I15*Bandbreite/Ueberbuchung,"") | K15: =IF(Netz!C15=A15,MAX(1,CEILING(J15/Uplink_Kap,1)),"") | L15: =IF(Netz!C15=A15,E15*(P_UCG+P_DAC)*EK,"") | M15: =IF(Netz!C15=A15,(P_KVz+P_USV+P_MontStandort+H15*P_Agg)*EK,"") | N15: =IF(Netz!C15=A15,L15+M15,"") | O15: =IF(Netz!C15=A15,(K15*Uplink_Monat*12+Strom_Standort+E15*Strom_GW)*EK+N15*Wartung,"") | P15: =IF(Netz!C15=A15,IF(E15>Max_GW,"Achtung: mehr als "&Max_GW&" Gateways",IF(K15>1,"OK – "&K15&" Internet-Anschlüsse nötig","OK")),"")
A16: =Anlagen!A16 -> 12 | B16: =IF(Netz!C16=A16,Anlagen!B16,"") | C16: =IF(Netz!C16=A16,COUNTIF(Netz!$C$5:$C$92,A16),"") | D16: =IF(Netz!C16=A16,SUMIF(Netz!$C$5:$C$92,A16,Anlagen!$F$5:$F$92),"") | E16: =IF(Netz!C16=A16,CEILING(D16/PG,1),"") | F16: =IF(Netz!C16=A16,D16/(E16*PG),"") | G16: =IF(Netz!C16=A16,Investition!E16+COUNTIF(Netz!$D$5:$D$92,A16),"") | H16: =IF(Netz!C16=A16,CEILING((E16+G16)/Ports_Agg,1),"") | I16: =IF(Netz!C16=A16,SUMIF(Netz!$C$5:$C$92,A16,Netz!$O$5:$O$92),"") | J16: =IF(Netz!C16=A16,I16*Bandbreite/Ueberbuchung,"") | K16: =IF(Netz!C16=A16,MAX(1,CEILING(J16/Uplink_Kap,1)),"") | L16: =IF(Netz!C16=A16,E16*(P_UCG+P_DAC)*EK,"") | M16: =IF(Netz!C16=A16,(P_KVz+P_USV+P_MontStandort+H16*P_Agg)*EK,"") | N16: =IF(Netz!C16=A16,L16+M16,"") | O16: =IF(Netz!C16=A16,(K16*Uplink_Monat*12+Strom_Standort+E16*Strom_GW)*EK+N16*Wartung,"") | P16: =IF(Netz!C16=A16,IF(E16>Max_GW,"Achtung: mehr als "&Max_GW&" Gateways",IF(K16>1,"OK – "&K16&" Internet-Anschlüsse nötig","OK")),"")
... A92: =Anlagen!A92 -> 88 | B92: =IF(Netz!C92=A92,Anlagen!B92,"") | C92: =IF(Netz!C92=A92,COUNTIF(Netz!$C$5:$C$92,A92),"") | D92: =IF(Netz!C92=A92,SUMIF(Netz!$C$5:$C$92,A92,Anlagen!$F$5:$F$92),"") | E92: =IF(Netz!C92=A92,CEILING(D92/PG,1),"") | F92: =IF(Netz!C92=A92,D92/(E92*PG),"") | G92: =IF(Netz!C92=A92,Investition!E92+COUNTIF(Netz!$D$5:$D$92,A92),"") | H92: =IF(Netz!C92=A92,CEILING((E92+G92)/Ports_Agg,1),"") | I92: =IF(Netz!C92=A92,SUMIF(Netz!$C$5:$C$92,A92,Netz!$O$5:$O$92),"") | J92: =IF(Netz!C92=A92,I92*Bandbreite/Ueberbuchung,"") | K92: =IF(Netz!C92=A92,MAX(1,CEILING(J92/Uplink_Kap,1)),"") | L92: =IF(Netz!C92=A92,E92*(P_UCG+P_DAC)*EK,"") | M92: =IF(Netz!C92=A92,(P_KVz+P_USV+P_MontStandort+H92*P_Agg)*EK,"") | N92: =IF(Netz!C92=A92,L92+M92,"") | O92: =IF(Netz!C92=A92,(K92*Uplink_Monat*12+Strom_Standort+E92*Strom_GW)*EK+N92*Wartung,"") | P92: =IF(Netz!C92=A92,IF(E92>Max_GW,"Achtung: mehr als "&Max_GW&" Gateways",IF(K92>1,"OK – "&K92&" Internet-Anschlüsse nötig","OK")),"")
B93: Summe | C93: =COUNTIF(Netz!E5:E92,"Gateway-Standort")+COUNTIF(Netz!E5:E92,"eigenständig") -> 16 | D93: =SUM(D5:D92) -> 5017 | E93: =SUM(E5:E92) -> 96 | I93: =SUM(I5:I92) -> 2814.8136 | K93: =SUM(K5:K92) -> 23 | L93: =SUM(L5:L92) -> 30844.8 | M93: =SUM(M5:M92) -> 52836 | N93: =SUM(N5:N92) -> 83680.8 | O93: =SUM(O5:O92) -> 31522.624

Sheet Ergebnis
A1: Ergebnis je Sparte (Standortkosten nach Parzellen verteilt)
A2: Umsatz = Kunden × Ø Tarifpreis · Deckungsbeitrag = Umsatz − laufende Kosten − Zahlungsabwicklung (vor zentralen Firmenkosten)
A4: Nr. | B4: Kleingartenanlage | C4: Entwicklungsstufe | D4: versorgt durch | E4: Parzellen | F4: Quote | G4: Kunden | H4: Umsatz / Jahr | I4: Anteil Standort | J4: Investition (inkl. Anteil Standort) | K4: laufende Kosten / Jahr | L4: Deckungsbeitrag / Jahr | M4: Amortisation (Jahre) | N4: Investition je Kunde
A5: =Anlagen!A5 -> 1 | B5: =Anlagen!B5 -> 1. März | C5: =Anlagen!D5 -> B – Beobachtung | D5: =Netz!N5 -> Fohrder Landstraße: GW 3 | E5: =Anlagen!F5 -> 30 | F5: =Buchungsquote!T5 -> 0.62363636 | G5: =Buchungsquote!V5 -> 18.709091 | H5: =G5*Preis_Jahr -> 2245.0909 | I5: =IFERROR(E5/INDEX(Standorte!$D$5:$D$92,MATCH(Netz!C5,Anlagen!$A$5:$A$92,0)),0) -> 0.058365759 | J5: =Investition!N5+I5*IFERROR(INDEX(Standorte!$N$5:$N$92,MATCH(Netz!C5,Anlagen!$A$5:$A$92,0)),0) -> 14158.269 | K5: =Investition!O5+I5*IFERROR(INDEX(Standorte!$O$5:$O$92,MATCH(Netz!C5,Anlagen!$A$5:$A$92,0)),0)+H5*Zahlung -> 818.54047 | L5: =H5-K5 -> 1426.5504 | M5: =IF(L5>0,J5/L5,"nie") -> 9.9248287 | N5: =IF(G5>0,J5/G5,0) -> 756.75877
A6: =Anlagen!A6 -> 2 | B6: =Anlagen!B6 -> Abendfrieden | C6: =Anlagen!D6 -> C – Qualifizierung | D6: =Netz!N6 -> Glück im Winkel: GW 3–4 | E6: =Anlagen!F6 -> 75 | F6: =Buchungsquote!T6 -> 0.53532971 | G6: =Buchungsquote!V6 -> 40.149728 | H6: =G6*Preis_Jahr -> 4817.9674 | I6: =IFERROR(E6/INDEX(Standorte!$D$5:$D$92,MATCH(Netz!C6,Anlagen!$A$5:$A$92,0)),0) -> 0.13888889 | J6: =Investition!N6+I6*IFERROR(INDEX(Standorte!$N$5:$N$92,MATCH(Netz!C6,Anlagen!$A$5:$A$92,0)),0) -> 24362.729 | K6: =Investition!O6+I6*IFERROR(INDEX(Standorte!$O$5:$O$92,MATCH(Netz!C6,Anlagen!$A$5:$A$92,0)),0)+H6*Zahlung -> 1524.9625 | L6: =H6-K6 -> 3293.0048 | M6: =IF(L6>0,J6/L6,"nie") -> 7.3983276 | N6: =IF(G6>0,J6/G6,0) -> 606.79685
A7: =Anlagen!A7 -> 3 | B7: =Anlagen!B7 -> Abendrot | C7: =Anlagen!D7 -> A – Stabil | D7: =Netz!N7 -> Feierabend: GW 4–6 | E7: =Anlagen!F7 -> 137 | F7: =Buchungsquote!T7 -> 0.56886465 | G7: =Buchungsquote!V7 -> 77.934457 | H7: =G7*Preis_Jahr -> 9352.1349 | I7: =IFERROR(E7/INDEX(Standorte!$D$5:$D$92,MATCH(Netz!C7,Anlagen!$A$5:$A$92,0)),0) -> 0.25091575 | J7: =Investition!N7+I7*IFERROR(INDEX(Standorte!$N$5:$N$92,MATCH(Netz!C7,Anlagen!$A$5:$A$92,0)),0) -> 43165.327 | K7: =Investition!O7+I7*IFERROR(INDEX(Standorte!$O$5:$O$92,MATCH(Netz!C7,Anlagen!$A$5:$A$92,0)),0)+H7*Zahlung -> 2747.02 | L7: =H7-K7 -> 6605.1149 | M7: =IF(L7>0,J7/L7,"nie") -> 6.5351364 | N7: =IF(G7>0,J7/G7,0) -> 553.86703
A8: =Anlagen!A8 -> 4 | B8: =Anlagen!B8 -> Abendruh | C8: =Anlagen!D8 -> A – Stabil | D8: =Netz!N8 -> Feierabend: GW 6–9 | E8: =Anlagen!F8 -> 142 | F8: =Buchungsquote!T8 -> 0.56023756 | G8: =Buchungsquote!V8 -> 79.553733 | H8: =G8*Preis_Jahr -> 9546.448 | I8: =IFERROR(E8/INDEX(Standorte!$D$5:$D$92,MATCH(Netz!C8,Anlagen!$A$5:$A$92,0)),0) -> 0.26007326 | J8: =Investition!N8+I8*IFERROR(INDEX(Standorte!$N$5:$N$92,MATCH(Netz!C8,Anlagen!$A$5:$A$92,0)),0) -> 44701.944 | K8: =Investition!O8+I8*IFERROR(INDEX(Standorte!$O$5:$O$92,MATCH(Netz!C8,Anlagen!$A$5:$A$92,0)),0)+H8*Zahlung -> 2881.6594 | L8: =H8-K8 -> 6664.7885 | M8: =IF(L8>0,J8/L8,"nie") -> 6.7071811 | N8: =IF(G8>0,J8/G8,0) -> 561.90881
A9: =Anlagen!A9 -> 5 | B9: =Anlagen!B9 -> Abendsonne | C9: =Anlagen!D9 -> A – Stabil | D9: =Netz!N9 -> Eigener Fleiß: GW 3–4 | E9: =Anlagen!F9 -> 67 | F9: =Buchungsquote!T9 -> 0.50373134 | G9: =Buchungsquote!V9 -> 33.75 | H9: =G9*Preis_Jahr -> 4050 | I9: =IFERROR(E9/INDEX(Standorte!$D$5:$D$92,MATCH(Netz!C9,Anlagen!$A$5:$A$92,0)),0) -> 0.12271062 | J9: =Investition!N9+I9*IFERROR(INDEX(Standorte!$N$5:$N$92,MATCH(Netz!C9,Anlagen!$A$5:$A$92,0)),0) -> 22005.842 | K9: =Investition!O9+I9*IFERROR(INDEX(Standorte!$O$5:$O$92,MATCH(Netz!C9,Anlagen!$A$5:$A$92,0)),0)+H9*Zahlung -> 1390.2099 | L9: =H9-K9 -> 2659.7901 | M9: =IF(L9>0,J9/L9,"nie") -> 8.2735257 | N9: =IF(G9>0,J9/G9,0) -> 652.02494
A10: =Anlagen!A10 -> 6 | B10: =Anlagen!B10 -> Altstadt Forst | C10: =Anlagen!D10 -> A – Stabil | D10: =Netz!N10 -> Fohrder Landstraße: GW 3–5 | E10: =Anlagen!F10 -> 88 | F10: =Buchungsquote!T10 -> 0.56023756 | G10: =Buchungsquote!V10 -> 49.300905 | H10: =G10*Preis_Jahr -> 5916.1086 | I10: =IFERROR(E10/INDEX(Standorte!$D$5:$D$92,MATCH(Netz!C10,Anlagen!$A$5:$A$92,0)),0) -> 0.17120623 | J10: =Investition!N10+I10*IFERROR(INDEX(Standorte!$N$5:$N$92,MATCH(Netz!C10,Anlagen!$A$5:$A$92,0)),0) -> 28624.501 | K10: =Investition!O10+I10*IFERROR(INDEX(Standorte!$O$5:$O$92,MATCH(Netz!C10,Anlagen!$A$5:$A$92,0)),0)+H10*Zahlung -> 1827.1747 | L10: =H10-K10 -> 4088.9339 | M10: =IF(L10>0,J10/L10,"nie") -> 7.0004801 | N10: =IF(G10>0,J10/G10,0) -> 580.60802
A11: =Anlagen!A11 -> 7 | B11: =Anlagen!B11 -> Am Beetzseeufer | C11: =Anlagen!D11 -> A – Stabil | D11: =Netz!N11 -> Helgoland: GW 3–4 | E11: =Anlagen!F11 -> 77 | F11: =Buchungsquote!T11 -> 0.63290378 | G11: =Buchungsquote!V11 -> 48.733591 | H11: =G11*Preis_Jahr -> 5848.0309 | I11: =IFERROR(E11/INDEX(Standorte!$D$5:$D$92,MATCH(Netz!C11,Anlagen!$A$5:$A$92,0)),0) -> 0.14025501 | J11: =Investition!N11+I11*IFERROR(INDEX(Standorte!$N$5:$N$92,MATCH(Netz!C11,Anlagen!$A$5:$A$92,0)),0) -> 25858.645 | K11: =Investition!O11+I11*IFERROR(INDEX(Standorte!$O$5:$O$92,MATCH(Netz!C11,Anlagen!$A$5:$A$92,0)),0)+H11*Zahlung -> 1604.2047 | L11: =H11-K11 -> 4243.8263 | M11: =IF(L11>0,J11/L11,"nie") -> 6.0932385 | N11: =IF(G11>0,J11/G11,0) -> 530.61235
A12: =Anlagen!A12 -> 8 | B12: =Anlagen!B12 -> Am Büttelhandfassgraben | C12: =Anlagen!D12 -> B – Beobachtung | D12: =Netz!N12 -> Helgoland: GW 4 | E12: =Anlagen!F12 -> 5 | F12: =Buchungsquote!T12 -> 0.67857143 | G12: =Buchungsquote!V12 -> 3.3928571 | H12: =G12*Preis_Jahr -> 407.14286 | I12: =IFERROR(E12/INDEX(Standorte!$D$5:$D$92,MATCH(Netz!C12,Anlagen!$A$5:$A$92,0)),0) -> 0.0091074681 | J12: =Investition!N12+I12*IFERROR(INDEX(Standorte!$N$5:$N$92,MATCH(Netz!C12,Anlagen!$A$5:$A$92,0)),0) -> 4222.1605 | K12: =Investition!O12+I12*IFERROR(INDEX(Standorte!$O$5:$O$92,MATCH(Netz!C12,Anlagen!$A$5:$A$92,0)),0)+H12*Zahlung -> 221.4638 | L12: =H12-K12 -> 185.67906 | M12: =IF(L12>0,J12/L12,"nie") -> 22.739024 | N12: =IF(G12>0,J12/G12,0) -> 1244.4263
A13: =Anlagen!A13 -> 9 | B13: =Anlagen!B13 -> Am Eichenweg | C13: =Anlagen!D13 -> C – Qualifizierung | D13: =Netz!N13 -> Birkenwäldchen: GW 2 | E13: =Anlagen!F13 -> 54 | F13: =Buchungsquote!T13 -> 0.55873333 | G13: =Buchungsquote!V13 -> 30.1716 | H13: =G13*Preis_Jahr -> 3620.592 | I13: =IFERROR(E13/INDEX(Standorte!$D$5:$D$92,MATCH(Netz!C13,Anlagen!$A$5:$A$92,0)),0) -> 0.099447514 | J13: =Investition!N13+I13*IFERROR(INDEX(Standorte!$N$5:$N$92,MATCH(Netz!C13,Anlagen!$A$5:$A$92,0)),0) -> 21023.189 | K13: =Investition!O13+I13*IFERROR(INDEX(Standorte!$O$5:$O$92,MATCH(Netz!C13,Anlagen!$A$5:$A$92,0)),0)+H13*Zahlung -> 1229.383 | L13: =H13-K13 -> 2391.209 | M13: =IF(L13>0,J13/L13,"nie") -> 8.7918662 | N13: =IF(G13>0,J13/G13,0) -> 696.78735
A14: =Anlagen!A14 -> 10 | B14: =Anlagen!B14 -> Am Jakobsgraben | C14: =Anlagen!D14 -> D – Planungskonflikt | D14: =Netz!N14 -> Birkenwäldchen: GW 3 | E14: =Anlagen!F14 -> 41 | F14: =Buchungsquote!T14 -> 0.45456587 | G14: =Buchungsquote!V14 -> 18.637201 | H14: =G14*Preis_Jahr -> 2236.4641 | I14: =IFERROR(E14/INDEX(Standorte!$D$5:$D$92,MATCH(Netz!C14,Anlagen!$A$5:$A$92,0)),0) -> 0.075506446 | J14: =Investition!N14+I14*IFERROR(INDEX(Standorte!$N$5:$N$92,MATCH(Netz!C14,Anlagen!$A$5:$A$92,0)),0) -> 17205.706 | K14: =Investition!O14+I14*IFERROR(INDEX(Standorte!$O$5:$O$92,MATCH(Netz!C14,Anlagen!$A$5:$A$92,0)),0)+H14*Zahlung -> 953.15128 | L14: =H14-K14 -> 1283.3128 | M14: =IF(L14>0,J14/L14,"nie") -> 13.407258 | N14: =IF(G14>0,J14/G14,0) -> 923.19153
A15: =Anlagen!A15 -> 11 | B15: =Anlagen!B15 -> Am Schafdamm | C15: =Anlagen!D15 -> C – Qualifizierung | D15: =Netz!N15 -> Fohrder Landstraße: GW 5 | E15: =Anlagen!F15 -> 10 | F15: =Buchungsquote!T15 -> 0.46230769 | G15: =Buchungsquote!V15 -> 4.6230769 | H15: =G15*Preis_Jahr -> 554.76923 | I15: =IFERROR(E15/INDEX(Standorte!$D$5:$D$92,MATCH(Netz!C15,Anlagen!$A$5:$A$92,0)),0) -> 0.019455253 | J15: =Investition!N15+I15*IFERROR(INDEX(Standorte!$N$5:$N$92,MATCH(Netz!C15,Anlagen!$A$5:$A$92,0)),0) -> 6361.6591 | K15: =Investition!O15+I15*IFERROR(INDEX(Standorte!$O$5:$O$92,MATCH(Netz!C15,Anlagen!$A$5:$A$92,0)),0)+H15*Zahlung -> 316.30608 | L15: =H15-K15 -> 238.46315 | M15: =IF(L15>0,J15/L15,"nie") -> 26.677745 | N15: =IF(G15>0,J15/G15,0) -> 1376.066
A16: =Anlagen!A16 -> 12 | B16: =Anlagen!B16 -> Am Schlangenpfad | C16: =Anlagen!D16 -> C – Qualifizierung | D16: =Netz!N16 -> Fohrder Landstraße: GW 5 | E16: =Anlagen!F16 -> 19 | F16: =Buchungsquote!T16 -> 0.42913793 | G16: =Buchungsquote!V16 -> 8.1536207 | H16: =G16*Preis_Jahr -> 978.43448 | I16: =IFERROR(E16/INDEX(Standorte!$D$5:$D$92,MATCH(Netz!C16,Anlagen!$A$5:$A$92,0)),0) -> 0.036964981 | J16: =Investition!N16+I16*IFERROR(INDEX(Standorte!$N$5:$N$92,MATCH(Netz!C16,Anlagen!$A$5:$A$92,0)),0) -> 9322.2765 | K16: =Investition!O16+I16*IFERROR(INDEX(Standorte!$O$5:$O$92,MATCH(Netz!C16,Anlagen!$A$5:$A$92,0)),0)+H16*Zahlung -> 521.71646 | L16: =H16-K16 -> 456.71802 | M16: =IF(L16>0,J16/L16,"nie") -> 20.411449 | N16: =IF(G16>0,J16/G16,0) -> 1143.3297
... A92: =Anlagen!A92 -> 88 | B92: =Anlagen!B92 -> Zur Insel | C92: =Anlagen!D92 -> A – Stabil | D92: =Netz!N92 -> Helgoland: GW 9–10 | E92: =Anlagen!F92 -> 86 | F92: =Buchungsquote!T92 -> 0.56248799 | G92: =Buchungsquote!V92 -> 48.373967 | H92: =G92*Preis_Jahr -> 5804.8761 | I92: =IFERROR(E92/INDEX(Standorte!$D$5:$D$92,MATCH(Netz!C92,Anlagen!$A$5:$A$92,0)),0) -> 0.15664845 | J92: =Investition!N92+I92*IFERROR(INDEX(Standorte!$N$5:$N$92,MATCH(Netz!C92,Anlagen!$A$5:$A$92,0)),0) -> 29993.01 | K92: =Investition!O92+I92*IFERROR(INDEX(Standorte!$O$5:$O$92,MATCH(Netz!C92,Anlagen!$A$5:$A$92,0)),0)+H92*Zahlung -> 1827.9934 | L92: =H92-K92 -> 3976.8827 | M92: =IF(L92>0,J92/L92,"nie") -> 7.5418392 | N92: =IF(G92>0,J92/G92,0) -> 620.02377
B93: Summe | E93: =SUM(E5:E92) -> 5017 | F93: =G93/E93 -> 0.56105513 | G93: =SUM(G5:G92) -> 2814.8136 | H93: =SUM(H5:H92) -> 337777.63 | J93: =SUM(J5:J92) -> 1768027.3 | K93: =SUM(K5:K92) -> 114379.85 | L93: =SUM(L5:L92) -> 223397.79 | M93: =IF(L93>0,J93/L93,"nie") -> 7.9142561 | N93: =J93/G93 -> 628.11522
